Workbook

Sheet Arvind
A1: Simulations | B1: count | C1: 5000
A2: Period 2024 | B2: Days | C2: 365
A3: Non Stochastic Drivers
A4: Refining Throughput Volume | B4: k BPD | C4: 2922
A5: Ref. Operating Expenses (excl. D&A) | B5: $ Millions | C5: 1307
A6: Ref. D&A Expense | B6: $ Millions | C6: 707
A7: Renewable Diesel Sales Volume | B7: k BPD | C7: 2732
A8: RD Operating Expenses (excl. D&A) | B8: $ Millions | C8: 72 | I8: Driver | J8: ULS Spread | K8: CBOB Spread | L8: RD Feed (UCO) | M8: RD RIN | N8: Eth. Feed (Corn) | O8: Eth. Price (Ethanol)
A9: RD D&A Expense | B9: $ Millions | C9: 61 | I9: 1. Ref. Spread ULS | J9: 1 | K9: 0.9 | L9: 0.15 | M9: 0.1 | N9: -0.1 | O9: 0.05
A10: Ethanol Production Volume | B10: k BPD | C10: 4583 | I10: 2. Ref. Spread CBOB | J10: 0.9 | K10: 1 | L10: 0.1 | M10: 0.05 | N10: -0.05 | O10: 0.1
A11: Eth. Operating Expenses (excl. D&A | B11: $ Millions | C11: 144 | I11: 3. RD Feed (UCO) | J11: 0.15 | K11: 0.1 | L11: 1 | M11: 0.5 | N11: 0.35 | O11: 0.25
A12: Eth. D&A Expense | C12: 19 | I12: 4. RD RIN | J12: 0.1 | K12: 0.05 | L12: 0.5 | M12: 1 | N12: 0.3 | O12: 0.4
A13: Stochastic Drivers | C13: Mean | D13: ST. Dev | I13: 5. Eth. Feed (Corn) | J13: -0.1 | K13: -0.05 | L13: 0.35 | M13: 0.3 | N13: 1 | O13: 0.8
A14: Ref. Spread ULS Diesel less WTI | B14: $/bbl | C14: 20.6 | D14: 4.12 | I14: 6. Eth. Price (Ethanol) | J14: 0.05 | K14: 0.1 | L14: 0.25 | M14: 0.4 | N14: 0.8 | O14: 1
A15: Ref. Spread CBOB Gas less WTI | B15: $/bbl | C15: 14.91 | D15: 2.98
A16: RD Feedstock Cost (USGC UCO) | B16: $/lb | C16: 0.56 | D16: 0.11 | T16: SUMMARY OUTPUT
A17: RD Reg. Price (Biodiesel RIN) | B17: $/RIN | C17: 1.09 | D17: 0.22
A18: Eth. Feedstock Cost (CBOT Corn) | B18: $/bushel | C18: 4.52 | D18: 0.9 | T18: Regression Statistics
A19: Eth. Product Price (NY Harbor Ethanol) | B19: $/gallon | C19: 1.84 | D19: 0.37 | T19: Multiple R | U19: 1
A20: Results For Adjusted Operating Income | T20: R Square | U20: 1
A21: Average | B21: $ Millions | D21: =AVERAGE(R28:R5027) -> 66845427 | T21: Adjusted R Square | U21: 1
A22: Standard Deviation | B22: $ Millions | D22: =STDEV(R28:R5027) -> 13895465 | T22: Standard Error | U22: 6.91271e-09
A23: Median | B23: $ Millions | D23: =MEDIAN(R28:R5027) -> 66822397 | T23: Observations | U23: 5000
A24: Worst 5% (Var 95%) | B24: $ Millions | D24: =_xlfn.PERCENTILE.EXC(R28:R5027,0.05) -> 44080809
A25: Best 5% | B25: $ Millions | D25: =_xlfn.PERCENTILE.EXC(R29:R5028,0.95) -> 88826571 | T25: ANOVA
U26: df | V26: SS | W26: MS | X26: F | Y26: Significance F
C27: Z1 value | D27: Z2 value | E27: Z3 value | F27: Z4 value | G27: Z5 value | H27: Z6 value | I27: ULS Diesel less WTI | J27: Spread CBOB Gas less WTI | K27: RD Feedstock Cost (USGC UCO) | L27: RD Reg. Price (Biodiesel RIN) | M27: Eth. Feedstock Cost (CBOT Corn) | N27: Eth. Product Price (NY Harbor Ethanol) | O27: Refining Operating Income | P27: RD Operating Income | Q27: Ethanol Operating Income | R27: Total Adjusted Operating Income | T27: Regression | U27: 6 | V27: 6.82794e+16 | W27: 1.14e+16 | X27: 2.38e+32 | Y27: 0 | AD27: Y1 | AE27: Y2 | AF27: Y3 | AG27: Y4 | AH27: Y5 | AI27: Y6
C28: {=_xlfn.NORM.S.INV(_xlfn.RANDARRAY(5000))} -> -2.138727 | D28: {=_xlfn.NORM.S.INV(_xlfn.RANDARRAY(5000))} -> -1.0511294 | E28: {=_xlfn.NORM.S.INV(_xlfn.RANDARRAY(5000))} -> -1.2589502 | F28: {=_xlfn.NORM.S.INV(_xlfn.RANDARRAY(5000))} -> -2.2234653 | G28: {=_xlfn.NORM.S.INV(_xlfn.RANDARRAY(5000))} -> 1.8836262 | H28: {=_xlfn.NORM.S.INV(_xlfn.RANDARRAY(5000))} -> 0.86625034 | I28: =$C$14+AD28*$D$14 -> 5.5991518 | J28: =$C$15+AE28*$D$15 -> 5.3125875 | K28: =$C$16+AF28*$D$16 -> 1100000.4 | L28: =$C$17+AG28*$D$17 -> 0.60428806 | M28: =$C$18+AH28*$D$18 -> 6.0818451 | N28: =$C$19+AI28*$D$19 -> 2.194082 | O28: =(I28+J28)/2*$C$4*365-$C$5-$C$6 -> 5816834.6 | P28: =(L28/1.7*42+I28)*$C$7*365-$C$8-$C$9 -> 20470598 | Q28: =(N28-M28/2.8)*$C$10*365-$C$11-$C$12 -> 36629.189 | R28: =O28+P28+Q28 -> 26324062 | T28: Residual | U28: 4993 | V28: 2.38594e-13 | W28: 4.78e-17 | AD28: =SUMPRODUCT(C28:H28,$J$9:$O$9) -> -3.6409826 | AE28: =SUMPRODUCT(C28:H28,$J$10:$O$10) -> -3.2206082 | AF28: 9999999 | AG28: =SUMPRODUCT(C28:H28,$J$12:$O$12) -> -2.2077816 | AH28: =SUMPRODUCT(C28:H28,$J$13:$O$13) -> 1.7353835 | AI28: =SUMPRODUCT(C28:H28,$J$14:$O$14) -> 0.95697834
C29: 0.68932027 | D29: -1.8514305 | E29: -0.0008968515 | F29: 0.1227327 | G29: -0.74645462 | H29: 0.9213479 | I29: =$C$14+AD29*$D$14 -> 17.122244 | J29: =$C$15+AE29*$D$15 -> 11.645297 | K29: =$C$16+AF29*$D$16 -> 0.55425826 | L29: =$C$17+AG29*$D$17 -> 1.1435145 | M29: =$C$18+AH29*$D$18 -> 4.5656922 | N29: =$C$19+AI29*$D$19 -> 1.9222791 | O29: =(I29+J29)/2*$C$4*365-$C$5-$C$6 -> 15338709 | P29: =(L29/1.7*42+I29)*$C$7*365-$C$8-$C$9 -> 45245691 | Q29: =(N29-M29/2.8)*$C$10*365-$C$11-$C$12 -> 487749.11 | R29: =O29+P29+Q29 -> 61072149 | T29: Total | U29: 4999 | V29: 6.82794e+16 | AD29: =SUMPRODUCT(C29:H29,$J$9:$O$9) -> -0.84411557 | AE29: =SUMPRODUCT(C29:H29,$J$10:$O$10) -> -1.0955378 | AF29: =SUMPRODUCT(C29:H29,$J$11:$O$11) -> -0.052197654 | AG29: =SUMPRODUCT(C29:H29,$J$12:$O$12) -> 0.24324755 | AH29: =SUMPRODUCT(C29:H29,$J$13:$O$13) -> 0.050769108 | AI29: =SUMPRODUCT(C29:H29,$J$14:$O$14) -> 0.22237603
C30: 1.2938344 | D30: -0.21183807 | E30: -0.92371424 | F30: 0.55699845 | G30: -1.6485307 | H30: 0.47214063 | I30: =$C$14+AD30*$D$14 -> 25.580186 | J30: =$C$15+AE30*$D$15 -> 17.942841 | K30: =$C$16+AF30*$D$16 -> 0.45755983 | L30: =$C$17+AG30*$D$17 -> 1.0698106 | M30: =$C$18+AH30*$D$18 -> 3.1287709 | N30: =$C$19+AI30*$D$19 -> 1.5398171 | O30: =(I30+J30)/2*$C$4*365-$C$5-$C$6 -> 23207293 | P30: =(L30/1.7*42+I30)*$C$7*365-$C$8-$C$9 -> 51863997 | Q30: =(N30-M30/2.8)*$C$10*365-$C$11-$C$12 -> 706423.8 | R30: =O30+P30+Q30 -> 75777713 | AD30: =SUMPRODUCT(C30:H30,$J$9:$O$9) -> 1.2087829 | AE30: =SUMPRODUCT(C30:H30,$J$10:$O$10) -> 1.017732 | AF30: =SUMPRODUCT(C30:H30,$J$11:$O$11) -> -0.93127424 | AG30: =SUMPRODUCT(C30:H30,$J$12:$O$12) -> -0.091770086 | AH30: =SUMPRODUCT(C30:H30,$J$13:$O$13) -> -1.5458101 | AI30: =SUMPRODUCT(C30:H30,$J$14:$O$14) -> -0.81130516
C31: 0.72282977 | D31: 0.26852996 | E31: 0.89375877 | F31: -0.49698641 | G31: -0.51830656 | H31: 1.6785786 | I31: =$C$14+AD31*$D$14 -> 25.480682 | J31: =$C$15+AE31*$D$15 -> 18.418582 | K31: =$C$16+AF31*$D$16 -> 0.67206584 | L31: =$C$17+AG31*$D$17 -> 1.2113392 | M31: =$C$18+AH31*$D$18 -> 5.3323098 | N31: =$C$19+AI31*$D$19 -> 2.340082 | O31: =(I31+J31)/2*$C$4*365-$C$5-$C$6 -> 23407927 | P31: =(L31/1.7*42+I31)*$C$7*365-$C$8-$C$9 -> 55251503 | Q31: =(N31-M31/2.8)*$C$10*365-$C$11-$C$12 -> 728649.73 | R31: =O31+P31+Q31 -> 79388079 | U31: Coefficients | V31: Standard Error | W31: t Stat | X31: P-value | Y31: Lower 95% | Z31: Upper 95% | AA31: Lower 95.0% | AB31: Upper 95.0% | AD31: =SUMPRODUCT(C31:H31,$J$9:$O$9) -> 1.1846315 | AE31: =SUMPRODUCT(C31:H31,$J$10:$O$10) -> 1.1773765 | AF31: =SUMPRODUCT(C31:H31,$J$11:$O$11) -> 1.0187804 | AG31: =SUMPRODUCT(C31:H31,$J$12:$O$12) -> 0.55154192 | AH31: =SUMPRODUCT(C31:H31,$J$13:$O$13) -> 0.90256648 | AI31: =SUMPRODUCT(C31:H31,$J$14:$O$14) -> 1.351573
C32: -0.68597854 | D32: 1.2521731 | E32: 1.1923436 | F32: -0.20545646 | G32: 0.021195703 | H32: 1.4250897 | I32: =$C$14+AD32*$D$14 -> 23.353882 | J32: =$C$15+AE32*$D$15 -> 17.547905 | K32: =$C$16+AF32*$D$16 -> 0.72231895 | L32: =$C$17+AG32*$D$17 -> 1.3014466 | M32: =$C$18+AH32*$D$18 -> 5.890646 | N32: =$C$19+AI32*$D$19 -> 2.4870812 | O32: =(I32+J32)/2*$C$4*365-$C$5-$C$6 -> 21809478 | P32: =(L32/1.7*42+I32)*$C$7*365-$C$8-$C$9 -> 55350604 | Q32: =(N32-M32/2.8)*$C$10*365-$C$11-$C$12 -> 640984.21 | R32: =O32+P32+Q32 -> 77801066 | T32: Intercept | U32: -2014 | V32: 1.20949e-09 | W32: -1700000000000 | X32: 0 | Y32: -2014 | Z32: -2014 | AA32: -2014 | AB32: -2014 | AD32: =SUMPRODUCT(C32:H32,$J$9:$O$9) -> 0.66841804 | AE32: =SUMPRODUCT(C32:H32,$J$10:$O$10) -> 0.88520311 | AF32: =SUMPRODUCT(C32:H32,$J$11:$O$11) -> 1.4756268 | AG32: =SUMPRODUCT(C32:H32,$J$12:$O$12) -> 0.96112074 | AH32: =SUMPRODUCT(C32:H32,$J$13:$O$13) -> 1.52294 | AI32: =SUMPRODUCT(C32:H32,$J$14:$O$14) -> 1.748868
C33: -0.64743937 | D33: 0.40172931 | E33: -0.22684791 | F33: 0.12553865 | G33: 1.0249222 | H33: 1.8303847 | I33: =$C$14+AD33*$D$14 -> 19.288483 | J33: =$C$15+AE33*$D$15 -> 14.714567 | K33: =$C$16+AF33*$D$16 -> 0.62548271 | L33: =$C$17+AG33*$D$17 -> 1.3115593 | M33: =$C$18+AH33*$D$18 -> 6.7629371 | N33: =$C$19+AI33*$D$19 -> 2.821102 | O33: =(I33+J33)/2*$C$4*365-$C$5-$C$6 -> 18130622 | P33: =(L33/1.7*42+I33)*$C$7*365-$C$8-$C$9 -> 51545810 | Q33: =(N33-M33/2.8)*$C$10*365-$C$11-$C$12 -> 678602.51 | R33: =O33+P33+Q33 -> 70355035 | T33: X Variable 1 | U33: 533265 | V33: 2.40354e-11 | W33: 2.22e+16 | X33: 0 | Y33: 533265 | Z33: 533265 | AA33: 533265 | AB33: 533265 | AD33: =SUMPRODUCT(C33:H33,$J$9:$O$9) -> -0.3183293 | AE33: =SUMPRODUCT(C33:H33,$J$10:$O$10) -> -0.065581622 | AF33: =SUMPRODUCT(C33:H33,$J$11:$O$11) -> 0.59529739 | AG33: =SUMPRODUCT(C33:H33,$J$12:$O$12) -> 1.0070878 | AH33: =SUMPRODUCT(C33:H33,$J$13:$O$13) -> 2.4921523 | AI33: =SUMPRODUCT(C33:H33,$J$14:$O$14) -> 2.6516269
C34: -0.30091092 | D34: -0.088567651 | E34: 0.34709085 | F34: -0.42782958 | G34: 2.9338752 | H34: -1.4309075 | I34: =$C$14+AD34*$D$14 -> 17.566551 | J34: =$C$15+AE34*$D$15 -> 13.015154 | K34: =$C$16+AF34*$D$16 -> 0.64231433 | L34: =$C$17+AG34*$D$17 -> 1.0941791 | M34: =$C$18+AH34*$D$18 -> 6.1551214 | N34: =$C$19+AI34*$D$19 -> 2.1389346 | O34: =(I34+J34)/2*$C$4*365-$C$5-$C$6 -> 16306139 | P34: =(L34/1.7*42+I34)*$C$7*365-$C$8-$C$9 -> 44473308 | Q34: =(N34-M34/2.8)*$C$10*365-$C$11-$C$12 -> -99398.387 | R34: =O34+P34+Q34 -> 60680049 | T34: X Variable 2 | U34: 533265 | V34: 3.94736e-11 | W34: 1.35e+16 | X34: 0 | Y34: 533265 | Z34: 533265 | AA34: 533265 | AB34: 533265 | AD34: =SUMPRODUCT(C34:H34,$J$9:$O$9) -> -0.73627403 | AE34: =SUMPRODUCT(C34:H34,$J$10:$O$10) -> -0.63585438 | AF34: =SUMPRODUCT(C34:H34,$J$11:$O$11) -> 0.74831211 | AG34: =SUMPRODUCT(C34:H34,$J$12:$O$12) -> 0.018995939 | AH34: =SUMPRODUCT(C34:H34,$J$13:$O$13) -> 1.8168016 | AI34: =SUMPRODUCT(C34:H34,$J$14:$O$14) -> 0.80793124
C35: -0.74269291 | D35: 1.0763432 | E35: -1.3052344 | F35: -1.7376548 | G35: 0.61786484 | H35: 0.090134483 | I35: =$C$14+AD35*$D$14 -> 19.772645 | J35: =$C$15+AE35*$D$15 -> 15.412528 | K35: =$C$16+AF35*$D$16 -> 0.34670504 | L35: =$C$17+AG35*$D$17 -> 0.60835161 | M35: =$C$18+AH35*$D$18 -> 4.2790665 | N35: =$C$19+AI35*$D$19 -> 1.7044155 | O35: =(I35+J35)/2*$C$4*365-$C$5-$C$6 -> 18761007 | P35: =(L35/1.7*42+I35)*$C$7*365-$C$8-$C$9 -> 34704232 | Q35: =(N35-M35/2.8)*$C$10*365-$C$11-$C$12 -> 294545.86 | R35: =O35+P35+Q35 -> 53759785 | T35: X Variable 3 | U35: 1.73225e-10 | V35: 9.02135e-10 | W35: 0.192017 | X35: 0.847737 | Y35: -1.59535e-09 | Z35: 1.94e-09 | AA35: -1.6e-09 | AB35: 1.94e-09 | AD35: =SUMPRODUCT(C35:H35,$J$9:$O$9) -> -0.20081443 | AE35: =SUMPRODUCT(C35:H35,$J$10:$O$10) -> 0.16863361 | AF35: =SUMPRODUCT(C35:H35,$J$11:$O$11) -> -1.9390451 | AG35: =SUMPRODUCT(C35:H35,$J$12:$O$12) -> -2.1893109 | AH35: =SUMPRODUCT(C35:H35,$J$13:$O$13) -> -0.26770391 | AI35: =SUMPRODUCT(C35:H35,$J$14:$O$14) -> -0.36644448
C36: 0.72235041 | D36: 0.80700173 | E36: 1.3461984 | F36: -1.1130191 | G36: 0.73485182 | H36: -1.9023263 | I36: =$C$14+AD36*$D$14 -> 26.247195 | J36: =$C$15+AE36*$D$15 -> 18.81115 | K36: =$C$16+AF36*$D$16 -> 0.6436394 | L36: =$C$17+AG36*$D$17 -> 0.89908186 | M36: =$C$18+AH36*$D$18 -> 3.8339024 | N36: =$C$19+AI36*$D$19 -> 1.3566745 | O36: =(I36+J36)/2*$C$4*365-$C$5-$C$6 -> 24026024 | P36: =(L36/1.7*42+I36)*$C$7*365-$C$8-$C$9 -> 48323016 | Q36: =(N36-M36/2.8)*$C$10*365-$C$11-$C$12 -> -21200.713 | R36: =O36+P36+Q36 -> 72327839 | T36: X Variable 4 | U36: -4.63704e-10 | V36: 4.43929e-10 | W36: -1.04455 | X36: 0.296284 | Y36: -1.334e-09 | Z36: 4.07e-10 | AA36: -1.3e-09 | AB36: 4.07e-10 | AD36: =SUMPRODUCT(C36:H36,$J$9:$O$9) -> 1.3706783 | AE36: =SUMPRODUCT(C36:H36,$J$10:$O$10) -> 1.3091108 | AF36: =SUMPRODUCT(C36:H36,$J$11:$O$11) -> 0.76035814 | AG36: =SUMPRODUCT(C36:H36,$J$12:$O$12) -> -0.86780973 | AH36: =SUMPRODUCT(C36:H36,$J$13:$O$13) -> -0.76233063 | AI36: =SUMPRODUCT(C36:H36,$J$14:$O$14) -> -1.3062852
C37: 0.8872776 | D37: -0.46676485 | E37: 0.58832529 | F37: 0.48688083 | G37: 1.7839988 | H37: -0.39375817 | I37: =$C$14+AD37*$D$14 -> 22.272878 | J37: =$C$15+AE37*$D$15 -> 15.76343 | K37: =$C$16+AF37*$D$16 -> 0.7188555 | L37: =$C$17+AG37*$D$17 -> 1.3593085 | M37: =$C$18+AH37*$D$18 -> 6.1000228 | N37: =$C$19+AI37*$D$19 -> 2.3479959 | O37: =(I37+J37)/2*$C$4*365-$C$5-$C$6 -> 20281418 | P37: =(L37/1.7*42+I37)*$C$7*365-$C$8-$C$9 -> 55698146 | Q37: =(N37-M37/2.8)*$C$10*365-$C$11-$C$12 -> 283235.83 | R37: =O37+P37+Q37 -> 76262800 | T37: X Variable 5 | U37: -2.90703e-10 | V37: 1.10024e-10 | W37: -2.64218 | X37: 0.008263 | Y37: -5.06398e-10 | Z37: -7.5e-11 | AA37: -5.1e-10 | AB37: -7.5e-11 | AD37: =SUMPRODUCT(C37:H37,$J$9:$O$9) -> 0.40603833 | AE37: =SUMPRODUCT(C37:H37,$J$10:$O$10) -> 0.28638581 | AF37: =SUMPRODUCT(C37:H37,$J$11:$O$11) -> 1.4441409 | AG37: =SUMPRODUCT(C37:H37,$J$12:$O$12) -> 1.2241294 | AH37: =SUMPRODUCT(C37:H37,$J$13:$O$13) -> 1.7555808 | AI37: =SUMPRODUCT(C37:H37,$J$14:$O$14) -> 1.3729619
C38: -0.43700989 | D38: 0.63589552 | E38: -0.34640669 | F38: -0.5628743 | G38: -1.9273651 | H38: 0.58705271 | I38: =$C$14+AD38*$D$14 -> 21.626444 | J38: =$C$15+AE38*$D$15 -> 15.90793 | K38: =$C$16+AF38*$D$16 -> 0.43266176 | L38: =$C$17+AG38*$D$17 -> 0.8498981 | M38: =$C$18+AH38*$D$18 -> 2.9576708 | N38: =$C$19+AI38*$D$19 -> 1.3868049 | O38: =(I38+J38)/2*$C$4*365-$C$5-$C$6 -> 20013754 | P38: =(L38/1.7*42+I38)*$C$7*365-$C$8-$C$9 -> 42503593 | Q38: =(N38-M38/2.8)*$C$10*365-$C$11-$C$12 -> 552685.5 | R38: =O38+P38+Q38 -> 63070033 | T38: X Variable 6 | U38: -2.76609e-10 | V38: 2.59822e-10 | W38: -1.06461 | X38: 0.287105 | Y38: -7.85975e-10 | Z38: 2.33e-10 | AA38: -7.9e-10 | AB38: 2.33e-10 | AD38: =SUMPRODUCT(C38:H38,$J$9:$O$9) -> 0.24913678 | AE38: =SUMPRODUCT(C38:H38,$J$10:$O$10) -> 0.33487575 | AF38: =SUMPRODUCT(C38:H38,$J$11:$O$11) -> -1.1576204 | AG38: =SUMPRODUCT(C38:H38,$J$12:$O$12) -> -1.0913723 | AH38: =SUMPRODUCT(C38:H38,$J$13:$O$13) -> -1.7359213 | AI38: =SUMPRODUCT(C38:H38,$J$14:$O$14) -> -1.2248517
C39: -0.46840615 | D39: -1.3286987 | E39: 0.41726286 | F39: 0.68289202 | G39: -1.263852 | H39: -0.23619819 | I39: =$C$14+AD39*$D$14 -> 14.754622 | J39: =$C$15+AE39*$D$15 -> 10.038235 | K39: =$C$16+AF39*$D$16 -> 0.56595984 | L39: =$C$17+AG39*$D$17 -> 1.1570149 | M39: =$C$18+AH39*$D$18 -> 3.6302372 | N39: =$C$19+AI39*$D$19 -> 1.460344 | O39: =(I39+J39)/2*$C$4*365-$C$5-$C$6 -> 13219149 | P39: =(L39/1.7*42+I39)*$C$7*365-$C$8-$C$9 -> 43217344 | Q39: =(N39-M39/2.8)*$C$10*365-$C$11-$C$12 -> 273892.14 | R39: =O39+P39+Q39 -> 56710385 | AD39: =SUMPRODUCT(C39:H39,$J$9:$O$9) -> -1.4187811 | AE39: =SUMPRODUCT(C39:H39,$J$10:$O$10) -> -1.6348206 | AF39: =SUMPRODUCT(C39:H39,$J$11:$O$11) -> 0.054180335 | AG39: =SUMPRODUCT(C39:H39,$J$12:$O$12) -> 0.30461303 | AH39: =SUMPRODUCT(C39:H39,$J$13:$O$13) -> -0.98862535 | AI39: =SUMPRODUCT(C39:H39,$J$14:$O$14) -> -1.0260974
C40: 0.85608364 | D40: 1.7986533 | E40: 0.20517718 | F40: -0.39180465 | G40: 0.071897254 | H40: 0.31013575 | I40: =$C$14+AD40*$D$14 -> 30.796113 | J40: =$C$15+AE40*$D$15 -> 22.650475 | K40: =$C$16+AF40*$D$16 -> 0.60622758 | L40: =$C$17+AG40*$D$17 -> 1.0970287 | M40: =$C$18+AH40*$D$18 -> 4.6088619 | N40: =$C$19+AI40*$D$19 -> 2.0194113 | O40: =(I40+J40)/2*$C$4*365-$C$5-$C$6 -> 28499181 | P40: =(L40/1.7*42+I40)*$C$7*365-$C$8-$C$9 -> 57735766 | Q40: =(N40-M40/2.8)*$C$10*365-$C$11-$C$12 -> 624440.64 | R40: =O40+P40+Q40 -> 86859387 | T40: SUMMARY OUTPUT | AD40: =SUMPRODUCT(C40:H40,$J$9:$O$9) -> 2.4747848 | AE40: =SUMPRODUCT(C40:H40,$J$10:$O$10) -> 2.5974748 | AF40: =SUMPRODUCT(C40:H40,$J$11:$O$11) -> 0.42025071 | AG40: =SUMPRODUCT(C40:H40,$J$12:$O$12) -> 0.031948444 | AH40: =SUMPRODUCT(C40:H40,$J$13:$O$13) -> 0.098735446 | AI40: =SUMPRODUCT(C40:H40,$J$14:$O$14) -> 0.4848955
C41: 0.47439611 | D41: 0.69378364 | E41: 1.1769002 | F41: 0.37299261 | G41: 1.1642411 | H41: -0.56328872 | I41: =$C$14+AD41*$D$14 -> 25.412354 | J41: =$C$15+AE41*$D$15 -> 18.314766 | K41: =$C$16+AF41*$D$16 -> 0.75476562 | L41: =$C$17+AG41*$D$17 -> 1.3468562 | M41: =$C$18+AH41*$D$18 -> 5.5597648 | N41: =$C$19+AI41*$D$19 -> 2.1747111 | O41: =(I41+J41)/2*$C$4*365-$C$5-$C$6 -> 23316129 | P41: =(L41/1.7*42+I41)*$C$7*365-$C$8-$C$9 -> 58521994 | Q41: =(N41-M41/2.8)*$C$10*365-$C$11-$C$12 -> 316130.35 | R41: =O41+P41+Q41 -> 82154253 | AD41: =SUMPRODUCT(C41:H41,$J$9:$O$9) -> 1.1680471 | AE41: =SUMPRODUCT(C41:H41,$J$10:$O$10) -> 1.1425389 | AF41: =SUMPRODUCT(C41:H41,$J$11:$O$11) -> 1.7705965 | AG41: =SUMPRODUCT(C41:H41,$J$12:$O$12) -> 1.1675284 | AH41: =SUMPRODUCT(C41:H41,$J$13:$O$13) -> 1.1552942 | AI41: =SUMPRODUCT(C41:H41,$J$14:$O$14) -> 0.90462446
C42: 0.89217347 | D42: -1.8925596 | E42: 0.2136797 | F42: -0.27885272 | G42: -2.7940467 | H42: 0.50872492 | I42: =$C$14+AD42*$D$14 -> 18.531255 | J42: =$C$15+AE42*$D$15 -> 12.253022 | K42: =$C$16+AF42*$D$16 -> 0.46848971 | L42: =$C$17+AG42*$D$17 -> 0.91132754 | M42: =$C$18+AH42*$D$18 -> 2.3685283 | N42: =$C$19+AI42*$D$19 -> 1.1261661 | O42: =(I42+J42)/2*$C$4*365-$C$5-$C$6 -> 16414163 | P42: =(L42/1.7*42+I42)*$C$7*365-$C$8-$C$9 -> 40930522 | Q42: =(N42-M42/2.8)*$C$10*365-$C$11-$C$12 -> 468659.69 | R42: =O42+P42+Q42 -> 57813345 | T42: Regression Statistics | AD42: =SUMPRODUCT(C42:H42,$J$9:$O$9) -> -0.5021226 | AE42: =SUMPRODUCT(C42:H42,$J$10:$O$10) -> -0.89160335 | AF42: =SUMPRODUCT(C42:H42,$J$11:$O$11) -> -0.83191173 | AG42: =SUMPRODUCT(C42:H42,$J$12:$O$12) -> -0.81214756 | AH42: =SUMPRODUCT(C42:H42,$J$13:$O$13) -> -2.3905241 | AI42: =SUMPRODUCT(C42:H42,$J$14:$O$14) -> -1.9292809
C43: 0.2601662 | D43: 1.0610615 | E43: 1.0381039 | F43: -0.25269587 | G43: -1.1158915 | H43: -0.22991211 | I43: =$C$14+AD43*$D$14 -> 26.556124 | J43: =$C$15+AE43*$D$15 -> 19.139186 | K43: =$C$16+AF43*$D$16 -> 0.62697317 | L43: =$C$17+AG43*$D$17 -> 1.0721126 | M43: =$C$18+AH43*$D$18 -> 3.537773 | N43: =$C$19+AI43*$D$19 -> 1.5273266 | O43: =(I43+J43)/2*$C$4*365-$C$5-$C$6 -> 24365695 | P43: =(L43/1.7*42+I43)*$C$7*365-$C$8-$C$9 -> 52893895 | Q43: =(N43-M43/2.8)*$C$10*365-$C$11-$C$12 -> 441180.93 | R43: =O43+P43+Q43 -> 77700771 | T43: Multiple R | U43: 1 | AD43: =SUMPRODUCT(C43:H43,$J$9:$O$9) -> 1.4456611 | AE43: =SUMPRODUCT(C43:H43,$J$10:$O$10) -> 1.41919 | AF43: =SUMPRODUCT(C43:H43,$J$11:$O$11) -> 0.608847 | AG43: =SUMPRODUCT(C43:H43,$J$12:$O$12) -> -0.081306518 | AH43: =SUMPRODUCT(C43:H43,$J$13:$O$13) -> -1.0913633 | AI43: =SUMPRODUCT(C43:H43,$J$14:$O$14) -> -0.84506325
C44: -1.9839341 | D44: -0.44799582 | E44: -0.55998217 | F44: -0.92285307 | G44: -1.0603267 | H44: -0.28841733 | I44: =$C$14+AD44*$D$14 -> 10.416179 | J44: =$C$15+AE44*$D$15 -> 8.0217218 | K44: =$C$16+AF44*$D$16 -> 0.36122812 | L44: =$C$17+AG44*$D$17 -> 0.6814375 | M44: =$C$18+AH44*$D$18 -> 3.1311947 | N44: =$C$19+AI44*$D$19 -> 1.1777697 | O44: =(I44+J44)/2*$C$4*365-$C$5-$C$6 -> 9830273.3 | P44: =(L44/1.7*42+I44)*$C$7*365-$C$8-$C$9 -> 27174711 | Q44: =(N44-M44/2.8)*$C$10*365-$C$11-$C$12 -> 99344.627 | R44: =O44+P44+Q44 -> 37104329 | T44: R Square | U44: 1 | AD44: =SUMPRODUCT(C44:H44,$J$9:$O$9) -> -2.4718011 | AE44: =SUMPRODUCT(C44:H44,$J$10:$O$10) -> -2.3115028 | AF44: =SUMPRODUCT(C44:H44,$J$11:$O$11) -> -1.8070171 | AG44: =SUMPRODUCT(C44:H44,$J$12:$O$12) -> -1.8571023 | AH44: =SUMPRODUCT(C44:H44,$J$13:$O$13) -> -1.543117 | AI44: =SUMPRODUCT(C44:H44,$J$14:$O$14) -> -1.7898117
C45: 1.0145048 | D45: 0.26326214 | E45: -0.88692162 | F45: 0.28297415 | G45: -0.17340314 | H45: -0.16301814 | I45: =$C$14+AD45*$D$14 -> 25.362264 | J45: =$C$15+AE45*$D$15 -> 18.170541 | K45: =$C$16+AF45*$D$16 -> 0.48647839 | L45: =$C$17+AG45*$D$17 -> 1.0541177 | M45: =$C$18+AH45*$D$18 -> 3.9404346 | N45: =$C$19+AI45*$D$19 -> 1.7167049 | O45: =(I45+J45)/2*$C$4*365-$C$5-$C$6 -> 23212507 | P45: =(L45/1.7*42+I45)*$C$7*365-$C$8-$C$9 -> 51260077 | Q45: =(N45-M45/2.8)*$C$10*365-$C$11-$C$12 -> 517411.23 | R45: =O45+P45+Q45 -> 74989995 | T45: Adjusted R Square | U45: 1 | AD45: =SUMPRODUCT(C45:H45,$J$9:$O$9) -> 1.1558893 | AE45: =SUMPRODUCT(C45:H45,$J$10:$O$10) -> 1.0941413 | AF45: =SUMPRODUCT(C45:H45,$J$11:$O$11) -> -0.66837825 | AG45: =SUMPRODUCT(C45:H45,$J$12:$O$12) -> -0.16310127 | AH45: =SUMPRODUCT(C45:H45,$J$13:$O$13) -> -0.64396156 | AI45: =SUMPRODUCT(C45:H45,$J$14:$O$14) -> -0.33322994
C46: -0.74399272 | D46: 2.3370823 | E46: 0.31007097 | F46: -0.95758661 | G46: -1.7203541 | H46: 0.73299592 | I46: =$C$14+AD46*$D$14 -> 26.857532 | J46: =$C$15+AE46*$D$15 -> 20.303603 | K46: =$C$16+AF46*$D$16 -> 0.50879633 | L46: =$C$17+AG46*$D$17 -> 0.87373909 | M46: =$C$18+AH46*$D$18 -> 3.300353 | N46: =$C$19+AI46*$D$19 -> 1.5616506 | O46: =(I46+J46)/2*$C$4*365-$C$5-$C$6 -> 25147369 | P46: =(L46/1.7*42+I46)*$C$7*365-$C$8-$C$9 -> 48307283 | Q46: =(N46-M46/2.8)*$C$10*365-$C$11-$C$12 -> 640439.05 | R46: =O46+P46+Q46 -> 74095091 | T46: Standard Error | U46: 2.64933e-08 | AD46: =SUMPRODUCT(C46:H46,$J$9:$O$9) -> 1.5188186 | AE46: =SUMPRODUCT(C46:H46,$J$10:$O$10) -> 1.8099339 | AF46: =SUMPRODUCT(C46:H46,$J$11:$O$11) -> -0.46548795 | AG46: =SUMPRODUCT(C46:H46,$J$12:$O$12) -> -0.98300413 | AH46: =SUMPRODUCT(C46:H46,$J$13:$O$13) -> -1.3551633 | AI46: =SUMPRODUCT(C46:H46,$J$14:$O$14) -> -0.75229563
C47: 1.0920011 | D47: 0.47104216 | E47: -0.8678557 | F47: 1.0388703 | G47: -1.2902265 | H47: 0.78546679 | I47: =$C$14+AD47*$D$14 -> 27.430728 | J47: =$C$15+AE47*$D$15 -> 19.564936 | K47: =$C$16+AF47*$D$16 -> 0.51679984 | L47: =$C$17+AG47*$D$17 -> 1.236259 | M47: =$C$18+AH47*$D$18 -> 3.8119757 | N47: =$C$19+AI47*$D$19 -> 1.8598224 | O47: =(I47+J47)/2*$C$4*365-$C$5-$C$6 -> 25059129 | P47: =(L47/1.7*42+I47)*$C$7*365-$C$8-$C$9 -> 57809978 | Q47: =(N47-M47/2.8)*$C$10*365-$C$11-$C$12 -> 833562.24 | R47: =O47+P47+Q47 -> 83702669 | T47: Observations | U47: 5000 | AD47: =SUMPRODUCT(C47:H47,$J$9:$O$9) -> 1.6579437 | AE47: =SUMPRODUCT(C47:H47,$J$10:$O$10) -> 1.5620591 | AF47: =SUMPRODUCT(C47:H47,$J$11:$O$11) -> -0.39272872 | AG47: =SUMPRODUCT(C47:H47,$J$12:$O$12) -> 0.66481348 | AH47: =SUMPRODUCT(C47:H47,$J$13:$O$13) -> -0.78669366 | AI47: =SUMPRODUCT(C47:H47,$J$14:$O$14) -> 0.053574088
C48: 1.5002609 | D48: -0.010549304 | E48: 0.23406676 | F48: -3.4087395 | G48: 1.9547476 | H48: -0.95795353 | I48: =$C$14+AD48*$D$14 -> 24.479516 | J48: =$C$15+AE48*$D$15 -> 17.887385 | K48: =$C$16+AF48*$D$16 -> 0.47181899 | L48: =$C$17+AG48*$D$17 -> 0.44342778 | M48: =$C$18+AH48*$D$18 -> 4.6083689 | N48: =$C$19+AI48*$D$19 -> 1.6086847 | O48: =(I48+J48)/2*$C$4*365-$C$5-$C$6 -> 22590772 | P48: =(L48/1.7*42+I48)*$C$7*365-$C$8-$C$9 -> 35334732 | Q48: =(N48-M48/2.8)*$C$10*365-$C$11-$C$12 -> -62326.275 | R48: =O48+P48+Q48 -> 57863177 | AD48: =SUMPRODUCT(C48:H48,$J$9:$O$9) -> 0.94163015 | AE48: =SUMPRODUCT(C48:H48,$J$10:$O$10) -> 0.99912247 | AF48: =SUMPRODUCT(C48:H48,$J$11:$O$11) -> -0.8016455 | AG48: =SUMPRODUCT(C48:H48,$J$12:$O$12) -> -2.9389646 | AH48: =SUMPRODUCT(C48:H48,$J$13:$O$13) -> 0.098187707 | AI48: =SUMPRODUCT(C48:H48,$J$14:$O$14) -> -0.62517642
C49: 0.2685136 | D49: -0.46309965 | E49: -0.63712565 | F49: -0.53999056 | G49: -1.2302052 | H49: -1.3646322 | I49: =$C$14+AD49*$D$14 -> 19.598613 | J49: =$C$15+AE49*$D$15 -> 13.756435 | K49: =$C$16+AF49*$D$16 -> 0.37466279 | L49: =$C$17+AG49*$D$17 -> 0.70065028 | M49: =$C$18+AH49*$D$18 -> 2.0804613 | N49: =$C$19+AI49*$D$19 -> 0.81992542 | O49: =(I49+J49)/2*$C$4*365-$C$5-$C$6 -> 17785066 | P49: =(L49/1.7*42+I49)*$C$7*365-$C$8-$C$9 -> 36804581 | Q49: =(N49-M49/2.8)*$C$10*365-$C$11-$C$12 -> 128480.83 | R49: =O49+P49+Q49 -> 54718127 | T49: ANOVA | AD49: =SUMPRODUCT(C49:H49,$J$9:$O$9) -> -0.24305508 | AE49: =SUMPRODUCT(C49:H49,$J$10:$O$10) -> -0.38710246 | AF49: =SUMPRODUCT(C49:H49,$J$11:$O$11) -> -1.6848837 | AG49: =SUMPRODUCT(C49:H49,$J$12:$O$12) -> -1.7697715 | AH49: =SUMPRODUCT(C49:H49,$J$13:$O$13) -> -2.7105985 | AI49: =SUMPRODUCT(C49:H49,$J$14:$O$14) -> -2.7569583
C50: -1.0078328 | D50: 0.035900729 | E50: -0.52318088 | F50: -0.97386288 | G50: 0.10206827 | H50: 0.8062786 | I50: =$C$14+AD50*$D$14 -> 15.980333 | J50: =$C$15+AE50*$D$15 -> 12.238026 | K50: =$C$16+AF50*$D$16 -> 0.4587556 | L50: =$C$17+AG50*$D$17 -> 0.87411188 | M50: =$C$18+AH50*$D$18 -> 4.8537265 | N50: =$C$19+AI50*$D$19 -> 1.9586928 | O50: =(I50+J50)/2*$C$4*365-$C$5-$C$6 -> 15045849 | P50: =(L50/1.7*42+I50)*$C$7*365-$C$8-$C$9 -> 37469940 | Q50: =(N50-M50/2.8)*$C$10*365-$C$11-$C$12 -> 376582.25 | R50: =O50+P50+Q50 -> 52892371 | U50: df | V50: SS | W50: MS | X50: F | Y50: Significance F | AD50: =SUMPRODUCT(C50:H50,$J$9:$O$9) -> -1.1212785 | AE50: =SUMPRODUCT(C50:H50,$J$10:$O$10) -> -0.89663562 | AF50: =SUMPRODUCT(C50:H50,$J$11:$O$11) -> -0.92040363 | AG50: =SUMPRODUCT(C50:H50,$J$12:$O$12) -> -0.98130965 | AH50: =SUMPRODUCT(C50:H50,$J$13:$O$13) -> 0.37080722 | AI50: =SUMPRODUCT(C50:H50,$J$14:$O$14) -> 0.32079127
C51: -1.8319569 | D51: 0.37796576 | E51: -0.22494016 | F51: 0.9200967 | G51: -0.97267148 | H51: -0.51042785 | I51: =$C$14+AD51*$D$14 -> 14.989494 | J51: =$C$15+AE51*$D$15 -> 11.185912 | K51: =$C$16+AF51*$D$16 -> 0.50830762 | L51: =$C$17+AG51*$D$17 -> 1.1224185 | M51: =$C$18+AH51*$D$18 -> 3.6025252 | N51: =$C$19+AI51*$D$19 -> 1.4586918 | O51: =(I51+J51)/2*$C$4*365-$C$5-$C$6 -> 13956414 | P51: =(L51/1.7*42+I51)*$C$7*365-$C$8-$C$9 -> 42599229 | Q51: =(N51-M51/2.8)*$C$10*365-$C$11-$C$12 -> 287684.3 | R51: =O51+P51+Q51 -> 56843328 | T51: Regression | U51: 6 | V51: 2.66105e+17 | W51: 4.44e+16 | X51: 6.32e+31 | Y51: 0 | AD51: =SUMPRODUCT(C51:H51,$J$9:$O$9) -> -1.3617733 | AE51: =SUMPRODUCT(C51:H51,$J$10:$O$10) -> -1.2496939 | AF51: =SUMPRODUCT(C51:H51,$J$11:$O$11) -> -0.46993076 | AG51: =SUMPRODUCT(C51:H51,$J$12:$O$12) -> 0.14735663 | AH51: =SUMPRODUCT(C51:H51,$J$13:$O$13) -> -1.0194164 | AI51: =SUMPRODUCT(C51:H51,$J$14:$O$14) -> -1.0305627
C52: 1.8495093 | D52: -0.032143243 | E52: -1.058482 | F52: -1.1984964 | G52: 0.34399045 | H52: -1.148954 | I52: =$C$14+AD52*$D$14 -> 26.57446 | J52: =$C$15+AE52*$D$15 -> 18.886951 | K52: =$C$16+AF52*$D$16 -> 0.38946041 | L52: =$C$17+AG52*$D$17 -> 0.67182883 | M52: =$C$18+AH52*$D$18 -> 3.1803193 | N52: =$C$19+AI52*$D$19 -> 1.2744478 | O52: =(I52+J52)/2*$C$4*365-$C$5-$C$6 -> 24240965 | P52: =(L52/1.7*42+I52)*$C$7*365-$C$8-$C$9 -> 43050704 | Q52: =(N52-M52/2.8)*$C$10*365-$C$11-$C$12 -> 231718.93 | R52: =O52+P52+Q52 -> 67523389 | T52: Residual | U52: 4993 | V52: 3.50455e-12 | W52: 7.02e-16 | AD52: =SUMPRODUCT(C52:H52,$J$9:$O$9) -> 1.4501117 | AE52: =SUMPRODUCT(C52:H52,$J$10:$O$10) -> 1.3345472 | AF52: =SUMPRODUCT(C52:H52,$J$11:$O$11) -> -1.5503599 | AG52: =SUMPRODUCT(C52:H52,$J$12:$O$12) -> -1.9007781 | AH52: =SUMPRODUCT(C52:H52,$J$13:$O$13) -> -1.4885341 | AI52: =SUMPRODUCT(C52:H52,$J$14:$O$14) -> -1.5285195
C53: -0.28727705 | D53: 1.0868677 | E53: -2.081364 | F53: 1.0981167 | G53: 0.18210878 | H53: 0.33933652 | I53: =$C$14+AD53*$D$14 -> 22.607539 | J53: =$C$15+AE53*$D$15 -> 16.99575 | K53: =$C$16+AF53*$D$16 -> 0.4150048 | L53: =$C$17+AG53*$D$17 -> 1.1501519 | M53: =$C$18+AH53*$D$18 -> 4.5460279 | N53: =$C$19+AI53*$D$19 -> 2.0243533 | O53: =(I53+J53)/2*$C$4*365-$C$5-$C$6 -> 21117034 | P53: =(L53/1.7*42+I53)*$C$7*365-$C$8-$C$9 -> 50879039 | Q53: =(N53-M53/2.8)*$C$10*365-$C$11-$C$12 -> 670246.21 | R53: =O53+P53+Q53 -> 72666319 | T53: Total | U53: 4999 | V53: 2.66105e+17 | AD53: =SUMPRODUCT(C53:H53,$J$9:$O$9) -> 0.48726687 | AE53: =SUMPRODUCT(C53:H53,$J$10:$O$10) -> 0.69991597 | AF53: =SUMPRODUCT(C53:H53,$J$11:$O$11) -> -1.3181382 | AG53: =SUMPRODUCT(C53:H53,$J$12:$O$12) -> 0.27341766 | AH53: =SUMPRODUCT(C53:H53,$J$13:$O$13) -> 0.028919943 | AI53: =SUMPRODUCT(C53:H53,$J$14:$O$14) -> 0.49825216
C54: 0.91477001 | D54: -2.440563 | E54: -0.52758581 | F54: 0.89512672 | G54: -0.080059799 | H54: 0.2208107 | I54: =$C$14+AD54*$D$14 -> 15.440461 | J54: =$C$15+AE54*$D$15 -> 10.144419 | K54: =$C$16+AF54*$D$16 -> 0.54243503 | L54: =$C$17+AG54*$D$17 -> 1.2363196 | M54: =$C$18+AH54*$D$18 -> 4.7099206 | N54: =$C$19+AI54*$D$19 -> 1.9083017 | O54: =(I54+J54)/2*$C$4*365-$C$5-$C$6 -> 13641507 | P54: =(L54/1.7*42+I54)*$C$7*365-$C$8-$C$9 -> 45855016 | Q54: =(N54-M54/2.8)*$C$10*365-$C$11-$C$12 -> 378201.88 | R54: =O54+P54+Q54 -> 59874725 | AD54: =SUMPRODUCT(C54:H54,$J$9:$O$9) -> -1.2523154 | AE54: =SUMPRODUCT(C54:H54,$J$10:$O$10) -> -1.5991882 | AF54: =SUMPRODUCT(C54:H54,$J$11:$O$11) -> -0.1596815 | AG54: =SUMPRODUCT(C54:H54,$J$12:$O$12) -> 0.66508901 | AH54: =SUMPRODUCT(C54:H54,$J$13:$O$13) -> 0.21102289 | AI54: =SUMPRODUCT(C54:H54,$J$14:$O$14) -> 0.18459929
C55: 0.30272486 | D55: -0.54645311 | E55: -1.2315182 | F55: -0.45892753 | G55: -0.73043904 | H55: 0.32876017 | I55: =$C$14+AD55*$D$14 -> 19.239487 | J55: =$C$15+AE55*$D$15 -> 13.864911 | K55: =$C$16+AF55*$D$16 -> 0.37919496 | L55: =$C$17+AG55*$D$17 -> 0.83493983 | M55: =$C$18+AH55*$D$18 -> 3.5848187 | N55: =$C$19+AI55*$D$19 -> 1.5489762 | O55: =(I55+J55)/2*$C$4*365-$C$5-$C$6 -> 17651403 | P55: =(L55/1.7*42+I55)*$C$7*365-$C$8-$C$9 -> 39754853 | Q55: =(N55-M55/2.8)*$C$10*365-$C$11-$C$12 -> 449290.02 | R55: =O55+P55+Q55 -> 57855547 | U55: Coefficients | V55: Standard Error | W55: t Stat | X55: P-value | Y55: Lower 95% | Z55: Upper 95% | AA55: Lower 95.0% | AB55: Upper 95.0% | AD55: =SUMPRODUCT(C55:H55,$J$9:$O$9) -> -0.3302215 | AE55: =SUMPRODUCT(C55:H55,$J$10:$O$10) -> -0.35070095 | AF55: =SUMPRODUCT(C55:H55,$J$11:$O$11) -> -1.6436821 | AG55: =SUMPRODUCT(C55:H55,$J$12:$O$12) -> -1.1593644 | AH55: =SUMPRODUCT(C55:H55,$J$13:$O$13) -> -1.0390903 | AI55: =SUMPRODUCT(C55:H55,$J$14:$O$14) -> -0.78655068
C56: -0.87644549 | D56: 0.27824575 | E56: 0.50441678 | F56: -1.400673 | G56: 0.082114904 | H56: 0.1543016 | I56: =$C$14+AD56*$D$14 -> 17.753387 | J56: =$C$15+AE56*$D$15 -> 13.363908 | K56: =$C$16+AF56*$D$16 -> 0.5344529 | L56: =$C$17+AG56*$D$17 -> 0.84011482 | M56: =$C$18+AH56*$D$18 -> 4.5520692 | N56: =$C$19+AI56*$D$19 -> 1.7548374 | O56: =(I56+J56)/2*$C$4*365-$C$5-$C$6 -> 16591750 | P56: =(L56/1.7*42+I56)*$C$7*365-$C$8-$C$9 -> 38400436 | Q56: =(N56-M56/2.8)*$C$10*365-$C$11-$C$12 -> 215792.18 | R56: =O56+P56+Q56 -> 55207979 | T56: Intercept | U56: -133 | V56: 4.57892e-09 | W56: -29000000000 | X56: 0 | Y56: -133 | Z56: -133 | AA56: -133 | AB56: -133 | AD56: =SUMPRODUCT(C56:H56,$J$9:$O$9) -> -0.6909255 | AE56: =SUMPRODUCT(C56:H56,$J$10:$O$10) -> -0.51882274 | AF56: =SUMPRODUCT(C56:H56,$J$11:$O$11) -> -0.23224633 | AG56: =SUMPRODUCT(C56:H56,$J$12:$O$12) -> -1.1358417 | AH56: =SUMPRODUCT(C56:H56,$J$13:$O$13) -> 0.035632433 | AI56: =SUMPRODUCT(C56:H56,$J$14:$O$14) -> -0.23016916
C57: 3.1355273 | D57: 0.35342024 | E57: -0.70225617 | F57: -0.16209936 | G57: 1.4445712 | H57: -0.60153341 | I57: =$C$14+AD57*$D$14 -> 33.608996 | J57: =$C$15+AE57*$D$15 -> 23.744753 | K57: =$C$16+AF57*$D$16 -> 0.568534 | L57: =$C$17+AG57*$D$17 -> 1.0923659 | M57: =$C$18+AH57*$D$18 -> 4.8239311 | N57: =$C$19+AI57*$D$19 -> 2.0271601 | O57: =(I57+J57)/2*$C$4*365-$C$5-$C$6 -> 30582733 | P57: =(L57/1.7*42+I57)*$C$7*365-$C$8-$C$9 -> 60425845 | Q57: =(N57-M57/2.8)*$C$10*365-$C$11-$C$12 -> 508914.64 | R57: =O57+P57+Q57 -> 91517493 | T57: X Variable 1 | U57: 997180 | V57: 9.11221e-11 | W57: 1.09e+16 | X57: 0 | Y57: 997180 | Z57: 997180 | AA57: 997180 | AB57: 997180 | AD57: =SUMPRODUCT(C57:H57,$J$9:$O$9) -> 3.1575234 | AE57: =SUMPRODUCT(C57:H57,$J$10:$O$10) -> 2.9646824 | AF57: =SUMPRODUCT(C57:H57,$J$11:$O$11) -> 0.077581838 | AG57: =SUMPRODUCT(C57:H57,$J$12:$O$12) -> 0.010754291 | AH57: =SUMPRODUCT(C57:H57,$J$13:$O$13) -> 0.33770124 | AI57: =SUMPRODUCT(C57:H57,$J$14:$O$14) -> 0.50583814
C58: -0.96251879 | D58: 0.79386589 | E58: -0.31510962 | F58: 0.95195094 | G58: -0.19882745 | H58: -0.23815766 | I58: =$C$14+AD58*$D$14 -> 19.8084 | J58: =$C$15+AE58*$D$15 -> 14.700837 | K58: =$C$16+AF58*$D$16 -> 0.55634202 | L58: =$C$17+AG58*$D$17 -> 1.2182438 | M58: =$C$18+AH58*$D$18 -> 4.3782517 | N58: =$C$19+AI58*$D$19 -> 1.8163363 | O58: =(I58+J58)/2*$C$4*365-$C$5-$C$6 -> 18400554 | P58: =(L58/1.7*42+I58)*$C$7*365-$C$8-$C$9 -> 49765319 | Q58: =(N58-M58/2.8)*$C$10*365-$C$11-$C$12 -> 422510.39 | R58: =O58+P58+Q58 -> 68588383 | T58: X Variable 2 | U58: 5.69507e-10 | V58: 1.50247e-10 | W58: 3.790485 | X58: 0.000152 | Y58: 2.74958e-10 | Z58: 8.64e-10 | AA58: 2.75e-10 | AB58: 8.64e-10 | AD58: =SUMPRODUCT(C58:H58,$J$9:$O$9) -> -0.19213598 | AE58: =SUMPRODUCT(C58:H58,$J$10:$O$10) -> -0.070188835 | AF58: =SUMPRODUCT(C58:H58,$J$11:$O$11) -> -0.033254403 | AG58: =SUMPRODUCT(C58:H58,$J$12:$O$12) -> 0.58292625 | AH58: =SUMPRODUCT(C58:H58,$J$13:$O$13) -> -0.15749808 | AI58: =SUMPRODUCT(C58:H58,$J$14:$O$14) -> -0.063956005
C59: -1.6389323 | D59: -0.48282727 | E59: -0.75807781 | F59: 0.33162406 | G59: -0.44243805 | H59: 1.8172065 | I59: =$C$14+AD59*$D$14 -> 12.282042 | J59: =$C$15+AE59*$D$15 -> 9.506514 | K59: =$C$16+AF59*$D$16 -> 0.4954366 | L59: =$C$17+AG59*$D$17 -> 1.1689144 | M59: =$C$18+AH59*$D$18 -> 5.4501696 | N59: =$C$19+AI59*$D$19 -> 2.3121781 | O59: =(I59+J59)/2*$C$4*365-$C$5-$C$6 -> 11617060 | P59: =(L59/1.7*42+I59)*$C$7*365-$C$8-$C$9 -> 41044896 | Q59: =(N59-M59/2.8)*$C$10*365-$C$11-$C$12 -> 611559.61 | R59: =O59+P59+Q59 -> 53273515 | T59: X Variable 3 | U59: 1.17304e-09 | V59: 3.38906e-09 | W59: 0.346127 | X59: 0.729262 | Y59: -5.471e-09 | Z59: 7.82e-09 | AA59: -5.5e-09 | AB59: 7.82e-09 | AD59: =SUMPRODUCT(C59:H59,$J$9:$O$9) -> -2.0189219 | AE59: =SUMPRODUCT(C59:H59,$J$10:$O$10) -> -1.8132503 | AF59: =SUMPRODUCT(C59:H59,$J$11:$O$11) -> -0.58694003 | AG59: =SUMPRODUCT(C59:H59,$J$12:$O$12) -> 0.35870176 | AH59: =SUMPRODUCT(C59:H59,$J$13:$O$13) -> 1.0335217 | AI59: =SUMPRODUCT(C59:H59,$J$14:$O$14) -> 1.2761569
C60: 1.2600118 | D60: -0.036770233 | E60: 0.28195063 | F60: -0.49847798 | G60: 0.048811932 | H60: 0.24235623 | I60: =$C$14+AD60*$D$14 -> 25.653592 | J60: =$C$15+AE60*$D$15 -> 18.254474 | K60: =$C$16+AF60*$D$16 -> 0.59252806 | L60: =$C$17+AG60*$D$17 -> 1.0632141 | M60: =$C$18+AH60*$D$18 -> 4.5809062 | N60: =$C$19+AI60*$D$19 -> 1.9183755 | O60: =(I60+J60)/2*$C$4*365-$C$5-$C$6 -> 23412621 | P60: =(L60/1.7*42+I60)*$C$7*365-$C$8-$C$9 -> 51774685 | Q60: =(N60-M60/2.8)*$C$10*365-$C$11-$C$12 -> 472129.95 | R60: =O60+P60+Q60 -> 75659435 | T60: X Variable 4 | U60: 24636212 | V60: 1.72008e-09 | W60: 1.43e+16 | X60: 0 | Y60: 24636212 | Z60: 24636212 | AA60: 24636212 | AB60: 24636212 | AD60: =SUMPRODUCT(C60:H60,$J$9:$O$9) -> 1.2266 | AE60: =SUMPRODUCT(C60:H60,$J$10:$O$10) -> 1.1223066 | AF60: =SUMPRODUCT(C60:H60,$J$11:$O$11) -> 0.29570962 | AG60: =SUMPRODUCT(C60:H60,$J$12:$O$12) -> -0.12175392 | AH60: =SUMPRODUCT(C60:H60,$J$13:$O$13) -> 0.067673568 | AI60: =SUMPRODUCT(C60:H60,$J$14:$O$14) -> 0.21182581
C61: 0.49570125 | D61: -2.0429481 | E61: 2.6033422 | F61: 2.1574729 | G61: 0.86312339 | H61: 0.41153052 | I61: =$C$14+AD61*$D$14 -> 17.29395 | J61: =$C$15+AE61*$D$15 -> 11.242776 | K61: =$C$16+AF61*$D$16 -> 0.99528264 | L61: =$C$17+AG61*$D$17 -> 1.9326255 | M61: =$C$18+AH61*$D$18 -> 7.0430031 | N61: =$C$19+AI61*$D$19 -> 2.7414474 | O61: =(I61+J61)/2*$C$4*365-$C$5-$C$6 -> 15215623 | P61: =(L61/1.7*42+I61)*$C$7*365-$C$8-$C$9 -> 64857620 | Q61: =(N61-M61/2.8)*$C$10*365-$C$11-$C$12 -> 378037.75 | R61: =O61+P61+Q61 -> 80451281 | T61: X Variable 5 | U61: 7.60062e-10 | V61: 4.16177e-10 | W61: 1.826293 | X61: 0.067866 | Y61: -5.58286e-11 | Z61: 1.58e-09 | AA61: -5.6e-11 | AB61: 1.58e-09 | AD61: =SUMPRODUCT(C61:H61,$J$9:$O$9) -> -0.80243922 | AE61: =SUMPRODUCT(C61:H61,$J$10:$O$10) -> -1.2306122 | AF61: =SUMPRODUCT(C61:H61,$J$11:$O$11) -> 3.9571149 | AG61: =SUMPRODUCT(C61:H61,$J$12:$O$12) -> 3.830116 | AH61: =SUMPRODUCT(C61:H61,$J$13:$O$13) -> 2.8033367 | AI61: =SUMPRODUCT(C61:H61,$J$14:$O$14) -> 2.4363442
C62: 0.78501911 | D62: 0.55688033 | E62: 0.064782047 | F62: 0.48852841 | G62: 0.31528923 | H62: -0.16890018 | I62: =$C$14+AD62*$D$14 -> 25.975807 | J62: =$C$15+AE62*$D$15 -> 18.66971 | K62: =$C$16+AF62*$D$16 -> 0.62056747 | L62: =$C$17+AG62*$D$17 -> 1.2339443 | M62: =$C$18+AH62*$D$18 -> 4.7387499 | N62: =$C$19+AI62*$D$19 -> 1.9842545 | O62: =(I62+J62)/2*$C$4*365-$C$5-$C$6 -> 23805878 | P62: =(L62/1.7*42+I62)*$C$7*365-$C$8-$C$9 -> 56302135 | Q62: =(N62-M62/2.8)*$C$10*365-$C$11-$C$12 -> 488031.94 | R62: =O62+P62+Q62 -> 80596044 | T62: X Variable 6 | U62: -3.30924e-10 | V62: 1.01102e-09 | W62: -0.32732 | X62: 0.743441 | Y62: -2.31296e-09 | Z62: 1.65e-09 | AA62: -2.3e-09 | AB62: 1.65e-09 | AD62: =SUMPRODUCT(C62:H62,$J$9:$O$9) -> 1.3048076 | AE62: =SUMPRODUCT(C62:H62,$J$10:$O$10) -> 1.2616477 | AF62: =SUMPRODUCT(C62:H62,$J$11:$O$11) -> 0.55061334 | AG62: =SUMPRODUCT(C62:H62,$J$12:$O$12) -> 0.65429206 | AH62: =SUMPRODUCT(C62:H62,$J$13:$O$13) -> 0.24305539 | AI62: =SUMPRODUCT(C62:H62,$J$14:$O$14) -> 0.38987707
C63: 3.029772 | D63: -0.037749559 | E63: -0.077486363 | F63: 0.59514234 | G63: -1.2038474 | H63: 0.92606317 | I63: =$C$14+AD63*$D$14 -> 33.826752 | J63: =$C$15+AE63*$D$15 -> 23.44428 | K63: =$C$16+AF63*$D$16 -> 0.61290393 | L63: =$C$17+AG63*$D$17 -> 1.2806872 | M63: =$C$18+AH63*$D$18 -> 3.9686023 | N63: =$C$19+AI63*$D$19 -> 1.9618722 | O63: =(I63+J63)/2*$C$4*365-$C$5-$C$6 -> 30538623 | P63: =(L63/1.7*42+I63)*$C$7*365-$C$8-$C$9 -> 65282508 | Q63: =(N63-M63/2.8)*$C$10*365-$C$11-$C$12 -> 910697.64 | R63: =O63+P63+Q63 -> 96731828 | AD63: =SUMPRODUCT(C63:H63,$J$9:$O$9) -> 3.2103766 | AE63: =SUMPRODUCT(C63:H63,$J$10:$O$10) -> 2.8638524 | AF63: =SUMPRODUCT(C63:H63,$J$11:$O$11) -> 0.48094484 | AG63: =SUMPRODUCT(C63:H63,$J$12:$O$12) -> 0.86675991 | AH63: =SUMPRODUCT(C63:H63,$J$13:$O$13) -> -0.61266416 | AI63: =SUMPRODUCT(C63:H63,$J$14:$O$14) -> 0.3293842
C64: -0.25207183 | D64: -0.22365133 | E64: 0.71578107 | F64: -1.4524308 | G64: -0.53608157 | H64: 1.1163718 | I64: =$C$14+AD64*$D$14 -> 19.026954 | J64: =$C$15+AE64*$D$15 -> 13.976908 | K64: =$C$16+AF64*$D$16 -> 0.56229396 | L64: =$C$17+AG64*$D$17 -> 0.90405473 | M64: =$C$18+AH64*$D$18 -> 4.7073797 | N64: =$C$19+AI64*$D$19 -> 1.932689 | O64: =(I64+J64)/2*$C$4*365-$C$5-$C$6 -> 17597791 | P64: =(L64/1.7*42+I64)*$C$7*365-$C$8-$C$9 -> 41245649 | Q64: =(N64-M64/2.8)*$C$10*365-$C$11-$C$12 -> 420514.69 | R64: =O64+P64+Q64 -> 59263954 | T64: SUMMARY OUTPUT | AD64: =SUMPRODUCT(C64:H64,$J$9:$O$9) -> -0.3818072 | AE64: =SUMPRODUCT(C64:H64,$J$10:$O$10) -> -0.31311816 | AF64: =SUMPRODUCT(C64:H64,$J$11:$O$11) -> 0.02085415 | AG64: =SUMPRODUCT(C64:H64,$J$12:$O$12) -> -0.84520579 | AH64: =SUMPRODUCT(C64:H64,$J$13:$O$13) -> 0.20819972 | AI64: =SUMPRODUCT(C64:H64,$J$14:$O$14) -> 0.25051072
C65: -1.4535089 | D65: 0.35829633 | E65: -0.53601491 | F65: -0.52378659 | G65: -0.53501175 | H65: -0.72404274 | I65: =$C$14+AD65*$D$14 -> 15.464321 | J65: =$C$15+AE65*$D$15 -> 11.705588 | K65: =$C$16+AF65*$D$16 -> 0.41167933 | L65: =$C$17+AG65*$D$17 -> 0.78874284 | M65: =$C$18+AH65*$D$18 -> 3.321604 | N65: =$C$19+AI65*$D$19 -> 1.273006 | O65: =(I65+J65)/2*$C$4*365-$C$5-$C$6 -> 14486747 | P65: =(L65/1.7*42+I65)*$C$7*365-$C$8-$C$9 -> 34852214 | Q65: =(N65-M65/2.8)*$C$10*365-$C$11-$C$12 -> 144899.79 | R65: =O65+P65+Q65 -> 49483861 | AD65: =SUMPRODUCT(C65:H65,$J$9:$O$9) -> -1.246524 | AE65: =SUMPRODUCT(C65:H65,$J$10:$O$10) -> -1.0753062 | AF65: =SUMPRODUCT(C65:H65,$J$11:$O$11) -> -1.3483697 | AG65: =SUMPRODUCT(C65:H65,$J$12:$O$12) -> -1.3693507 | AH65: =SUMPRODUCT(C65:H65,$J$13:$O$13) -> -1.3315511 | AI65: =SUMPRODUCT(C65:H65,$J$14:$O$14) -> -1.5324163
C66: -0.97494817 | D66: 1.7578181 | E66: -0.79889805 | F66: -0.57917118 | G66: 0.67793726 | H66: -0.049968916 | I66: =$C$14+AD66*$D$14 -> 22.079262 | J66: =$C$15+AE66*$D$15 -> 17.093216 | K66: =$C$16+AF66*$D$16 -> 0.46824259 | L66: =$C$17+AG66*$D$17 -> 0.91293729 | M66: =$C$18+AH66*$D$18 -> 4.6947803 | N66: =$C$19+AI66*$D$19 -> 1.9095683 | O66: =(I66+J66)/2*$C$4*365-$C$5-$C$6 -> 20887297 | P66: =(L66/1.7*42+I66)*$C$7*365-$C$8-$C$9 -> 44508182 | Q66: =(N66-M66/2.8)*$C$10*365-$C$11-$C$12 -> 389365.71 | R66: =O66+P66+Q66 -> 65784845 | T66: Regression Statistics | AD66: =SUMPRODUCT(C66:H66,$J$9:$O$9) -> 0.35904417 | AE66: =SUMPRODUCT(C66:H66,$J$10:$O$10) -> 0.73262268 | AF66: =SUMPRODUCT(C66:H66,$J$11:$O$11) -> -0.83415824 | AG66: =SUMPRODUCT(C66:H66,$J$12:$O$12) -> -0.8048305 | AH66: =SUMPRODUCT(C66:H66,$J$13:$O$13) -> 0.19420036 | AI66: =SUMPRODUCT(C66:H66,$J$14:$O$14) -> 0.18802231
C67: -0.91971836 | D67: 1.6389105 | E67: 0.2687228 | F67: 1.8746455 | G67: 0.10057573 | H67: 1.0876216 | I67: =$C$14+AD67*$D$14 -> 24.008878 | J67: =$C$15+AE67*$D$15 -> 17.995796 | K67: =$C$16+AF67*$D$16 -> 0.72929943 | L67: =$C$17+AG67*$D$17 -> 1.6321244 | M67: =$C$18+AH67*$D$18 -> 5.9934313 | N67: =$C$19+AI67*$D$19 -> 2.6181197 | O67: =(I67+J67)/2*$C$4*365-$C$5-$C$6 -> 22397608 | P67: =(L67/1.7*42+I67)*$C$7*365-$C$8-$C$9 -> 64150403 | Q67: =(N67-M67/2.8)*$C$10*365-$C$11-$C$12 -> 798778.1 | R67: =O67+P67+Q67 -> 87346789 | T67: Multiple R | U67: 1 | AD67: =SUMPRODUCT(C67:H67,$J$9:$O$9) -> 0.82739754 | AE67: =SUMPRODUCT(C67:H67,$J$10:$O$10) -> 1.0355019 | AF67: =SUMPRODUCT(C67:H67,$J$11:$O$11) -> 1.5390857 | AG67: =SUMPRODUCT(C67:H67,$J$12:$O$12) -> 2.4642019 | AH67: =SUMPRODUCT(C67:H67,$J$13:$O$13) -> 1.6371459 | AI67: =SUMPRODUCT(C67:H67,$J$14:$O$14) -> 2.1030262
C68: -1.6822237 | D68: -1.7135381 | E68: 0.11988533 | F68: -0.89308825 | G68: 0.53363247 | H68: -0.51404055 | I68: =$C$14+AD68*$D$14 -> 6.6958269 | J68: =$C$15+AE68*$D$15 -> 4.9618929 | K68: =$C$16+AF68*$D$16 -> 0.48387066 | L68: =$C$17+AG68*$D$17 -> 0.84083431 | M68: =$C$18+AH68*$D$18 -> 4.6552994 | N68: =$C$19+AI68*$D$19 -> 1.5921505 | O68: =(I68+J68)/2*$C$4*365-$C$5-$C$6 -> 6214639.9 | P68: =(L68/1.7*42+I68)*$C$7*365-$C$8-$C$9 -> 27391784 | Q68: =(N68-M68/2.8)*$C$10*365-$C$11-$C$12 -> -118022.19 | R68: =O68+P68+Q68 -> 33488402 | T68: R Square | U68: 1 | AD68: =SUMPRODUCT(C68:H68,$J$9:$O$9) -> -3.3747993 | AE68: =SUMPRODUCT(C68:H68,$J$10:$O$10) -> -3.338291 | AF68: =SUMPRODUCT(C68:H68,$J$11:$O$11) -> -0.69208493 | AG68: =SUMPRODUCT(C68:H68,$J$12:$O$12) -> -1.1325713 | AH68: =SUMPRODUCT(C68:H68,$J$13:$O$13) -> 0.15033269 | AI68: =SUMPRODUCT(C68:H68,$J$14:$O$14) -> -0.66986354
C69: 0.60600632 | D69: 1.9669092 | E69: 1.2265102 | F69: 1.5537583 | G69: -1.5063088 | H69: -0.33955814 | I69: =$C$14+AD69*$D$14 -> 32.338827 | J69: =$C$15+AE69*$D$15 -> 23.11696 | K69: =$C$16+AF69*$D$16 -> 0.74467719 | L69: =$C$17+AG69*$D$17 -> 1.4724136 | M69: =$C$18+AH69*$D$18 -> 3.5826542 | N69: =$C$19+AI69*$D$19 -> 1.6958913 | O69: =(I69+J69)/2*$C$4*365-$C$5-$C$6 -> 29570616 | P69: =(L69/1.7*42+I69)*$C$7*365-$C$8-$C$9 -> 68522192 | Q69: =(N69-M69/2.8)*$C$10*365-$C$11-$C$12 -> 696341.85 | R69: =O69+P69+Q69 -> 98789150 | T69: Adjusted R Square | U69: 1 | AD69: =SUMPRODUCT(C69:H69,$J$9:$O$9) -> 2.8492299 | AE69: =SUMPRODUCT(C69:H69,$J$10:$O$10) -> 2.7540135 | AF69: =SUMPRODUCT(C69:H69,$J$11:$O$11) -> 1.6788836 | AG69: =SUMPRODUCT(C69:H69,$J$12:$O$12) -> 1.7382436 | AH69: =SUMPRODUCT(C69:H69,$J$13:$O$13) -> -1.0414953 | AI69: =SUMPRODUCT(C69:H69,$J$14:$O$14) -> -0.38948305
C70: 0.75740128 | D70: 1.269449 | E70: -0.2608032 | F70: -1.2594652 | G70: -1.1748399 | H70: -0.36535096 | I70: =$C$14+AD70*$D$14 -> 28.156306 | J70: =$C$15+AE70*$D$15 -> 20.525105 | K70: =$C$16+AF70*$D$16 -> 0.43322363 | L70: =$C$17+AG70*$D$17 -> 0.70516575 | M70: =$C$18+AH70*$D$18 -> 2.6520914 | N70: =$C$19+AI70*$D$19 -> 1.2075239 | O70: =(I70+J70)/2*$C$4*365-$C$5-$C$6 -> 25958078 | P70: =(L70/1.7*42+I70)*$C$7*365-$C$8-$C$9 -> 45449385 | Q70: =(N70-M70/2.8)*$C$10*365-$C$11-$C$12 -> 435346.5 | R70: =O70+P70+Q70 -> 71842810 | T70: Standard Error | U70: 3.07136e-09 | AD70: =SUMPRODUCT(C70:H70,$J$9:$O$9) -> 1.8340548 | AE70: =SUMPRODUCT(C70:H70,$J$10:$O$10) -> 1.8842634 | AF70: =SUMPRODUCT(C70:H70,$J$11:$O$11) -> -1.1525124 | AG70: =SUMPRODUCT(C70:H70,$J$12:$O$12) -> -1.7492466 | AH70: =SUMPRODUCT(C70:H70,$J$13:$O$13) -> -2.0754539 | AI70: =SUMPRODUCT(C70:H70,$J$14:$O$14) -> -1.7093948
C71: 1.2402284 | D71: -0.12530589 | E71: -0.39491417 | F71: -1.511201 | G71: 0.025347099 | H71: 1.4282196 | I71: =$C$14+AD71*$D$14 -> 24.662205 | J71: =$C$15+AE71*$D$15 -> 17.94186 | K71: =$C$16+AF71*$D$16 -> 0.49278069 | L71: =$C$17+AG71*$D$17 -> 0.86735811 | M71: =$C$18+AH71*$D$18 -> 4.9327264 | N71: =$C$19+AI71*$D$19 -> 2.1340646 | O71: =(I71+J71)/2*$C$4*365-$C$5-$C$6 -> 22717243 | P71: =(L71/1.7*42+I71)*$C$7*365-$C$8-$C$9 -> 45960943 | Q71: =(N71-M71/2.8)*$C$10*365-$C$11-$C$12 -> 622746.65 | R71: =O71+P71+Q71 -> 69300933 | T71: Observations | U71: 5000 | AD71: =SUMPRODUCT(C71:H71,$J$9:$O$9) -> 0.98597219 | AE71: =SUMPRODUCT(C71:H71,$J$10:$O$10) -> 1.0174028 | AF71: =SUMPRODUCT(C71:H71,$J$11:$O$11) -> -0.61108462 | AG71: =SUMPRODUCT(C71:H71,$J$12:$O$12) -> -1.0120086 | AH71: =SUMPRODUCT(C71:H71,$J$13:$O$13) -> 0.45858494 | AI71: =SUMPRODUCT(C71:H71,$J$14:$O$14) -> 0.79476914
C72: 1.359608 | D72: 1.0423283 | E72: 1.3271594 | F72: 0.54967596 | G72: 0.27454545 | H72: 0.2076018 | I72: =$C$14+AD72*$D$14 -> 31.042842 | J72: =$C$15+AE72*$D$15 -> 22.16096 | K72: =$C$16+AF72*$D$16 -> 0.7863979 | L72: =$C$17+AG72*$D$17 -> 1.4346822 | M72: =$C$18+AH72*$D$18 -> 5.3137624 | N72: =$C$19+AI72*$D$19 -> 2.2659113 | O72: =(I72+J72)/2*$C$4*365-$C$5-$C$6 -> 28369712 | P72: =(L72/1.7*42+I72)*$C$7*365-$C$8-$C$9 -> 66300303 | Q72: =(N72-M72/2.8)*$C$10*365-$C$11-$C$12 -> 615658.09 | R72: =O72+P72+Q72 -> 95285673 | AD72: =SUMPRODUCT(C72:H72,$J$9:$O$9) -> 2.5346705 | AE72: =SUMPRODUCT(C72:H72,$J$10:$O$10) -> 2.4332081 | AF72: =SUMPRODUCT(C72:H72,$J$11:$O$11) -> 2.0581628 | AG72: =SUMPRODUCT(C72:H72,$J$12:$O$12) -> 1.5667372 | AH72: =SUMPRODUCT(C72:H72,$J$13:$O$13) -> 0.88195825 | AI72: =SUMPRODUCT(C72:H72,$J$14:$O$14) -> 1.1511116
C73: -2.0344714 | D73: 1.1471725 | E73: 0.22518511 | F73: -0.38714449 | G73: 0.48126294 | H73: -0.16356736 | I73: =$C$14+AD73*$D$14 -> 16.219379 | J73: =$C$15+AE73*$D$15 -> 12.761091 | K73: =$C$16+AF73*$D$16 -> 0.55655806 | L73: =$C$17+AG73*$D$17 -> 1.0148285 | M73: =$C$18+AH73*$D$18 -> 4.9332521 | N73: =$C$19+AI73*$D$19 -> 1.8902738 | O73: =(I73+J73)/2*$C$4*365-$C$5-$C$6 -> 15452257 | P73: =(L73/1.7*42+I73)*$C$7*365-$C$8-$C$9 -> 41175038 | Q73: =(N73-M73/2.8)*$C$10*365-$C$11-$C$12 -> 214620.63 | R73: =O73+P73+Q73 -> 56841915 | T73: ANOVA | AD73: =SUMPRODUCT(C73:H73,$J$9:$O$9) -> -1.0632575 | AE73: =SUMPRODUCT(C73:H73,$J$10:$O$10) -> -0.72111032 | AF73: =SUMPRODUCT(C73:H73,$J$11:$O$11) -> -0.031290401 | AG73: =SUMPRODUCT(C73:H73,$J$12:$O$12) -> -0.34168851 | AH73: =SUMPRODUCT(C73:H73,$J$13:$O$13) -> 0.459169 | AI73: =SUMPRODUCT(C73:H73,$J$14:$O$14) -> 0.13587515
C74: 0.15413652 | D74: 0.060083755 | E74: -1.3267704 | F74: 0.20984286 | G74: -0.1641367 | H74: 1.4104108 | I74: =$C$14+AD74*$D$14 -> 21.082513 | J74: =$C$15+AE74*$D$15 -> 15.583092 | K74: =$C$16+AF74*$D$16 -> 0.46126782 | L74: =$C$17+AG74*$D$17 -> 1.1075557 | M74: =$C$18+AH74*$D$18 -> 5.0099216 | N74: =$C$19+AI74*$D$19 -> 2.2266726 | O74: =(I74+J74)/2*$C$4*365-$C$5-$C$6 -> 19550470 | P74: =(L74/1.7*42+I74)*$C$7*365-$C$8-$C$9 -> 48308905 | Q74: =(N74-M74/2.8)*$C$10*365-$C$11-$C$12 -> 731542.51 | R74: =O74+P74+Q74 -> 68590917 | U74: df | V74: SS | W74: MS | X74: F | Y74: Significance F | AD74: =SUMPRODUCT(C74:H74,$J$9:$O$9) -> 0.11711483 | AE74: =SUMPRODUCT(C74:H74,$J$10:$O$10) -> 0.22586964 | AF74: =SUMPRODUCT(C74:H74,$J$11:$O$11) -> -0.89756528 | AG74: =SUMPRODUCT(C74:H74,$J$12:$O$12) -> 0.079798812 | AH74: =SUMPRODUCT(C74:H74,$J$13:$O$13) -> 0.54435734 | AI74: =SUMPRODUCT(C74:H74,$J$14:$O$14) -> 1.0450612
C75: 0.3722042 | D75: 1.3177657 | E75: -1.1414036 | F75: 1.6075327 | G75: -0.84133521 | H75: 0.42148667 | I75: =$C$14+AD75*$D$14 -> 27.410129 | J75: =$C$15+AE75*$D$15 -> 19.98554 | K75: =$C$16+AF75*$D$16 -> 0.52269618 | L75: =$C$17+AG75*$D$17 -> 1.3223494 | M75: =$C$18+AH75*$D$18 -> 4.0479626 | N75: =$C$19+AI75*$D$19 -> 1.934893 | O75: =(I75+J75)/2*$C$4*365-$C$5-$C$6 -> 25272437 | P75: =(L75/1.7*42+I75)*$C$7*365-$C$8-$C$9 -> 59910380 | Q75: =(N75-M75/2.8)*$C$10*365-$C$11-$C$12 -> 818155 | R75: =O75+P75+Q75 -> 86000972 | T75: Regression | U75: 6 | V75: 3.23825e+15 | W75: 540000000000000 | X75: 5.72e+31 | Y75: 0 | AD75: =SUMPRODUCT(C75:H75,$J$9:$O$9) -> 1.652944 | AE75: =SUMPRODUCT(C75:H75,$J$10:$O$10) -> 1.7032012 | AF75: =SUMPRODUCT(C75:H75,$J$11:$O$11) -> -0.33912568 | AG75: =SUMPRODUCT(C75:H75,$J$12:$O$12) -> 1.0561337 | AH75: =SUMPRODUCT(C75:H75,$J$13:$O$13) -> -0.52448602 | AI75: =SUMPRODUCT(C75:H75,$J$14:$O$14) -> 0.25646747
C76: 1.3031785 | D76: -1.9883444 | E76: 1.2043152 | F76: -0.21972775 | G76: 2.112319 | H76: 0.88695507 | I76: =$C$14+AD76*$D$14 -> 18.56249 | J76: =$C$15+AE76*$D$15 -> 12.755582 | K76: =$C$16+AF76*$D$16 -> 0.78573585 | L76: =$C$17+AG76*$D$17 -> 1.3983978 | M76: =$C$18+AH76*$D$18 -> 7.351917 | N76: =$C$19+AI76*$D$19 -> 2.8228393 | O76: =(I76+J76)/2*$C$4*365-$C$5-$C$6 -> 16698818 | P76: =(L76/1.7*42+I76)*$C$7*365-$C$8-$C$9 -> 52961236 | Q76: =(N76-M76/2.8)*$C$10*365-$C$11-$C$12 -> 329636.34 | R76: =O76+P76+Q76 -> 69989690 | T76: Residual | U76: 4993 | V76: 4.71003e-14 | W76: 9.43e-18 | AD76: =SUMPRODUCT(C76:H76,$J$9:$O$9) -> -0.49454116 | AE76: =SUMPRODUCT(C76:H76,$J$10:$O$10) -> -0.72295912 | AF76: =SUMPRODUCT(C76:H76,$J$11:$O$11) -> 2.0521441 | AG76: =SUMPRODUCT(C76:H76,$J$12:$O$12) -> 1.4018082 | AH76: =SUMPRODUCT(C76:H76,$J$13:$O$13) -> 3.1465744 | AI76: =SUMPRODUCT(C76:H76,$J$14:$O$14) -> 2.6563225
C77: 1.4639465 | D77: -0.49522349 | E77: 1.2409367 | F77: 2.4346262 | G77: -0.94184151 | H77: -1.8986914 | I77: =$C$14+AD77*$D$14 -> 26.562044 | J77: =$C$15+AE77*$D$15 -> 17.667621 | K77: =$C$16+AF77*$D$16 -> 0.76064023 | L77: =$C$17+AG77*$D$17 -> 1.5596338 | M77: =$C$18+AH77*$D$18 -> 3.2440589 | N77: =$C$19+AI77*$D$19 -> 1.3425702 | O77: =(I77+J77)/2*$C$4*365-$C$5-$C$6 -> 23584118 | P77: =(L77/1.7*42+I77)*$C$7*365-$C$8-$C$9 -> 64910474 | Q77: =(N77-M77/2.8)*$C$10*365-$C$11-$C$12 -> 307594 | R77: =O77+P77+Q77 -> 88802187 | T77: Total | U77: 4999 | V77: 3.23825e+15 | AD77: =SUMPRODUCT(C77:H77,$J$9:$O$9) -> 1.447098 | AE77: =SUMPRODUCT(C77:H77,$J$10:$O$10) -> 0.92537624 | AF77: =SUMPRODUCT(C77:H77,$J$11:$O$11) -> 1.8240021 | AG77: =SUMPRODUCT(C77:H77,$J$12:$O$12) -> 2.1346991 | AH77: =SUMPRODUCT(C77:H77,$J$13:$O$13) -> -1.4177124 | AI77: =SUMPRODUCT(C77:H77,$J$14:$O$14) -> -1.344405
C78: 2.1946226 | D78: -0.33466404 | E78: 0.54464992 | F78: -0.091025172 | G78: 0.51534177 | H78: 0.041769293 | I78: =$C$14+AD78*$D$14 -> 28.496286 | J78: =$C$15+AE78*$D$15 -> 19.883083 | K78: =$C$16+AF78*$D$16 -> 0.66842439 | L78: =$C$17+AG78*$D$17 -> 1.2121746 | M78: =$C$18+AH78*$D$18 -> 4.9784133 | N78: =$C$19+AI78*$D$19 -> 2.0731221 | O78: =(I78+J78)/2*$C$4*365-$C$5-$C$6 -> 25797010 | P78: =(L78/1.7*42+I78)*$C$7*365-$C$8-$C$9 -> 58279183 | Q78: =(N78-M78/2.8)*$C$10*365-$C$11-$C$12 -> 493507.92 | R78: =O78+P78+Q78 -> 84569701 | AD78: =SUMPRODUCT(C78:H78,$J$9:$O$9) -> 1.9165742 | AE78: =SUMPRODUCT(C78:H78,$J$10:$O$10) -> 1.6688199 | AF78: =SUMPRODUCT(C78:H78,$J$11:$O$11) -> 0.98567626 | AG78: =SUMPRODUCT(C78:H78,$J$12:$O$12) -> 0.55533909 | AH78: =SUMPRODUCT(C78:H78,$J$13:$O$13) -> 0.50934807 | AI78: =SUMPRODUCT(C78:H78,$J$14:$O$14) -> 0.63005985
C79: 1.9956471 | D79: 2.239375 | E79: 1.2317281 | F79: 0.019381922 | G79: -1.7749823 | H79: -1.1334634 | I79: =$C$14+AD79*$D$14 -> 38.392661 | J79: =$C$15+AE79*$D$15 -> 27.232306 | K79: =$C$16+AF79*$D$16 -> 0.65461033 | L79: =$C$17+AG79*$D$17 -> 1.0813979 | M79: =$C$18+AH79*$D$18 -> 2.2192696 | N79: =$C$19+AI79*$D$19 -> 1.1318035 | O79: =(I79+J79)/2*$C$4*365-$C$5-$C$6 -> 34993484 | P79: =(L79/1.7*42+I79)*$C$7*365-$C$8-$C$9 -> 64925808 | Q79: =(N79-M79/2.8)*$C$10*365-$C$11-$C$12 -> 567261.11 | R79: =O79+P79+Q79 -> 1.0048655e+08 | U79: Coefficients | V79: Standard Error | W79: t Stat | X79: P-value | Y79: Lower 95% | Z79: Upper 95% | AA79: Lower 95.0% | AB79: Upper 95.0% | AD79: =SUMPRODUCT(C79:H79,$J$9:$O$9) -> 4.3186072 | AE79: =SUMPRODUCT(C79:H79,$J$10:$O$10) -> 4.1350022 | AF79: =SUMPRODUCT(C79:H79,$J$11:$O$11) -> 0.86009395 | AG79: =SUMPRODUCT(C79:H79,$J$12:$O$12) -> -0.039100638 | AH79: =SUMPRODUCT(C79:H79,$J$13:$O$13) -> -2.5563671 | AI79: =SUMPRODUCT(C79:H79,$J$14:$O$14) -> -1.9140446
C80: 1.9535983 | D80: -1.3158189 | E80: 0.29298723 | F80: 0.19118194 | G80: 0.21051162 | H80: 0.74687141 | I80: =$C$14+AD80*$D$14 -> 24.096727 | J80: =$C$15+AE80*$D$15 -> 16.535408 | K80: =$C$16+AF80*$D$16 -> 0.64914763 | L80: =$C$17+AG80*$D$17 -> 1.2724122 | M80: =$C$18+AH80*$D$18 -> 5.274506 | N80: =$C$19+AI80*$D$19 -> 2.2215064 | O80: =(I80+J80)/2*$C$4*365-$C$5-$C$6 -> 21665681 | P80: =(L80/1.7*42+I80)*$C$7*365-$C$8-$C$9 -> 55376058 | Q80: =(N80-M80/2.8)*$C$10*365-$C$11-$C$12 -> 564830.61 | R80: =O80+P80+Q80 -> 77606570 | T80: Intercept | U80: -163 | V80: 5.37372e-10 | W80: -300000000000 | X80: 0 | Y80: -163 | Z80: -163 | AA80: -163 | AB80: -163 | AD80: =SUMPRODUCT(C80:H80,$J$9:$O$9) -> 0.84872003 | AE80: =SUMPRODUCT(C80:H80,$J$10:$O$10) -> 0.54543901 | AF80: =SUMPRODUCT(C80:H80,$J$11:$O$11) -> 0.81043298 | AG80: =SUMPRODUCT(C80:H80,$J$12:$O$12) -> 0.82914649 | AH80: =SUMPRODUCT(C80:H80,$J$13:$O$13) -> 0.83833997 | AI80: =SUMPRODUCT(C80:H80,$J$14:$O$14) -> 1.0310983
C81: 1.0670483 | D81: -0.58126836 | E81: 0.42760798 | F81: -0.80996755 | G81: -0.73253759 | H81: 1.6155412 | I81: =$C$14+AD81*$D$14 -> 23.406058 | J81: =$C$15+AE81*$D$15 -> 16.636965 | K81: =$C$16+AF81*$D$16 -> 0.58992569 | L81: =$C$17+AG81*$D$17 -> 1.0697453 | M81: =$C$18+AH81*$D$18 -> 4.8700339 | N81: =$C$19+AI81*$D$19 -> 2.1388311 | O81: =(I81+J81)/2*$C$4*365-$C$5-$C$6 -> 21351529 | P81: =(L81/1.7*42+I81)*$C$7*365-$C$8-$C$9 -> 49694391 | Q81: =(N81-M81/2.8)*$C$10*365-$C$11-$C$12 -> 668174.35 | R81: =O81+P81+Q81 -> 71714094 | T81: X Variable 1 | U81: 3.34073e-12 | V81: 1.05812e-11 | W81: 0.315724 | X81: 0.752225 | Y81: -1.7403e-11 | Z81: 2.41e-11 | AA81: -1.7e-11 | AB81: 2.41e-11 | AD81: =SUMPRODUCT(C81:H81,$J$9:$O$9) -> 0.68108207 | AE81: =SUMPRODUCT(C81:H81,$J$10:$O$10) -> 0.57951856 | AF81: =SUMPRODUCT(C81:H81,$J$11:$O$11) -> 0.27205177 | AG81: =SUMPRODUCT(C81:H81,$J$12:$O$12) -> -0.09206693 | AH81: =SUMPRODUCT(C81:H81,$J$13:$O$13) -> 0.38892651 | AI81: =SUMPRODUCT(C81:H81,$J$14:$O$14) -> 0.80765172
C82: 0.87818925 | D82: 0.24541416 | E82: 0.51951258 | F82: -0.18058163 | G82: -0.24903746 | H82: -1.422179 | I82: =$C$14+AD82*$D$14 -> 25.184429 | J82: =$C$15+AE82*$D$15 -> 17.737843 | K82: =$C$16+AF82*$D$16 -> 0.57570621 | L82: =$C$17+AG82*$D$17 -> 0.98784992 | M82: =$C$18+AH82*$D$18 -> 3.2967062 | N82: =$C$19+AI82*$D$19 -> 1.2867343 | O82: =(I82+J82)/2*$C$4*365-$C$5-$C$6 -> 22886931 | P82: =(L82/1.7*42+I82)*$C$7*365-$C$8-$C$9 -> 49450156 | Q82: =(N82-M82/2.8)*$C$10*365-$C$11-$C$12 -> 182739.21 | R82: =O82+P82+Q82 -> 72519827 | T82: X Variable 2 | U82: -4.19154e-11 | V82: 1.72897e-11 | W82: -2.42429 | X82: 0.015373 | Y82: -7.58109e-11 | Z82: -8e-12 | AA82: -7.6e-11 | AB82: -8e-12 | AD82: =SUMPRODUCT(C82:H82,$J$9:$O$9) -> 1.1127255 | AE82: =SUMPRODUCT(C82:H82,$J$10:$O$10) -> 0.94894063 | AF82: =SUMPRODUCT(C82:H82,$J$11:$O$11) -> 0.14278371 | AG82: =SUMPRODUCT(C82:H82,$J$12:$O$12) -> -0.46431854 | AH82: =SUMPRODUCT(C82:H82,$J$13:$O$13) -> -1.3592154 | AI82: =SUMPRODUCT(C82:H82,$J$14:$O$14) -> -1.4953126
C83: -0.23826234 | D83: -0.45890372 | E83: 0.75563101 | F83: -0.19353535 | G83: -1.8515225 | H83: -0.37437696 | I83: =$C$14+AD83*$D$14 -> 18.989693 | J83: =$C$15+AE83*$D$15 -> 13.264101 | K83: =$C$16+AF83*$D$16 -> 0.54191671 | L83: =$C$17+AG83*$D$17 -> 0.96510626 | M83: =$C$18+AH83*$D$18 -> 2.8119418 | N83: =$C$19+AI83*$D$19 -> 1.1732952 | O83: =(I83+J83)/2*$C$4*365-$C$5-$C$6 -> 17197806 | P83: =(L83/1.7*42+I83)*$C$7*365-$C$8-$C$9 -> 42712572 | Q83: =(N83-M83/2.8)*$C$10*365-$C$11-$C$12 -> 282589.99 | R83: =O83+P83+Q83 -> 60192967 | T83: X Variable 3 | U83: 2.79102e-10 | V83: 3.96211e-10 | W83: 0.704426 | X83: 0.4812 | Y83: -4.97647e-10 | Z83: 1.06e-09 | AA83: -5e-10 | AB83: 1.06e-09 | AD83: =SUMPRODUCT(C83:H83,$J$9:$O$9) -> -0.39085117 | AE83: =SUMPRODUCT(C83:H83,$J$10:$O$10) -> -0.55231506 | AF83: =SUMPRODUCT(C83:H83,$J$11:$O$11) -> -0.1643935 | AG83: =SUMPRODUCT(C83:H83,$J$12:$O$12) -> -0.5676988 | AH83: =SUMPRODUCT(C83:H83,$J$13:$O$13) -> -1.8978424 | AI83: =SUMPRODUCT(C83:H83,$J$14:$O$14) -> -1.8019048
C84: 0.47943043 | D84: 1.2691542 | E84: -0.77559151 | F84: -0.91684488 | G84: 1.4255213 | H84: 0.93400974 | I84: =$C$14+AD84*$D$14 -> 26.029313 | J84: =$C$15+AE84*$D$15 -> 19.676108 | K84: =$C$16+AF84*$D$16 -> 0.5266976 | L84: =$C$17+AG84*$D$17 -> 1.0037645 | M84: =$C$18+AH84*$D$18 -> 5.883336 | N84: =$C$19+AI84*$D$19 -> 2.4559308 | O84: =(I84+J84)/2*$C$4*365-$C$5-$C$6 -> 24371087 | P84: =(L84/1.7*42+I84)*$C$7*365-$C$8-$C$9 -> 50684731 | Q84: =(N84-M84/2.8)*$C$10*365-$C$11-$C$12 -> 593243.24 | R84: =O84+P84+Q84 -> 75649062 | T84: X Variable 4 | U84: 2.71453e-10 | V84: 2.00427e-10 | W84: 1.354372 | X84: 0.175679 | Y84: -1.21472e-10 | Z84: 6.64e-10 | AA84: -1.2e-10 | AB84: 6.64e-10 | AD84: =SUMPRODUCT(C84:H84,$J$9:$O$9) -> 1.3177943 | AE84: =SUMPRODUCT(C84:H84,$J$10:$O$10) -> 1.5993651 | AF84: =SUMPRODUCT(C84:H84,$J$11:$O$11) -> -0.30274908 | AG84: =SUMPRODUCT(C84:H84,$J$12:$O$12) -> -0.3919796 | AH84: =SUMPRODUCT(C84:H84,$J$13:$O$13) -> 1.5148178 | AI84: =SUMPRODUCT(C84:H84,$J$14:$O$14) -> 1.6646779
C85: 0.070188455 | D85: -0.23533367 | E85: 2.5864529 | F85: 2.217701 | G85: -1.0453916 | H85: -0.21418371 | I85: =$C$14+AD85*$D$14 -> 22.915259 | J85: =$C$15+AE85*$D$15 -> 15.590088 | K85: =$C$16+AF85*$D$16 -> 0.91891518 | L85: =$C$17+AG85*$D$17 -> 1.7735155 | M85: =$C$18+AH85*$D$18 -> 4.8427203 | N85: =$C$19+AI85*$D$19 -> 2.0113739 | O85: =(I85+J85)/2*$C$4*365-$C$5-$C$6 -> 20531540 | P85: =(L85/1.7*42+I85)*$C$7*365-$C$8-$C$9 -> 66543209 | Q85: =(N85-M85/2.8)*$C$10*365-$C$11-$C$12 -> 471282.39 | R85: =O85+P85+Q85 -> 87546031 | T85: X Variable 5 | U85: -597426.79 | V85: 4.85562e-11 | W85: -1.2e+16 | X85: 0 | Y85: -597426.79 | Z85: -597427 | AA85: -597427 | AB85: -597427 | AD85: =SUMPRODUCT(C85:H85,$J$9:$O$9) -> 0.56195617 | AE85: =SUMPRODUCT(C85:H85,$J$10:$O$10) -> 0.22821749 | AF85: =SUMPRODUCT(C85:H85,$J$11:$O$11) -> 3.2628653 | AG85: =SUMPRODUCT(C85:H85,$J$12:$O$12) -> 3.1068886 | AH85: =SUMPRODUCT(C85:H85,$J$13:$O$13) -> 0.35857807 | AI85: =SUMPRODUCT(C85:H85,$J$14:$O$14) -> 0.46317268
C86: -0.80228943 | D86: 0.95676156 | E86: -0.3133064 | F86: -0.40866058 | G86: -1.6045134 | H86: 0.40660393 | I86: =$C$14+AD86*$D$14 -> 21.225068 | J86: =$C$15+AE86*$D$15 -> 15.815394 | K86: =$C$16+AF86*$D$16 -> 0.44975441 | L86: =$C$17+AG86*$D$17 -> 0.88838824 | M86: =$C$18+AH86*$D$18 -> 3.1888147 | N86: =$C$19+AI86*$D$19 -> 1.4466027 | O86: =(I86+J86)/2*$C$4*365-$C$5-$C$6 -> 19750368 | P86: =(L86/1.7*42+I86)*$C$7*365-$C$8-$C$9 -> 43051601 | Q86: =(N86-M86/2.8)*$C$10*365-$C$11-$C$12 -> 514623.47 | R86: =O86+P86+Q86 -> 63316592 | T86: X Variable 6 | U86: 1672795 | V86: 1.19695e-10 | W86: 1.4e+16 | X86: 0 | Y86: 1672795 | Z86: 1672795 | AA86: 1672795 | AB86: 1672795 | AD86: =SUMPRODUCT(C86:H86,$J$9:$O$9) -> 0.1517155 | AE86: =SUMPRODUCT(C86:H86,$J$10:$O$10) -> 0.30382347 | AF86: =SUMPRODUCT(C86:H86,$J$11:$O$11) -> -1.0022327 | AG86: =SUMPRODUCT(C86:H86,$J$12:$O$12) -> -0.9164171 | AH86: =SUMPRODUCT(C86:H86,$J$13:$O$13) -> -1.4790948 | AI86: =SUMPRODUCT(C86:H86,$J$14:$O$14) -> -1.063236
C87: -0.53889536 | D87: 0.37116154 | E87: 0.068204477 | F87: 0.77613671 | G87: -1.2412311 | H87: -1.9562836 | I87: =$C$14+AD87*$D$14 -> 20.22633 | J87: =$C$15+AE87*$D$15 -> 14.308684 | K87: =$C$16+AF87*$D$16 -> 0.50379582 | L87: =$C$17+AG87*$D$17 -> 1.0064054 | M87: =$C$18+AH87*$D$18 -> 2.2572075 | N87: =$C$19+AI87*$D$19 -> 0.87371123 | O87: =(I87+J87)/2*$C$4*365-$C$5-$C$6 -> 18414300 | P87: =(L87/1.7*42+I87)*$C$7*365-$C$8-$C$9 -> 44963176 | Q87: =(N87-M87/2.8)*$C$10*365-$C$11-$C$12 -> 112860.56 | R87: =O87+P87+Q87 -> 63490337 | AD87: =SUMPRODUCT(C87:H87,$J$9:$O$9) -> -0.090696708 | AE87: =SUMPRODUCT(C87:H87,$J$10:$O$10) -> -0.20178381 | AF87: =SUMPRODUCT(C87:H87,$J$11:$O$11) -> -0.51094709 | AG87: =SUMPRODUCT(C87:H87,$J$12:$O$12) -> -0.37997527 | AH87: =SUMPRODUCT(C87:H87,$J$13:$O$13) -> -2.5142139 | AI87: =SUMPRODUCT(C87:H87,$J$14:$O$14) -> -2.6115913
C88: 1.5269257 | D88: 0.030433004 | E88: 1.0603129 | F88: -1.3849265 | G88: 0.43443908 | H88: -0.49192107 | I88: =$C$14+AD88*$D$14 -> 26.808139 | J88: =$C$15+AE88*$D$15 -> 18.994201 | K88: =$C$16+AF88*$D$16 -> 0.62919058 | L88: =$C$17+AG88*$D$17 -> 0.92126166 | M88: =$C$18+AH88*$D$18 -> 4.3780876 | N88: =$C$19+AI88*$D$19 -> 1.7090671 | O88: =(I88+J88)/2*$C$4*365-$C$5-$C$6 -> 24422770 | P88: =(L88/1.7*42+I88)*$C$7*365-$C$8-$C$9 -> 49428804 | Q88: =(N88-M88/2.8)*$C$10*365-$C$11-$C$12 -> 243169.16 | R88: =O88+P88+Q88 -> 74094744 | AD88: =SUMPRODUCT(C88:H88,$J$9:$O$9) -> 1.5068298 | AE88: =SUMPRODUCT(C88:H88,$J$10:$O$10) -> 1.3705371 | AF88: =SUMPRODUCT(C88:H88,$J$11:$O$11) -> 0.62900527 | AG88: =SUMPRODUCT(C88:H88,$J$12:$O$12) -> -0.76699247 | AH88: =SUMPRODUCT(C88:H88,$J$13:$O$13) -> -0.15768041 | AI88: =SUMPRODUCT(C88:H88,$J$14:$O$14) -> -0.35387257
C89: 0.066004597 | D89: -1.0566516 | E89: 0.57528532 | F89: -0.4037484 | G89: -0.72511785 | H89: -1.2898849 | I89: =$C$14+AD89*$D$14 -> 17.176089 | J89: =$C$15+AE89*$D$15 -> 11.773136 | K89: =$C$16+AF89*$D$16 -> 0.52715226 | L89: =$C$17+AG89*$D$17 -> 0.89291802 | M89: =$C$18+AH89*$D$18 -> 3.0524885 | N89: =$C$19+AI89*$D$19 -> 1.1036918 | O89: =(I89+J89)/2*$C$4*365-$C$5-$C$6 -> 15435594 | P89: =(L89/1.7*42+I89)*$C$7*365-$C$8-$C$9 -> 39125637 | Q89: =(N89-M89/2.8)*$C$10*365-$C$11-$C$12 -> 22448.73 | R89: =O89+P89+Q89 -> 54583680 | AD89: =SUMPRODUCT(C89:H89,$J$9:$O$9) -> -0.83104637 | AE89: =SUMPRODUCT(C89:H89,$J$10:$O$10) -> -1.052639 | AF89: =SUMPRODUCT(C89:H89,$J$11:$O$11) -> -0.29861582 | AG89: =SUMPRODUCT(C89:H89,$J$12:$O$12) -> -0.89582718 | AH89: =SUMPRODUCT(C89:H89,$J$13:$O$13) -> -1.6305683 | AI89: =SUMPRODUCT(C89:H89,$J$14:$O$14) -> -1.9900221
C90: -0.17754476 | D90: 1.3917181 | E90: -1.3909931 | F90: -0.27492878 | G90: 1.634278 | H90: -1.7776041 | I90: =$C$14+AD90*$D$14 -> 23.016593 | J90: =$C$15+AE90*$D$15 -> 17.352431 | K90: =$C$16+AF90*$D$16 -> 0.41828468 | L90: =$C$17+AG90*$D$17 -> 0.83934253 | M90: =$C$18+AH90*$D$18 -> 4.1519334 | N90: =$C$19+AI90*$D$19 -> 1.5448855 | O90: =(I90+J90)/2*$C$4*365-$C$5-$C$6 -> 21525374 | P90: =(L90/1.7*42+I90)*$C$7*365-$C$8-$C$9 -> 43629774 | Q90: =(N90-M90/2.8)*$C$10*365-$C$11-$C$12 -> 103637.45 | R90: =O90+P90+Q90 -> 65258785 | AD90: =SUMPRODUCT(C90:H90,$J$9:$O$9) -> 0.58655172 | AE90: =SUMPRODUCT(C90:H90,$J$10:$O$10) -> 0.8196078 | AF90: =SUMPRODUCT(C90:H90,$J$11:$O$11) -> -1.2883211 | AG90: =SUMPRODUCT(C90:H90,$J$12:$O$12) -> -1.1393521 | AH90: =SUMPRODUCT(C90:H90,$J$13:$O$13) -> -0.40896291 | AI90: =SUMPRODUCT(C90:H90,$J$14:$O$14) -> -0.79760688
C91: 0.49290615 | D91: 0.67801483 | E91: -0.76472185 | F91: 0.097435422 | G91: 0.44937529 | H91: -0.28896202 | I91: =$C$14+AD91*$D$14 -> 24.467729 | J91: =$C$15+AE91*$D$15 -> 17.886022 | K91: =$C$16+AF91*$D$16 -> 0.50618515 | L91: =$C$17+AG91*$D$17 -> 1.0498486 | M91: =$C$18+AH91*$D$18 -> 4.4269331 | N91: =$C$19+AI91*$D$19 -> 1.8439881 | O91: =(I91+J91)/2*$C$4*365-$C$5-$C$6 -> 22583759 | P91: =(L91/1.7*42+I91)*$C$7*365-$C$8-$C$9 -> 50262889 | Q91: =(N91-M91/2.8)*$C$10*365-$C$11-$C$12 -> 439682.72 | R91: =O91+P91+Q91 -> 73286331 | AD91: =SUMPRODUCT(C91:H91,$J$9:$O$9) -> 0.93876913 | AE91: =SUMPRODUCT(C91:H91,$J$10:$O$10) -> 0.99866498 | AF91: =SUMPRODUCT(C91:H91,$J$11:$O$11) -> -0.48922589 | AG91: =SUMPRODUCT(C91:H91,$J$12:$O$12) -> -0.18250637 | AH91: =SUMPRODUCT(C91:H91,$J$13:$O$13) -> -0.1034077 | AI91: =SUMPRODUCT(C91:H91,$J$14:$O$14) -> 0.010778708
C92: -0.03131163 | D92: 0.21570343 | E92: 0.52436798 | F92: 0.077875728 | G92: -1.1218942 | H92: -0.95491747 | I92: =$C$14+AD92*$D$14 -> 21.892476 | J92: =$C$15+AE92*$D$15 -> 15.51928 | K92: =$C$16+AF92*$D$16 -> 0.55436658 | L92: =$C$17+AG92*$D$17 -> 1.0084193 | M92: =$C$18+AH92*$D$18 -> 3.0020684 | N92: =$C$19+AI92*$D$19 -> 1.2220312 | O92: =(I92+J92)/2*$C$4*365-$C$5-$C$6 -> 19948366 | P92: =(L92/1.7*42+I92)*$C$7*365-$C$8-$C$9 -> 46674237 | Q92: =(N92-M92/2.8)*$C$10*365-$C$11-$C$12 -> 250528.71 | R92: =O92+P92+Q92 -> 66873132 | AD92: =SUMPRODUCT(C92:H92,$J$9:$O$9) -> 0.31370778 | AE92: =SUMPRODUCT(C92:H92,$J$10:$O$10) -> 0.20445652 | AF92: =SUMPRODUCT(C92:H92,$J$11:$O$11) -> -0.051212907 | AG92: =SUMPRODUCT(C92:H92,$J$12:$O$12) -> -0.37082153 | AH92: =SUMPRODUCT(C92:H92,$J$13:$O$13) -> -1.6865907 | AI92: =SUMPRODUCT(C92:H92,$J$14:$O$14) -> -1.6701858
C93: 0.57512615 | D93: 0.84165252 | E93: 0.61553936 | F93: -0.79943254 | G93: -0.58614195 | H93: -1.3182553 | I93: =$C$14+AD93*$D$14 -> 26.111334 | J93: =$C$15+AE93*$D$15 -> 18.719423 | K93: =$C$16+AF93*$D$16 -> 0.54366981 | L93: =$C$17+AG93*$D$17 -> 0.84905329 | M93: =$C$18+AH93*$D$18 -> 2.9317408 | N93: =$C$19+AI93*$D$19 -> 1.1591499 | O93: =(I93+J93)/2*$C$4*365-$C$5-$C$6 -> 23904660 | P93: =(L93/1.7*42+I93)*$C$7*365-$C$8-$C$9 -> 46955024 | Q93: =(N93-M93/2.8)*$C$10*365-$C$11-$C$12 -> 187356.62 | R93: =O93+P93+Q93 -> 71047041 | AD93: =SUMPRODUCT(C93:H93,$J$9:$O$9) -> 1.3377025 | AE93: =SUMPRODUCT(C93:H93,$J$10:$O$10) -> 1.2783299 | AF93: =SUMPRODUCT(C93:H93,$J$11:$O$11) -> -0.14845624 | AG93: =SUMPRODUCT(C93:H93,$J$12:$O$12) -> -1.0952123 | AH93: =SUMPRODUCT(C93:H93,$J$13:$O$13) -> -1.7647324 | AI93: =SUMPRODUCT(C93:H93,$J$14:$O$14) -> -1.8401355
C94: -1.0442968 | D94: -1.942761 | E94: 2.1379923 | F94: -0.59112229 | G94: 0.87786869 | H94: 0.91550096 | I94: =$C$14+AD94*$D$14 -> 9.9983877 | J94: =$C$15+AE94*$D$15 -> 7.0108296 | K94: =$C$16+AF94*$D$16 -> 0.78304038 | L94: =$C$17+AG94*$D$17 -> 1.2892908 | M94: =$C$18+AH94*$D$18 -> 6.664518 | N94: =$C$19+AI94*$D$19 -> 2.457661 | O94: =(I94+J94)/2*$C$4*365-$C$5-$C$6 -> 9068406.3 | P94: =(L94/1.7*42+I94)*$C$7*365-$C$8-$C$9 -> 41733299 | Q94: =(N94-M94/2.8)*$C$10*365-$C$11-$C$12 -> 129438.5 | R94: =O94+P94+Q94 -> 50931144 | AD94: =SUMPRODUCT(C94:H94,$J$9:$O$9) -> -2.5732069 | AE94: =SUMPRODUCT(C94:H94,$J$10:$O$10) -> -2.6507283 | AF94: =SUMPRODUCT(C94:H94,$J$11:$O$11) -> 2.0276398 | AG94: =SUMPRODUCT(C94:H94,$J$12:$O$12) -> 0.90586711 | AH94: =SUMPRODUCT(C94:H94,$J$13:$O$13) -> 2.3827978 | AI94: =SUMPRODUCT(C94:H94,$J$14:$O$14) -> 1.6693541
C95: -0.024966985 | D95: 0.15495275 | E95: -1.5553472 | F95: -0.14123338 | G95: 0.51455774 | H95: -0.83030627 | I95: =$C$14+AD95*$D$14 -> 19.669267 | J95: =$C$15+AE95*$D$15 -> 14.49616 | K95: =$C$16+AF95*$D$16 -> 0.37941355 | L95: =$C$17+AG95*$D$17 -> 0.84988953 | M95: =$C$18+AH95*$D$18 -> 3.8524882 | N95: =$C$19+AI95*$D$19 -> 1.525595 | O95: =(I95+J95)/2*$C$4*365-$C$5-$C$6 -> 18217213 | P95: =(L95/1.7*42+I95)*$C$7*365-$C$8-$C$9 -> 40551725 | Q95: =(N95-M95/2.8)*$C$10*365-$C$11-$C$12 -> 250264.99 | R95: =O95+P95+Q95 -> 59019203 | AD95: =SUMPRODUCT(C95:H95,$J$9:$O$9) -> -0.22590602 | AE95: =SUMPRODUCT(C95:H95,$J$10:$O$10) -> -0.13887244 | AF95: =SUMPRODUCT(C95:H95,$J$11:$O$11) -> -1.641695 | AG95: =SUMPRODUCT(C95:H95,$J$12:$O$12) -> -1.0914112 | AH95: =SUMPRODUCT(C95:H95,$J$13:$O$13) -> -0.74167975 | AI95: =SUMPRODUCT(C95:H95,$J$14:$O$14) -> -0.8497433
C96: -0.58525024 | D96: 0.70485695 | E96: 0.46406756 | F96: -0.4875729 | G96: -0.61736128 | H96: 0.31958277 | I96: =$C$14+AD96*$D$14 -> 21.208479 | J96: =$C$15+AE96*$D$15 -> 15.693699 | K96: =$C$16+AF96*$D$16 -> 0.56734784 | L96: =$C$17+AG96*$D$17 -> 1.0160368 | M96: =$C$18+AH96*$D$18 -> 4.229965 | N96: =$C$19+AI96*$D$19 -> 1.7615247 | O96: =(I96+J96)/2*$C$4*365-$C$5-$C$6 -> 19676626 | P96: =(L96/1.7*42+I96)*$C$7*365-$C$8-$C$9 -> 46179835 | Q96: =(N96-M96/2.8)*$C$10*365-$C$11-$C$12 -> 419412.36 | R96: =O96+P96+Q96 -> 66275873 | AD96: =SUMPRODUCT(C96:H96,$J$9:$O$9) -> 0.14768913 | AE96: =SUMPRODUCT(C96:H96,$J$10:$O$10) -> 0.26298619 | AF96: =SUMPRODUCT(C96:H96,$J$11:$O$11) -> 0.066798512 | AG96: =SUMPRODUCT(C96:H96,$J$12:$O$12) -> -0.33619657 | AH96: =SUMPRODUCT(C96:H96,$J$13:$O$13) -> -0.32226111 | AI96: =SUMPRODUCT(C96:H96,$J$14:$O$14) -> -0.21209534
C97: -1.2025009 | D97: -1.5443151 | E97: -0.32140437 | F97: 0.76911093 | G97: -0.69883962 | H97: 0.77770161 | I97: =$C$14+AD97*$D$14 -> 10.48575 | J97: =$C$15+AE97*$D$15 -> 7.4375349 | K97: =$C$16+AF97*$D$16 -> 0.52459936 | L97: =$C$17+AG97*$D$17 -> 1.2027218 | M97: =$C$18+AH97*$D$18 -> 4.7351263 | N97: =$C$19+AI97*$D$19 -> 1.9256057 | O97: =(I97+J97)/2*$C$4*365-$C$5-$C$6 -> 9555846.7 | P97: =(L97/1.7*42+I97)*$C$7*365-$C$8-$C$9 -> 40086556 | Q97: =(N97-M97/2.8)*$C$10*365-$C$11-$C$12 -> 392089.21 | R97: =O97+P97+Q97 -> 50034492 | AD97: =SUMPRODUCT(C97:H97,$J$9:$O$9) -> -2.454915 | AE97: =SUMPRODUCT(C97:H97,$J$10:$O$10) -> -2.5075386 | AF97: =SUMPRODUCT(C97:H97,$J$11:$O$11) -> -0.321824 | AG97: =SUMPRODUCT(C97:H97,$J$12:$O$12) -> 0.51237167 | AH97: =SUMPRODUCT(C97:H97,$J$13:$O$13) -> 0.23902926 | AI97: =SUMPRODUCT(C97:H97,$J$14:$O$14) -> 0.23136665
C98: 1.0808922 | D98: 0.88920604 | E98: 0.036031724 | F98: -1.1892342 | G98: -0.51676551 | H98: 2.2169526 | I98: =$C$14+AD98*$D$14 -> 28.552354 | J98: =$C$15+AE98*$D$15 -> 21.029978 | K98: =$C$16+AF98*$D$16 -> 0.56724232 | L98: =$C$17+AG98*$D$17 -> 1.0268782 | M98: =$C$18+AH98*$D$18 -> 5.2040791 | N98: =$C$19+AI98*$D$19 -> 2.3875333 | O98: =(I98+J98)/2*$C$4*365-$C$5-$C$6 -> 26438509 | P98: =(L98/1.7*42+I98)*$C$7*365-$C$8-$C$9 -> 53770092 | Q98: =(N98-M98/2.8)*$C$10*365-$C$11-$C$12 -> 884634.46 | R98: =O98+P98+Q98 -> 81093235 | AD98: =SUMPRODUCT(C98:H98,$J$9:$O$9) -> 1.9301831 | AE98: =SUMPRODUCT(C98:H98,$J$10:$O$10) -> 2.053684 | AF98: =SUMPRODUCT(C98:H98,$J$11:$O$11) -> 0.065839268 | AG98: =SUMPRODUCT(C98:H98,$J$12:$O$12) -> -0.28691744 | AH98: =SUMPRODUCT(C98:H98,$J$13:$O$13) -> 0.76008786 | AI98: =SUMPRODUCT(C98:H98,$J$14:$O$14) -> 1.4798196
... C5027: 0.50146682 | D5027: -0.78379921 | E5027: 1.4326204 | F5027: -0.32638332 | G5027: -2.0675136 | H5027: -0.50309735 | I5027: =$C$14+AD5027*$D$14 -> 21.258783 | J5027: =$C$15+AE5027*$D$15 -> 14.455639 | K5027: =$C$16+AF5027*$D$16 -> 0.60585512 | L5027: =$C$17+AG5027*$D$17 -> 0.99746593 | M5027: =$C$18+AH5027*$D$18 -> 2.6502986 | N5027: =$C$19+AI5027*$D$19 -> 1.1063592 | O5027: =(I5027+J5027)/2*$C$4*365-$C$5-$C$6 -> 19043237 | P5027: =(L5027/1.7*42+I5027)*$C$7*365-$C$8-$C$9 -> 45772482 | Q5027: =(N5027-M5027/2.8)*$C$10*365-$C$11-$C$12 -> 267189.76 | R5027: =O5027+P5027+Q5027 -> 65082909 | AD5027: =SUMPRODUCT(C5027:H5027,$J$9:$O$9) -> 0.15989875 | AE5027: =SUMPRODUCT(C5027:H5027,$J$10:$O$10) -> -0.15247025 | AF5027: =SUMPRODUCT(C5027:H5027,$J$11:$O$11) -> 0.41686472 | AG5027: =SUMPRODUCT(C5027:H5027,$J$12:$O$12) -> -0.42060942 | AH5027: =SUMPRODUCT(C5027:H5027,$J$13:$O$13) -> -2.0774461 | AI5027: =SUMPRODUCT(C5027:H5027,$J$14:$O$14) -> -1.982813
I5029: =MEDIAN(I$428:I$5027) -> 20.695652 | J5029: =MEDIAN(J$428:J$5027) -> 15.012561 | K5029: =MEDIAN(K$428:K$5027) -> 0.55967462 | L5029: =MEDIAN(L$428:L$5027) -> 1.0922067 | M5029: =MEDIAN(M$428:M$5027) -> 4.5299126 | N5029: =MEDIAN(N$428:N$5027) -> 1.8475023
...

Sheet Arvind 2
A1: Stochastic Drivers | B1: Mean | C1: ST. Dev | E1: Driver | F1: ULS Spread | G1: CBOB Spread | H1: RD Feed (UCO) | I1: RD RIN | J1: Eth. Feed (Corn) | K1: Eth. Price (Ethanol) | R1: Driver | S1: Refining OI Beta | T1: RD OI Beta | U1: Ethanol OI Beta | V1: Base Refining OI | W1: Base RD OI | X1: Base Ethanol OI
A2: Ref. Spread ULS Diesel less WTI | B2: 20.6 | C2: 4.12 | E2: 1. Ref. Spread ULS | F2: 1 | G2: 0.9 | H2: 0.15 | I2: 0.1 | J2: -0.1 | K2: 0.05 | R2: 1. Ref. Spread ULS | S2: 0.53 | T2: 0.997 | U2: 0 | V2: 1307 | W2: 2732 | X2: 4583
A3: Ref. Spread CBOB Gas less WTI | B3: 14.91 | C3: 2.98 | E3: 2. Ref. Spread CBOB | F3: 0.9 | G3: 1 | H3: 0.1 | I3: 0.05 | J3: -0.05 | K3: 0.1 | R3: 2. Ref. Spread CBOB | S3: 0.53 | T3: 0 | U3: 0
A4: RD Feedstock Cost (USGC UCO) | B4: 0.56 | C4: 0.11 | E4: 3. RD Feed (UCO) | F4: 0.15 | G4: 0.1 | H4: 1 | I4: 0.5 | J4: 0.35 | K4: 0.25 | R4: 3. RD Feed (UCO) | S4: 0 | T4: 0 | U4: 0
A5: RD Reg. Price (Biodiesel RIN) | B5: 1.09 | C5: 0.22 | E5: 4. RD RIN | F5: 0.1 | G5: 0.05 | H5: 0.5 | I5: 1 | J5: 0.3 | K5: 0.4 | R5: 4. RD RIN | S5: 0 | T5: 24.6 | U5: 0
A6: Eth. Feedstock Cost (CBOT Corn) | B6: 4.52 | C6: 0.9 | E6: 5. Eth. Feed (Corn) | F6: -0.1 | G6: -0.05 | H6: 0.35 | I6: 0.3 | J6: 1 | K6: 0.8 | R6: 5. Eth. Feed (Corn) | S6: 0 | T6: 0 | U6: -0.597
A7: Eth. Product Price (NY Harbor Ethanol) | B7: 1.84 | C7: 0.37 | E7: 6. Eth. Price (Ethanol) | F7: 0.05 | G7: 0.1 | H7: 0.25 | I7: 0.4 | J7: 0.8 | K7: 1 | R7: 6. Eth. Price (Ethanol) | S7: 0 | T7: 0 | U7: 1.67
D14: SUMMARY OUTPUT
D16: Regression Statistics
D17: Multiple R | E17: 1
D18: R Square | E18: 1
D19: Adjusted R Square | E19: 1
D20: Standard Error | E20: 6.91271e-09
D21: Observations | E21: 5000
D23: ANOVA
E24: df | F24: SS | G24: MS | H24: F | I24: Significance F
D25: Regression | E25: 6 | F25: 6.82794e+16 | G25: 1.14e+16 | H25: 2.38e+32 | I25: 0
D26: Residual | E26: 4993 | F26: 2.38594e-13 | G26: 4.78e-17
D27: Total | E27: 4999 | F27: 6.82794e+16
E29: Coefficients | F29: Standard Error | G29: t Stat | H29: P-value | I29: Lower 95% | J29: Upper 95% | K29: Lower 95.0% | L29: Upper 95.0%
D30: Intercept | E30: -2014 | F30: 1.20949e-09 | G30: -1700000000000 | H30: 0 | I30: -2014 | J30: -2014 | K30: -2014 | L30: -2014
D31: X Variable 1 | E31: 533265 | F31: 2.40354e-11 | G31: 2.22e+16 | H31: 0 | I31: 533265 | J31: 533265 | K31: 533265 | L31: 533265
D32: X Variable 2 | E32: 533265 | F32: 3.94736e-11 | G32: 1.35e+16 | H32: 0 | I32: 533265 | J32: 533265 | K32: 533265 | L32: 533265
D33: X Variable 3 | E33: 1.73225e-10 | F33: 9.02135e-10 | G33: 0.192017 | H33: 0.847737 | I33: -1.59535e-09 | J33: 1.94e-09 | K33: -1.6e-09 | L33: 1.94e-09
D34: X Variable 4 | E34: -4.63704e-10 | F34: 4.43929e-10 | G34: -1.04455 | H34: 0.296284 | I34: -1.334e-09 | J34: 4.07e-10 | K34: -1.3e-09 | L34: 4.07e-10
D35: X Variable 5 | E35: -2.90703e-10 | F35: 1.10024e-10 | G35: -2.64218 | H35: 0.008263 | I35: -5.06398e-10 | J35: -7.5e-11 | K35: -5.1e-10 | L35: -7.5e-11
D36: X Variable 6 | E36: -2.76609e-10 | F36: 2.59822e-10 | G36: -1.06461 | H36: 0.287105 | I36: -7.85975e-10 | J36: 2.33e-10 | K36: -7.9e-10 | L36: 2.33e-10
D38: SUMMARY OUTPUT
D40: Regression Statistics
D41: Multiple R | E41: 1
D42: R Square | E42: 1
D43: Adjusted R Square | E43: 1
D44: Standard Error | E44: 2.64933e-08
D45: Observations | E45: 5000
D47: ANOVA
E48: df | F48: SS | G48: MS | H48: F | I48: Significance F
D49: Regression | E49: 6 | F49: 2.66105e+17 | G49: 4.44e+16 | H49: 6.32e+31 | I49: 0
D50: Residual | E50: 4993 | F50: 3.50455e-12 | G50: 7.02e-16
D51: Total | E51: 4999 | F51: 2.66105e+17
E53: Coefficients | F53: Standard Error | G53: t Stat | H53: P-value | I53: Lower 95% | J53: Upper 95% | K53: Lower 95.0% | L53: Upper 95.0%
D54: Intercept | E54: -133 | F54: 4.57892e-09 | G54: -29000000000 | H54: 0 | I54: -133 | J54: -133 | K54: -133 | L54: -133
D55: X Variable 1 | E55: 997180 | F55: 9.11221e-11 | G55: 1.09e+16 | H55: 0 | I55: 997180 | J55: 997180 | K55: 997180 | L55: 997180
D56: X Variable 2 | E56: 5.69507e-10 | F56: 1.50247e-10 | G56: 3.790485 | H56: 0.000152 | I56: 2.74958e-10 | J56: 8.64e-10 | K56: 2.75e-10 | L56: 8.64e-10
D57: X Variable 3 | E57: 1.17304e-09 | F57: 3.38906e-09 | G57: 0.346127 | H57: 0.729262 | I57: -5.471e-09 | J57: 7.82e-09 | K57: -5.5e-09 | L57: 7.82e-09
D58: X Variable 4 | E58: 24636212 | F58: 1.72008e-09 | G58: 1.43e+16 | H58: 0 | I58: 24636212 | J58: 24636212 | K58: 24636212 | L58: 24636212
D59: X Variable 5 | E59: 7.60062e-10 | F59: 4.16177e-10 | G59: 1.826293 | H59: 0.067866 | I59: -5.58286e-11 | J59: 1.58e-09 | K59: -5.6e-11 | L59: 1.58e-09
D60: X Variable 6 | E60: -3.30924e-10 | F60: 1.01102e-09 | G60: -0.32732 | H60: 0.743441 | I60: -2.31296e-09 | J60: 1.65e-09 | K60: -2.3e-09 | L60: 1.65e-09
D62: SUMMARY OUTPUT
D64: Regression Statistics
D65: Multiple R | E65: 1
D66: R Square | E66: 1
D67: Adjusted R Square | E67: 1
D68: Standard Error | E68: 3.07136e-09
D69: Observations | E69: 5000
D71: ANOVA
E72: df | F72: SS | G72: MS | H72: F | I72: Significance F
D73: Regression | E73: 6 | F73: 3.23825e+15 | G73: 540000000000000 | H73: 5.72e+31 | I73: 0
D74: Residual | E74: 4993 | F74: 4.71003e-14 | G74: 9.43e-18
D75: Total | E75: 4999 | F75: 3.23825e+15
E77: Coefficients | F77: Standard Error | G77: t Stat | H77: P-value | I77: Lower 95% | J77: Upper 95% | K77: Lower 95.0% | L77: Upper 95.0%
D78: Intercept | E78: -163 | F78: 5.37372e-10 | G78: -300000000000 | H78: 0 | I78: -163 | J78: -163 | K78: -163 | L78: -163
D79: X Variable 1 | E79: 3.34073e-12 | F79: 1.05812e-11 | G79: 0.315724 | H79: 0.752225 | I79: -1.7403e-11 | J79: 2.41e-11 | K79: -1.7e-11 | L79: 2.41e-11
D80: X Variable 2 | E80: -4.19154e-11 | F80: 1.72897e-11 | G80: -2.42429 | H80: 0.015373 | I80: -7.58109e-11 | J80: -8e-12 | K80: -7.6e-11 | L80: -8e-12
D81: X Variable 3 | E81: 2.79102e-10 | F81: 3.96211e-10 | G81: 0.704426 | H81: 0.4812 | I81: -4.97647e-10 | J81: 1.06e-09 | K81: -5e-10 | L81: 1.06e-09
D82: X Variable 4 | E82: 2.71453e-10 | F82: 2.00427e-10 | G82: 1.354372 | H82: 0.175679 | I82: -1.21472e-10 | J82: 6.64e-10 | K82: -1.2e-10 | L82: 6.64e-10
D83: X Variable 5 | E83: -597426.79 | F83: 4.85562e-11 | G83: -1.2e+16 | H83: 0 | I83: -597426.79 | J83: -597427 | K83: -597427 | L83: -597427
D84: X Variable 6 | E84: 1672795 | F84: 1.19695e-10 | G84: 1.4e+16 | H84: 0 | I84: 1672795 | J84: 1672795 | K84: 1672795 | L84: 1672795

Sheet Krishna
V1: Quarter | W1: Utilization (%) | X1: Inventory | Y1: A/P | Z1: COGS
V2: 2020 Q1 | W2: 0.9 | X2: 3675 | Y2: 5906 | Z2: 22250 | AC2: Utilization (%) | AD2: Inventory | AE2: A/P | AF2: COGS
V3: 2020 Q2 | W3: 0.74 | X3: 5420 | Y3: 4652 | Z3: 7074 | AB3: Mean | AC3: =AVERAGE(W2:W23) -> 0.89818182 | AD3: =AVERAGE(X2:X23) -> 6709.6364 | AE3: =AVERAGE(Y2:Y23) -> 11019.409 | AF3: =AVERAGE(Z2:Z23) -> 27589.636
V4: 2020 Q3 | W4: 0.8 | X4: 5357 | Y4: 5237 | Z4: 14266 | AB4: Standard Deviation | AC4: =STDEV(W2:W23) -> 0.063443741 | AD4: =STDEV(X2:X23) -> 1030.3452 | AE4: =STDEV(Y2:Y23) -> 3192.4928 | AF4: =STDEV(Z2:Z23) -> 8206.1506
V5: 2020 Q4 | W5: 0.81 | X5: 6038 | Y5: 6082 | Z5: 14962
V6: 2021 Q1 | W6: 0.77 | X6: 5908 | Y6: 9113 | Z6: 20648
V7: 2021 Q2 | W7: 0.9 | X7: 6103 | Y7: 10168 | Z7: 23921
V8: 2021 Q3 | W8: 0.91 | X8: 6227 | Y8: 9820 | Z8: 26362
V9: 2021 Q4 | W9: 0.96 | X9: 6265 | Y9: 12495 | Z9: 31914
V10: 2022 Q1 | W10: 0.89 | X10: 7174 | Y10: 15236 | Z10: 34905
V11: 2022 Q2 | W11: 0.94 | X11: 7147 | Y11: 16643 | Z11: 43318
V12: 2022 Q3 | W12: 0.95 | X12: 6628 | Y12: 13003 | Z12: 38597
V13: 2022 Q4 | W13: 0.97 | X13: 6752 | Y13: 12728 | Z13: 35145
V14: 2023 Q1 | W14: 0.93 | X14: 7455 | Y14: 10498 | Z14: 30060
V15: 2023 Q2 | W15: 0.94 | X15: 6961 | Y15: 10825 | Z15: 29421
V16: 2023 Q3 | W16: 0.95 | X16: 7513 | Y16: 13342 | Z16: 32495
... V23: 2025 Q2 | W23: 0.92 | X23: 7538 | Y23: 11499 | Z23: 26192

Sheet Krishna_V2
A1: Utilization | B1: 0.74 | C1: 0.77 | D1: 0.8 | E1: 0.81 | F1: 0.87 | G1: 0.89 | H1: 0.9 | I1: 0.91 | J1: 0.92 | K1: 0.93 | L1: 0.94 | M1: 0.95 | N1: 0.96 | O1: 0.97 | S1: Item | T1: Observations | U1: Correlation with Utilization | V1: Regression Slope | W1: Intercept | X1: R^2 | Y1: Standard Error
A2: Probability | B2: =1/22 -> 0.045454545 | C2: =1/22 -> 0.045454545 | D2: =1/22 -> 0.045454545 | E2: =1/22 -> 0.045454545 | F2: =1/22 -> 0.045454545 | G2: =2/22 -> 0.090909091 | H2: =3/22 -> 0.13636364 | I2: =1/22 -> 0.045454545 | J2: =1/22 -> 0.045454545 | K2: =1/22 -> 0.045454545 | L2: =5/22 -> 0.22727273 | M2: =2/22 -> 0.090909091 | N2: =1/22 -> 0.045454545 | O2: =1/22 -> 0.045454545 | S2: Inventory | T2: 21 | U2: 0.64899611 | V2: 7938.4225 | W2: -275.317 | X2: 0.421196 | Y2: 620.68411
A3: ummulative | B3: =B2 -> 0.045454545 | C3: =B3+C2 -> 0.090909091 | D3: =C3+D2 -> 0.13636364 | E3: =D3+E2 -> 0.18181818 | F3: =E3+F2 -> 0.22727273 | G3: =F3+G2 -> 0.31818182 | H3: =G3+H2 -> 0.45454545 | I3: =H3+I2 -> 0.5 | J3: =I3+J2 -> 0.54545455 | ... O3: =N3+O2 -> 1 | S3: A/P | T3: 22 | U3: 0.72023883 | V3: 36242.461 | W3: -21532.9 | X3: 0.518744 | Y3: 2269.4085
S4: COGS | T4: 22 | U4: 0.84122396 | V4: 108808.38 | W4: -70140.1 | X4: 0.7076577 | Y4: 4546.5286
A5: Iterations | B5: Rand | C5: Utilization | D5: Inventory | E5: Accounts Payable | F5: COGS | G5: Change in Inventory | H5: Change in Accounts Payable | I5: Change in COGS | J5: Net Working Capital | L5: Inventory | M5: Accounts Payable | N5: COGS | O5: Change in Inventory | P5: Change in Accounts Payable | Q5: Change in COGS | R5: Net Working Capital | S5: Utilization
A6: 1 | B6: =RAND() -> 0.66687677 | C6: =IF(B6<=$B$3, $B$1, IF(B6<=$C$3, $C$1, IF(B6<=$D$3, $D$1, IF(B6<=$E$3, $E$1, IF(B6<=$F$3, $F$1, IF(B6<=$G$3, $G$1, IF(B6<=$H$3, $H$1, IF(B6<=$I$3, $I$1, IF(B6<=$J$3, $J$1, IF(B6<=$K$3, $K$1, IF(B6<=$L$3, $L$1, IF(B6<=$M$3, $M$1, IF(B6<=$N$3, $N$1, IF(B6<=$O$3, $O$1, "Error")))))))))))))) -> 0.94 | D6: =$W$2+$V$2*C6+$Y$2*_xlfn.NORM.INV(RAND(),0,1) -> 6923.0784 | E6: =MAX(0,$W$3+$V$3*C6+$Y$3*_xlfn.NORM.INV(RAND(),0,1)) -> 16482.615 | F6: =$W$4+$V$4*C6+$Y$4*_xlfn.NORM.INV(RAND(),0,1) -> 39059.481 | G6: =D6-Krishna!$AD$3 -> 213.44208 | H6: =E6-Krishna!$AE$3 -> 5463.2062 | I6: =F6-Krishna!$AF$3 -> 11469.845 | J6: =D6-E6 -> -9559.5368 | K6: Average | L6: =AVERAGE(D6:D5005) -> 6855.5269 | M6: =AVERAGE(E6:E5005) -> 10985.117 | N6: =AVERAGE(F6:F5005) -> 27558.865 | O6: =AVERAGE(G6:G5005) -> 145.89054 | P6: =AVERAGE(H6:H5005) -> -34.292093 | Q6: =AVERAGE(I6:I5005) -> -30.770984 | R6: =AVERAGE(J6:J5005) -> -4129.5901 | S6: =AVERAGE(C6:C5005) -> 0.897636
A7: 2 | B7: =RAND() -> 0.54678462 | C7: =IF(B7<=$B$3, $B$1, IF(B7<=$C$3, $C$1, IF(B7<=$D$3, $D$1, IF(B7<=$E$3, $E$1, IF(B7<=$F$3, $F$1, IF(B7<=$G$3, $G$1, IF(B7<=$H$3, $H$1, IF(B7<=$I$3, $I$1, IF(B7<=$J$3, $J$1, IF(B7<=$K$3, $K$1, IF(B7<=$L$3, $L$1, IF(B7<=$M$3, $M$1, IF(B7<=$N$3, $N$1, IF(B7<=$O$3, $O$1, "Error")))))))))))))) -> 0.93 | D7: =$W$2+$V$2*C7+$Y$2*_xlfn.NORM.INV(RAND(),0,1) -> 6657.9657 | E7: =MAX(0,$W$3+$V$3*C7+$Y$3*_xlfn.NORM.INV(RAND(),0,1)) -> 15418.07 | F7: =$W$4+$V$4*C7+$Y$4*_xlfn.NORM.INV(RAND(),0,1) -> 28426.426 | G7: =D7-Krishna!$AD$3 -> -51.670624 | H7: =E7-Krishna!$AE$3 -> 4398.6608 | I7: =F7-Krishna!$AF$3 -> 836.78914 | J7: =D7-E7 -> -8760.1041 | K7: Median - Normal | L7: =MEDIAN(D6:D5005) -> 6897.126 | M7: =MEDIAN(E6:E5005) -> 11298.984 | N7: =MEDIAN(F6:F5005) -> 29018.003 | O7: =MEDIAN(G6:G5005) -> 187.4896 | P7: =MEDIAN(H6:H5005) -> 279.57508 | Q7: =MEDIAN(I6:I5005) -> 1428.3664 | R7: =MEDIAN(J6:J5005) -> -4288.0676 | S7: =MEDIAN(C6:C5005) -> 0.92
A8: 3 | B8: =RAND() -> 0.33476222 | C8: =IF(B8<=$B$3, $B$1, IF(B8<=$C$3, $C$1, IF(B8<=$D$3, $D$1, IF(B8<=$E$3, $E$1, IF(B8<=$F$3, $F$1, IF(B8<=$G$3, $G$1, IF(B8<=$H$3, $H$1, IF(B8<=$I$3, $I$1, IF(B8<=$J$3, $J$1, IF(B8<=$K$3, $K$1, IF(B8<=$L$3, $L$1, IF(B8<=$M$3, $M$1, IF(B8<=$N$3, $N$1, IF(B8<=$O$3, $O$1, "Error")))))))))))))) -> 0.9 | D8: =$W$2+$V$2*C8+$Y$2*_xlfn.NORM.INV(RAND(),0,1) -> 6080.4995 | E8: =MAX(0,$W$3+$V$3*C8+$Y$3*_xlfn.NORM.INV(RAND(),0,1)) -> 11424.262 | F8: =$W$4+$V$4*C8+$Y$4*_xlfn.NORM.INV(RAND(),0,1) -> 33866.958 | G8: =D8-Krishna!$AD$3 -> -629.13689 | H8: =E8-Krishna!$AE$3 -> 404.85325 | I8: =F8-Krishna!$AF$3 -> 6277.3214 | J8: =D8-E8 -> -5343.7629 | K8: Percentile (5th) - Worst | L8: =_xlfn.PERCENTILE.EXC(D6:D5005, 0.05) -> 5451.5933 | M8: =_xlfn.PERCENTILE.EXC(E6:E5005, 0.05) -> 5199.8986 | N8: =_xlfn.PERCENTILE.EXC(F6:F5005, 0.05) -> 11660.135 | O8: =_xlfn.PERCENTILE.EXC(G6:G5005, 0.05) -> -1258.043 | P8: =_xlfn.PERCENTILE.EXC(H6:H5005, 0.05) -> -5819.5105 | Q8: =_xlfn.PERCENTILE.EXC(I6:I5005, 0.05) -> -15929.501 | R8: =_xlfn.PERCENTILE.INC(J6:J5005,0.05) -> -8648.0595 | S8: =_xlfn.PERCENTILE.INC(C6:C5005,0.05) -> 0.77
A9: 4 | B9: =RAND() -> 0.16938606 | C9: =IF(B9<=$B$3, $B$1, IF(B9<=$C$3, $C$1, IF(B9<=$D$3, $D$1, IF(B9<=$E$3, $E$1, IF(B9<=$F$3, $F$1, IF(B9<=$G$3, $G$1, IF(B9<=$H$3, $H$1, IF(B9<=$I$3, $I$1, IF(B9<=$J$3, $J$1, IF(B9<=$K$3, $K$1, IF(B9<=$L$3, $L$1, IF(B9<=$M$3, $M$1, IF(B9<=$N$3, $N$1, IF(B9<=$O$3, $O$1, "Error")))))))))))))) -> 0.81 | D9: =$W$2+$V$2*C9+$Y$2*_xlfn.NORM.INV(RAND(),0,1) -> 6084.7696 | E9: =MAX(0,$W$3+$V$3*C9+$Y$3*_xlfn.NORM.INV(RAND(),0,1)) -> 8054.4621 | F9: =$W$4+$V$4*C9+$Y$4*_xlfn.NORM.INV(RAND(),0,1) -> 21609.077 | G9: =D9-Krishna!$AD$3 -> -624.86679 | H9: =E9-Krishna!$AE$3 -> -2964.947 | I9: =F9-Krishna!$AF$3 -> -5980.5595 | J9: =D9-E9 -> -1969.6925 | K9: Percentile (95th) - Best | L9: =_xlfn.PERCENTILE.EXC(D6:D5005, 0.95) -> 8065.4238 | M9: =_xlfn.PERCENTILE.EXC(E6:E5005, 0.95) -> 15685.597 | N9: =_xlfn.PERCENTILE.EXC(F6:F5005, 0.95) -> 38708.33 | O9: =_xlfn.PERCENTILE.EXC(G6:G5005, 0.95) -> 1355.7875 | P9: =_xlfn.PERCENTILE.EXC(H6:H5005, 0.95) -> 4666.1875 | Q9: =_xlfn.PERCENTILE.EXC(I6:I5005, 0.95) -> 11118.693 | R9: =_xlfn.PERCENTILE.INC(J6:J5005,0.95) -> 896.47307 | S9: =_xlfn.PERCENTILE.INC(C6:C5005,0.95) -> 0.96
A10: 5 | B10: =RAND() -> 0.750507 | C10: =IF(B10<=$B$3, $B$1, IF(B10<=$C$3, $C$1, IF(B10<=$D$3, $D$1, IF(B10<=$E$3, $E$1, IF(B10<=$F$3, $F$1, IF(B10<=$G$3, $G$1, IF(B10<=$H$3, $H$1, IF(B10<=$I$3, $I$1, IF(B10<=$J$3, $J$1, IF(B10<=$K$3, $K$1, IF(B10<=$L$3, $L$1, IF(B10<=$M$3, $M$1, IF(B10<=$N$3, $N$1, IF(B10<=$O$3, $O$1, "Error")))))))))))))) -> 0.94 | D10: =$W$2+$V$2*C10+$Y$2*_xlfn.NORM.INV(RAND(),0,1) -> 7071.8645 | E10: =MAX(0,$W$3+$V$3*C10+$Y$3*_xlfn.NORM.INV(RAND(),0,1)) -> 13840.617 | F10: =$W$4+$V$4*C10+$Y$4*_xlfn.NORM.INV(RAND(),0,1) -> 34046.199 | G10: =D10-Krishna!$AD$3 -> 362.22811 | H10: =E10-Krishna!$AE$3 -> 2821.2074 | I10: =F10-Krishna!$AF$3 -> 6456.5622 | J10: =D10-E10 -> -6768.7521 | K10: Minimum | L10: =MIN(D6:D5005) -> 3701.826 | M10: =MIN(E6:E5005) -> 0 | N10: =MIN(F6:F5005) -> -3188.1612 | O10: =MIN(G6:G5005) -> -3007.8103 | P10: =MIN(H6:H5005) -> -11019.409 | Q10: =MIN(I6:I5005) -> -30777.798 | R10: =MIN(J6:J5005) -> -14567.278 | S10: =MIN(C6:C5005) -> 0.74
A11: 6 | B11: =RAND() -> 0.42669591 | C11: =IF(B11<=$B$3, $B$1, IF(B11<=$C$3, $C$1, IF(B11<=$D$3, $D$1, IF(B11<=$E$3, $E$1, IF(B11<=$F$3, $F$1, IF(B11<=$G$3, $G$1, IF(B11<=$H$3, $H$1, IF(B11<=$I$3, $I$1, IF(B11<=$J$3, $J$1, IF(B11<=$K$3, $K$1, IF(B11<=$L$3, $L$1, IF(B11<=$M$3, $M$1, IF(B11<=$N$3, $N$1, IF(B11<=$O$3, $O$1, "Error")))))))))))))) -> 0.9 | D11: =$W$2+$V$2*C11+$Y$2*_xlfn.NORM.INV(RAND(),0,1) -> 7195.2533 | E11: =MAX(0,$W$3+$V$3*C11+$Y$3*_xlfn.NORM.INV(RAND(),0,1)) -> 8197.1828 | F11: =$W$4+$V$4*C11+$Y$4*_xlfn.NORM.INV(RAND(),0,1) -> 28404.194 | G11: =D11-Krishna!$AD$3 -> 485.61691 | H11: =E11-Krishna!$AE$3 -> -2822.2263 | I11: =F11-Krishna!$AF$3 -> 814.55763 | J11: =D11-E11 -> -1001.9295 | K11: Maximum | L11: =MAX(D6:D5005) -> 9609.6816 | M11: =MAX(E6:E5005) -> 22553.022 | N11: =MAX(F6:F5005) -> 47282.847 | O11: =MAX(G6:G5005) -> 2900.0452 | P11: =MAX(H6:H5005) -> 11533.613 | Q11: =MAX(I6:I5005) -> 19693.211 | R11: =MAX(J6:J5005) -> 6518.1214 | S11: =MAX(C6:C5005) -> 0.97
A12: 7 | B12: =RAND() -> 0.81529699 | C12: =IF(B12<=$B$3, $B$1, IF(B12<=$C$3, $C$1, IF(B12<=$D$3, $D$1, IF(B12<=$E$3, $E$1, IF(B12<=$F$3, $F$1, IF(B12<=$G$3, $G$1, IF(B12<=$H$3, $H$1, IF(B12<=$I$3, $I$1, IF(B12<=$J$3, $J$1, IF(B12<=$K$3, $K$1, IF(B12<=$L$3, $L$1, IF(B12<=$M$3, $M$1, IF(B12<=$N$3, $N$1, IF(B12<=$O$3, $O$1, "Error")))))))))))))) -> 0.94 | D12: =$W$2+$V$2*C12+$Y$2*_xlfn.NORM.INV(RAND(),0,1) -> 7194.7633 | E12: =MAX(0,$W$3+$V$3*C12+$Y$3*_xlfn.NORM.INV(RAND(),0,1)) -> 11930.307 | F12: =$W$4+$V$4*C12+$Y$4*_xlfn.NORM.INV(RAND(),0,1) -> 36512.009 | G12: =D12-Krishna!$AD$3 -> 485.12697 | H12: =E12-Krishna!$AE$3 -> 910.89833 | I12: =F12-Krishna!$AF$3 -> 8922.373 | J12: =D12-E12 -> -4735.5441 | K12: Standard Deviation | L12: =STDEV(D6:D5005) -> 791.51393 | M12: =STDEV(E6:E5005) -> 3150.7941 | N12: =STDEV(F6:F5005) -> 8114.963 | O12: =STDEV(G6:G5005) -> 791.51393 | P12: =STDEV(H6:H5005) -> 3150.7941 | Q12: =STDEV(I6:I5005) -> 8114.963 | R12: =STDEV(J6:J5005) -> 2893.5443 | S12: =STDEV(C6:C5005) -> 0.062221747
A13: 8 | B13: =RAND() -> 0.63340414 | C13: =IF(B13<=$B$3, $B$1, IF(B13<=$C$3, $C$1, IF(B13<=$D$3, $D$1, IF(B13<=$E$3, $E$1, IF(B13<=$F$3, $F$1, IF(B13<=$G$3, $G$1, IF(B13<=$H$3, $H$1, IF(B13<=$I$3, $I$1, IF(B13<=$J$3, $J$1, IF(B13<=$K$3, $K$1, IF(B13<=$L$3, $L$1, IF(B13<=$M$3, $M$1, IF(B13<=$N$3, $N$1, IF(B13<=$O$3, $O$1, "Error")))))))))))))) -> 0.94 | D13: =$W$2+$V$2*C13+$Y$2*_xlfn.NORM.INV(RAND(),0,1) -> 8257.2846 | E13: =MAX(0,$W$3+$V$3*C13+$Y$3*_xlfn.NORM.INV(RAND(),0,1)) -> 15890.032 | F13: =$W$4+$V$4*C13+$Y$4*_xlfn.NORM.INV(RAND(),0,1) -> 33108.199 | G13: =D13-Krishna!$AD$3 -> 1547.6483 | H13: =E13-Krishna!$AE$3 -> 4870.6232 | I13: =F13-Krishna!$AF$3 -> 5518.5622 | J13: =D13-E13 -> -7632.7476
A14: 9 | B14: =RAND() -> 0.26162169 | C14: =IF(B14<=$B$3, $B$1, IF(B14<=$C$3, $C$1, IF(B14<=$D$3, $D$1, IF(B14<=$E$3, $E$1, IF(B14<=$F$3, $F$1, IF(B14<=$G$3, $G$1, IF(B14<=$H$3, $H$1, IF(B14<=$I$3, $I$1, IF(B14<=$J$3, $J$1, IF(B14<=$K$3, $K$1, IF(B14<=$L$3, $L$1, IF(B14<=$M$3, $M$1, IF(B14<=$N$3, $N$1, IF(B14<=$O$3, $O$1, "Error")))))))))))))) -> 0.89 | D14: =$W$2+$V$2*C14+$Y$2*_xlfn.NORM.INV(RAND(),0,1) -> 7490.9959 | E14: =MAX(0,$W$3+$V$3*C14+$Y$3*_xlfn.NORM.INV(RAND(),0,1)) -> 14251.489 | F14: =$W$4+$V$4*C14+$Y$4*_xlfn.NORM.INV(RAND(),0,1) -> 27753.796 | G14: =D14-Krishna!$AD$3 -> 781.35951 | H14: =E14-Krishna!$AE$3 -> 3232.0803 | I14: =F14-Krishna!$AF$3 -> 164.15927 | J14: =D14-E14 -> -6760.4935
A15: 10 | B15: =RAND() -> 0.21911209 | C15: =IF(B15<=$B$3, $B$1, IF(B15<=$C$3, $C$1, IF(B15<=$D$3, $D$1, IF(B15<=$E$3, $E$1, IF(B15<=$F$3, $F$1, IF(B15<=$G$3, $G$1, IF(B15<=$H$3, $H$1, IF(B15<=$I$3, $I$1, IF(B15<=$J$3, $J$1, IF(B15<=$K$3, $K$1, IF(B15<=$L$3, $L$1, IF(B15<=$M$3, $M$1, IF(B15<=$N$3, $N$1, IF(B15<=$O$3, $O$1, "Error")))))))))))))) -> 0.87 | D15: =$W$2+$V$2*C15+$Y$2*_xlfn.NORM.INV(RAND(),0,1) -> 6541.4776 | E15: =MAX(0,$W$3+$V$3*C15+$Y$3*_xlfn.NORM.INV(RAND(),0,1)) -> 9315.2432 | F15: =$W$4+$V$4*C15+$Y$4*_xlfn.NORM.INV(RAND(),0,1) -> 27947.062 | G15: =D15-Krishna!$AD$3 -> -168.15881 | H15: =E15-Krishna!$AE$3 -> -1704.1659 | I15: =F15-Krishna!$AF$3 -> 357.42561 | J15: =D15-E15 -> -2773.7657
A16: 11 | B16: =RAND() -> 0.8580307 | C16: =IF(B16<=$B$3, $B$1, IF(B16<=$C$3, $C$1, IF(B16<=$D$3, $D$1, IF(B16<=$E$3, $E$1, IF(B16<=$F$3, $F$1, IF(B16<=$G$3, $G$1, IF(B16<=$H$3, $H$1, IF(B16<=$I$3, $I$1, IF(B16<=$J$3, $J$1, IF(B16<=$K$3, $K$1, IF(B16<=$L$3, $L$1, IF(B16<=$M$3, $M$1, IF(B16<=$N$3, $N$1, IF(B16<=$O$3, $O$1, "Error")))))))))))))) -> 0.95 | D16: =$W$2+$V$2*C16+$Y$2*_xlfn.NORM.INV(RAND(),0,1) -> 6445.5437 | E16: =MAX(0,$W$3+$V$3*C16+$Y$3*_xlfn.NORM.INV(RAND(),0,1)) -> 13925.856 | F16: =$W$4+$V$4*C16+$Y$4*_xlfn.NORM.INV(RAND(),0,1) -> 40938.701 | G16: =D16-Krishna!$AD$3 -> -264.09264 | H16: =E16-Krishna!$AE$3 -> 2906.4467 | I16: =F16-Krishna!$AF$3 -> 13349.064 | J16: =D16-E16 -> -7480.3121
A17: 12 | B17: =RAND() -> 0.77948991 | C17: =IF(B17<=$B$3, $B$1, IF(B17<=$C$3, $C$1, IF(B17<=$D$3, $D$1, IF(B17<=$E$3, $E$1, IF(B17<=$F$3, $F$1, IF(B17<=$G$3, $G$1, IF(B17<=$H$3, $H$1, IF(B17<=$I$3, $I$1, IF(B17<=$J$3, $J$1, IF(B17<=$K$3, $K$1, IF(B17<=$L$3, $L$1, IF(B17<=$M$3, $M$1, IF(B17<=$N$3, $N$1, IF(B17<=$O$3, $O$1, "Error")))))))))))))) -> 0.94 | D17: =$W$2+$V$2*C17+$Y$2*_xlfn.NORM.INV(RAND(),0,1) -> 7210.9273 | E17: =MAX(0,$W$3+$V$3*C17+$Y$3*_xlfn.NORM.INV(RAND(),0,1)) -> 12056.125 | F17: =$W$4+$V$4*C17+$Y$4*_xlfn.NORM.INV(RAND(),0,1) -> 29644.944 | G17: =D17-Krishna!$AD$3 -> 501.29095 | H17: =E17-Krishna!$AE$3 -> 1036.7159 | I17: =F17-Krishna!$AF$3 -> 2055.3072 | J17: =D17-E17 -> -4845.1977
A18: 13 | B18: =RAND() -> 0.093271543 | C18: =IF(B18<=$B$3, $B$1, IF(B18<=$C$3, $C$1, IF(B18<=$D$3, $D$1, IF(B18<=$E$3, $E$1, IF(B18<=$F$3, $F$1, IF(B18<=$G$3, $G$1, IF(B18<=$H$3, $H$1, IF(B18<=$I$3, $I$1, IF(B18<=$J$3, $J$1, IF(B18<=$K$3, $K$1, IF(B18<=$L$3, $L$1, IF(B18<=$M$3, $M$1, IF(B18<=$N$3, $N$1, IF(B18<=$O$3, $O$1, "Error")))))))))))))) -> 0.8 | D18: =$W$2+$V$2*C18+$Y$2*_xlfn.NORM.INV(RAND(),0,1) -> 5281.3106 | E18: =MAX(0,$W$3+$V$3*C18+$Y$3*_xlfn.NORM.INV(RAND(),0,1)) -> 7734.5615 | F18: =$W$4+$V$4*C18+$Y$4*_xlfn.NORM.INV(RAND(),0,1) -> 20825.914 | G18: =D18-Krishna!$AD$3 -> -1428.3258 | H18: =E18-Krishna!$AE$3 -> -3284.8476 | I18: =F18-Krishna!$AF$3 -> -6763.7219 | J18: =D18-E18 -> -2453.2508
A19: 14 | B19: =RAND() -> 0.82111262 | C19: =IF(B19<=$B$3, $B$1, IF(B19<=$C$3, $C$1, IF(B19<=$D$3, $D$1, IF(B19<=$E$3, $E$1, IF(B19<=$F$3, $F$1, IF(B19<=$G$3, $G$1, IF(B19<=$H$3, $H$1, IF(B19<=$I$3, $I$1, IF(B19<=$J$3, $J$1, IF(B19<=$K$3, $K$1, IF(B19<=$L$3, $L$1, IF(B19<=$M$3, $M$1, IF(B19<=$N$3, $N$1, IF(B19<=$O$3, $O$1, "Error")))))))))))))) -> 0.95 | D19: =$W$2+$V$2*C19+$Y$2*_xlfn.NORM.INV(RAND(),0,1) -> 8426.1229 | E19: =MAX(0,$W$3+$V$3*C19+$Y$3*_xlfn.NORM.INV(RAND(),0,1)) -> 15510.095 | F19: =$W$4+$V$4*C19+$Y$4*_xlfn.NORM.INV(RAND(),0,1) -> 28784.121 | G19: =D19-Krishna!$AD$3 -> 1716.4865 | H19: =E19-Krishna!$AE$3 -> 4490.686 | I19: =F19-Krishna!$AF$3 -> 1194.4851 | J19: =D19-E19 -> -7083.9721
A20: 15 | B20: =RAND() -> 0.39831104 | C20: =IF(B20<=$B$3, $B$1, IF(B20<=$C$3, $C$1, IF(B20<=$D$3, $D$1, IF(B20<=$E$3, $E$1, IF(B20<=$F$3, $F$1, IF(B20<=$G$3, $G$1, IF(B20<=$H$3, $H$1, IF(B20<=$I$3, $I$1, IF(B20<=$J$3, $J$1, IF(B20<=$K$3, $K$1, IF(B20<=$L$3, $L$1, IF(B20<=$M$3, $M$1, IF(B20<=$N$3, $N$1, IF(B20<=$O$3, $O$1, "Error")))))))))))))) -> 0.9 | D20: =$W$2+$V$2*C20+$Y$2*_xlfn.NORM.INV(RAND(),0,1) -> 7165.6179 | E20: =MAX(0,$W$3+$V$3*C20+$Y$3*_xlfn.NORM.INV(RAND(),0,1)) -> 12121.178 | F20: =$W$4+$V$4*C20+$Y$4*_xlfn.NORM.INV(RAND(),0,1) -> 31903.577 | G20: =D20-Krishna!$AD$3 -> 455.98151 | H20: =E20-Krishna!$AE$3 -> 1101.7686 | I20: =F20-Krishna!$AF$3 -> 4313.9402 | J20: =D20-E20 -> -4955.5598
A21: 16 | B21: =RAND() -> 0.85340964 | C21: =IF(B21<=$B$3, $B$1, IF(B21<=$C$3, $C$1, IF(B21<=$D$3, $D$1, IF(B21<=$E$3, $E$1, IF(B21<=$F$3, $F$1, IF(B21<=$G$3, $G$1, IF(B21<=$H$3, $H$1, IF(B21<=$I$3, $I$1, IF(B21<=$J$3, $J$1, IF(B21<=$K$3, $K$1, IF(B21<=$L$3, $L$1, IF(B21<=$M$3, $M$1, IF(B21<=$N$3, $N$1, IF(B21<=$O$3, $O$1, "Error")))))))))))))) -> 0.95 | D21: =$W$2+$V$2*C21+$Y$2*_xlfn.NORM.INV(RAND(),0,1) -> 7921.6786 | E21: =MAX(0,$W$3+$V$3*C21+$Y$3*_xlfn.NORM.INV(RAND(),0,1)) -> 12634.81 | F21: =$W$4+$V$4*C21+$Y$4*_xlfn.NORM.INV(RAND(),0,1) -> 39881.456 | G21: =D21-Krishna!$AD$3 -> 1212.0422 | H21: =E21-Krishna!$AE$3 -> 1615.4005 | I21: =F21-Krishna!$AF$3 -> 12291.82 | J21: =D21-E21 -> -4713.131
A22: 17 | B22: =RAND() -> 0.92150471 | C22: =IF(B22<=$B$3, $B$1, IF(B22<=$C$3, $C$1, IF(B22<=$D$3, $D$1, IF(B22<=$E$3, $E$1, IF(B22<=$F$3, $F$1, IF(B22<=$G$3, $G$1, IF(B22<=$H$3, $H$1, IF(B22<=$I$3, $I$1, IF(B22<=$J$3, $J$1, IF(B22<=$K$3, $K$1, IF(B22<=$L$3, $L$1, IF(B22<=$M$3, $M$1, IF(B22<=$N$3, $N$1, IF(B22<=$O$3, $O$1, "Error")))))))))))))) -> 0.96 | D22: =$W$2+$V$2*C22+$Y$2*_xlfn.NORM.INV(RAND(),0,1) -> 8010.7795 | E22: =MAX(0,$W$3+$V$3*C22+$Y$3*_xlfn.NORM.INV(RAND(),0,1)) -> 15658.298 | F22: =$W$4+$V$4*C22+$Y$4*_xlfn.NORM.INV(RAND(),0,1) -> 37304.696 | G22: =D22-Krishna!$AD$3 -> 1301.1431 | H22: =E22-Krishna!$AE$3 -> 4638.8889 | I22: =F22-Krishna!$AF$3 -> 9715.0593 | J22: =D22-E22 -> -7647.5185
A23: 18 | B23: =RAND() -> 0.56482878 | C23: =IF(B23<=$B$3, $B$1, IF(B23<=$C$3, $C$1, IF(B23<=$D$3, $D$1, IF(B23<=$E$3, $E$1, IF(B23<=$F$3, $F$1, IF(B23<=$G$3, $G$1, IF(B23<=$H$3, $H$1, IF(B23<=$I$3, $I$1, IF(B23<=$J$3, $J$1, IF(B23<=$K$3, $K$1, IF(B23<=$L$3, $L$1, IF(B23<=$M$3, $M$1, IF(B23<=$N$3, $N$1, IF(B23<=$O$3, $O$1, "Error")))))))))))))) -> 0.93 | D23: =$W$2+$V$2*C23+$Y$2*_xlfn.NORM.INV(RAND(),0,1) -> 7593.6247 | E23: =MAX(0,$W$3+$V$3*C23+$Y$3*_xlfn.NORM.INV(RAND(),0,1)) -> 12276.442 | F23: =$W$4+$V$4*C23+$Y$4*_xlfn.NORM.INV(RAND(),0,1) -> 30017.619 | G23: =D23-Krishna!$AD$3 -> 883.98831 | H23: =E23-Krishna!$AE$3 -> 1257.0331 | I23: =F23-Krishna!$AF$3 -> 2427.9829 | J23: =D23-E23 -> -4682.8175
A24: 19 | B24: =RAND() -> 0.62839048 | C24: =IF(B24<=$B$3, $B$1, IF(B24<=$C$3, $C$1, IF(B24<=$D$3, $D$1, IF(B24<=$E$3, $E$1, IF(B24<=$F$3, $F$1, IF(B24<=$G$3, $G$1, IF(B24<=$H$3, $H$1, IF(B24<=$I$3, $I$1, IF(B24<=$J$3, $J$1, IF(B24<=$K$3, $K$1, IF(B24<=$L$3, $L$1, IF(B24<=$M$3, $M$1, IF(B24<=$N$3, $N$1, IF(B24<=$O$3, $O$1, "Error")))))))))))))) -> 0.94 | D24: =$W$2+$V$2*C24+$Y$2*_xlfn.NORM.INV(RAND(),0,1) -> 7820.4527 | E24: =MAX(0,$W$3+$V$3*C24+$Y$3*_xlfn.NORM.INV(RAND(),0,1)) -> 11016.307 | F24: =$W$4+$V$4*C24+$Y$4*_xlfn.NORM.INV(RAND(),0,1) -> 20785.49 | G24: =D24-Krishna!$AD$3 -> 1110.8163 | H24: =E24-Krishna!$AE$3 -> -3.1016504 | I24: =F24-Krishna!$AF$3 -> -6804.1463 | J24: =D24-E24 -> -3195.8547
... A5005: 5000 | B5005: =RAND() -> 0.82611502 | C5005: =IF(B5005<=$B$3, $B$1, IF(B5005<=$C$3, $C$1, IF(B5005<=$D$3, $D$1, IF(B5005<=$E$3, $E$1, IF(B5005<=$F$3, $F$1, IF(B5005<=$G$3, $G$1, IF(B5005<=$H$3, $H$1, IF(B5005<=$I$3, $I$1, IF(B5005<=$J$3, $J$1, IF(B5005<=$K$3, $K$1, IF(B5005<=$L$3, $L$1, IF(B5005<=$M$3, $M$1, IF(B5005<=$N$3, $N$1, IF(B5005<=$O$3, $O$1, "Error")))))))))))))) -> 0.95 | D5005: =$W$2+$V$2*C5005+$Y$2*_xlfn.NORM.INV(RAND(),0,1) -> 7313.9184 | E5005: =MAX(0,$W$3+$V$3*C5005+$Y$3*_xlfn.NORM.INV(RAND(),0,1)) -> 12258.57 | F5005: =$W$4+$V$4*C5005+$Y$4*_xlfn.NORM.INV(RAND(),0,1) -> 28291.218 | G5005: =D5005-Krishna!$AD$3 -> 604.282 | H5005: =E5005-Krishna!$AE$3 -> 1239.1606 | I5005: =F5005-Krishna!$AF$3 -> 701.58203 | J5005: =D5005-E5005 -> -4944.6513

Sheet Ramita
A1: Valero Environmental & Regulatory Risk Model | D1: Old data set | E1: Quarter - Year | F1: RIN: | G1: LCFS | H1: Carbon allowance | J1: Simulation Results | L1: new data set | M1: Quarter - Year | N1: RIN price ($) | O1: LCFS price ($) | P1: Carbon allowance ($)
E2: Q1 2024 | F2: 0.58 | G2: 63.55 | H2: 41.76 | M2: Q1 2020 | N2: 0.46 | O2: 206.03 | P2: 12
A3: Risk Driver Parameters | E3: Q2 2024 | F3: 0.51 | G3: 51.29 | H3: 37.02 | J3: Metric | K3: Value | M3: Q2 2020 | N3: 0.54 | O3: 201.01 | P3: 14
A4: Driver | B4: Mean (μ) | C4: Std Dev (σ) | D4: Sensitivity | E4: Q3 2024 | F4: 0.6 | G4: 53.65 | H4: 30.24 | J4: Iterations | K4: =COUNT(H9:H4343) -> 1000 | M4: Q3 2020 | N4: 0.67 | O4: 195.6 | P4: 16
A5: RIN Price | B5: =AVERAGE(N2:N23) -> 1.1095455 | C5: =_xlfn.STDEV.S(N2:N23) -> 0.4636961 | D5: 50 | E5: Q4 2024 | F5: 0.84 | G5: 68.71 | H5: 31.91 | J5: Expected Impact | K5: =AVERAGE(H9:H1007) -> 279.7421 | M5: Q4 2020 | N5: 0.88 | O5: 197.83 | P5: 18
A6: LCFS Price | B6: =AVERAGE(O2:O23) -> 116.88364 | C6: =_xlfn.STDEV.S(O2:O23) -> 61.173589 | D6: 25 | E6: Q1 2025 | F6: 0.79 | G6: 66.17 | H6: 36.58 | J6: 5% VaR (95% Confidence) | K6: =PERCENTILE(H9:H1007, 0.05) -> -477.50787 | M6: Q1 2021 | N6: 1.18 | O6: 195.3 | P6: 19
A7: Carbon Price | B7: =AVERAGE(P2:P23) -> 46.136364 | C7: =_xlfn.STDEV.S(P2:P23) -> 27.085922 | D7: 100 | E7: Q2 2025 | F7: 0.94 | G7: 52.36 | H7: 42 | J7: Worst Case | K7: =MIN(H9:H1007) -> -804.98351 | M7: Q2 2021 | N7: 1.71 | O7: 184.82 | P7: 20
A8: Iteration | B8: RIN Price | C8: LCFS Price | D8: Carbon Price | E8: change in Operating Income | F8: PP&E Impairment | G8: ARO Increase | H8: Total Impact | J8: Best Case | K8: =MAX(H9:H1007) -> 9119.593 | M8: Q3 2021 | N8: 1.18 | O8: 195.3 | P8: 22
A9: 1 | B9: =_xlfn.LOGNORM.INV(RAND(), $O$31, $O$32) -> 0.99096628 | C9: =_xlfn.LOGNORM.INV(RAND(), $O$28, $O$29) -> 59.790874 | D9: =_xlfn.LOGNORM.INV(RAND(), $O$25, $O$26) -> 10.706137 | E9: =((B9-$B$5)/0.1)*$D$5 + ((C9-$B$6)/10)*$D$6 + ((D9-$B$7)/10)*$D$7 -> -556.32376 | F9: =IF(OR(B9<0.4, D9>50), 150, 0) -> 0 | G9: =(D9/10)*D7 -> 107.06137 | H9: =E9+F9+G9 -> -449.26239 | J9: Std Deviation | K9: =STDEV(H9:H1007) -> 748.48635 | M9: Q4 2021 | N9: 1.49 | O9: 155.24 | P9: 25
A10: 2 | B10: =_xlfn.LOGNORM.INV(RAND(), $O$31, $O$32) -> 1.0315189 | C10: =_xlfn.LOGNORM.INV(RAND(), $O$28, $O$29) -> 98.238185 | D10: =_xlfn.LOGNORM.INV(RAND(), $O$25, $O$26) -> 25.750895 | E10: =((B10-$B$5)/0.1)*$D$5 + ((C10-$B$6)/10)*$D$6 + ((D10-$B$7)/10)*$D$7 -> -289.4816 | F10: =IF(OR(B10<0.4, D10>50), 150, 0) -> 0 | G10: =(D10/10)*D7 -> 257.50895 | H10: =E10+F10+G10 -> -31.972653 | M10: Q1 2022 | N10: 1.43 | O10: 138.63 | P10: 29
A11: 3 | B11: =_xlfn.LOGNORM.INV(RAND(), $O$31, $O$32) -> 2.2953264 | C11: =_xlfn.LOGNORM.INV(RAND(), $O$28, $O$29) -> 75.096802 | D11: =_xlfn.LOGNORM.INV(RAND(), $O$25, $O$26) -> 8.6794952 | E11: =((B11-$B$5)/0.1)*$D$5 + ((C11-$B$6)/10)*$D$6 + ((D11-$B$7)/10)*$D$7 -> 113.8547 | F11: =IF(OR(B11<0.4, D11>50), 150, 0) -> 0 | G11: =(D11/10)*D9 -> 9.2923866 | H11: =E11+F11+G11 -> 123.14709 | J11: Correlation | M11: Q2 2022 | N11: 1.7 | O11: 104.3 | P11: 32
A12: 4 | B12: =_xlfn.LOGNORM.INV(RAND(), $O$31, $O$32) -> 1.3303515 | C12: =_xlfn.LOGNORM.INV(RAND(), $O$28, $O$29) -> 72.545058 | D12: =_xlfn.LOGNORM.INV(RAND(), $O$25, $O$26) -> 44.784415 | E12: =((B12-$B$5)/0.1)*$D$5 + ((C12-$B$6)/10)*$D$6 + ((D12-$B$7)/10)*$D$7 -> -13.962915 | F12: =IF(OR(B12<0.4, D12>50), 150, 0) -> 0 | G12: =(D12/10)*D10 -> 115.32388 | H12: =E12+F12+G12 -> 101.36096 | J12: =CORREL(B9:B1008,D9:D1008) -> 0.00098256983 | M12: Q3 2022 | N12: 1.71 | O12: 86.21 | P12: 35
A13: 5 | B13: =_xlfn.LOGNORM.INV(RAND(), $O$31, $O$32) -> 0.91137238 | C13: =_xlfn.LOGNORM.INV(RAND(), $O$28, $O$29) -> 138.49825 | D13: =_xlfn.LOGNORM.INV(RAND(), $O$25, $O$26) -> 41.793388 | E13: =((B13-$B$5)/0.1)*$D$5 + ((C13-$B$6)/10)*$D$6 + ((D13-$B$7)/10)*$D$7 -> -88.479763 | F13: =IF(OR(B13<0.4, D13>50), 150, 0) -> 0 | G13: =(D13/10)*D11 -> 36.274551 | H13: =E13+F13+G13 -> -52.205212 | J13: =CORREL(B9:B1008,C9:C1008) -> 0.056659375 | M13: Q4 2022 | N13: 1.82 | O13: 65.78 | P13: 34
A14: 6 | B14: =_xlfn.LOGNORM.INV(RAND(), $O$31, $O$32) -> 1.3007729 | C14: =_xlfn.LOGNORM.INV(RAND(), $O$28, $O$29) -> 48.706841 | D14: =_xlfn.LOGNORM.INV(RAND(), $O$25, $O$26) -> 19.610699 | E14: =((B14-$B$5)/0.1)*$D$5 + ((C14-$B$6)/10)*$D$6 + ((D14-$B$7)/10)*$D$7 -> -340.0849 | F14: =IF(OR(B14<0.4, D14>50), 150, 0) -> 0 | G14: =(D14/10)*D12 -> 87.825367 | H14: =E14+F14+G14 -> -252.25953 | J14: =CORREL(D9:D1008,C9:C1008) -> 0.035879679 | M14: Q1 2023 | N14: 1.63 | O14: 65.68 | P14: 65
A15: 7 | B15: =_xlfn.LOGNORM.INV(RAND(), $O$31, $O$32) -> 0.49038156 | C15: =_xlfn.LOGNORM.INV(RAND(), $O$28, $O$29) -> 133.8892 | D15: =_xlfn.LOGNORM.INV(RAND(), $O$25, $O$26) -> 68.082269 | E15: =((B15-$B$5)/0.1)*$D$5 + ((C15-$B$6)/10)*$D$6 + ((D15-$B$7)/10)*$D$7 -> -47.609 | F15: =IF(OR(B15<0.4, D15>50), 150, 0) -> 150 | G15: =(D15/10)*D13 -> 284.53887 | H15: =E15+F15+G15 -> 386.92987 | M15: Q2 2023 | N15: 1.51 | O15: 80.81 | P15: 66
A16: 8 | B16: =_xlfn.LOGNORM.INV(RAND(), $O$31, $O$32) -> 1.7123072 | C16: =_xlfn.LOGNORM.INV(RAND(), $O$28, $O$29) -> 269.13472 | D16: =_xlfn.LOGNORM.INV(RAND(), $O$25, $O$26) -> 104.70528 | E16: =((B16-$B$5)/0.1)*$D$5 + ((C16-$B$6)/10)*$D$6 + ((D16-$B$7)/10)*$D$7 -> 1267.6977 | F16: =IF(OR(B16<0.4, D16>50), 150, 0) -> 150 | G16: =(D16/10)*D14 -> 205.33436 | H16: =E16+F16+G16 -> 1623.0321 | J16: =AVERAGE(E9:E1008) -> 21.383579 | M16: Q3 2023 | N16: 1.4 | O16: 74.46 | P16: 72
A17: 9 | B17: =_xlfn.LOGNORM.INV(RAND(), $O$31, $O$32) -> 0.44269275 | C17: =_xlfn.LOGNORM.INV(RAND(), $O$28, $O$29) -> 90.267029 | D17: =_xlfn.LOGNORM.INV(RAND(), $O$25, $O$26) -> 44.366983 | E17: =((B17-$B$5)/0.1)*$D$5 + ((C17-$B$6)/10)*$D$6 + ((D17-$B$7)/10)*$D$7 -> -417.66168 | F17: =IF(OR(B17<0.4, D17>50), 150, 0) -> 0 | G17: =(D17/10)*D15 -> 302.06049 | H17: =E17+F17+G17 -> -115.60119 | M17: Q4 2023 | N17: 0.84 | O17: 68.71 | P17: 65
A18: 10 | B18: =_xlfn.LOGNORM.INV(RAND(), $O$31, $O$32) -> 1.5254351 | C18: =_xlfn.LOGNORM.INV(RAND(), $O$28, $O$29) -> 84.934945 | D18: =_xlfn.LOGNORM.INV(RAND(), $O$25, $O$26) -> 18.169035 | E18: =((B18-$B$5)/0.1)*$D$5 + ((C18-$B$6)/10)*$D$6 + ((D18-$B$7)/10)*$D$7 -> -151.60017 | F18: =IF(OR(B18<0.4, D18>50), 150, 0) -> 0 | G18: =(D18/10)*D16 -> 190.23939 | H18: =E18+F18+G18 -> 38.639218 | M18: Q1 2024 | N18: 0.58 | O18: 63.55 | P18: 70
A19: 11 | B19: =_xlfn.LOGNORM.INV(RAND(), $O$31, $O$32) -> 0.6651088 | C19: =_xlfn.LOGNORM.INV(RAND(), $O$28, $O$29) -> 89.015006 | D19: =_xlfn.LOGNORM.INV(RAND(), $O$25, $O$26) -> 16.025448 | E19: =((B19-$B$5)/0.1)*$D$5 + ((C19-$B$6)/10)*$D$6 + ((D19-$B$7)/10)*$D$7 -> -592.99906 | F19: =IF(OR(B19<0.4, D19>50), 150, 0) -> 0 | G19: =(D19/10)*D17 -> 71.100076 | H19: =E19+F19+G19 -> -521.89899 | M19: Q2 2024 | N19: 0.51 | O19: 51.29 | P19: 75
A20: 12 | B20: =_xlfn.LOGNORM.INV(RAND(), $O$31, $O$32) -> 1.3020368 | C20: =_xlfn.LOGNORM.INV(RAND(), $O$28, $O$29) -> 76.131808 | D20: =_xlfn.LOGNORM.INV(RAND(), $O$25, $O$26) -> 28.659939 | E20: =((B20-$B$5)/0.1)*$D$5 + ((C20-$B$6)/10)*$D$6 + ((D20-$B$7)/10)*$D$7 -> -180.39813 | F20: =IF(OR(B20<0.4, D20>50), 150, 0) -> 0 | G20: =(D20/10)*D18 -> 52.072344 | H20: =E20+F20+G20 -> -128.32578 | M20: Q3 2024 | N20: 0.6 | O20: 53.65 | P20: 76
A21: 13 | B21: =_xlfn.LOGNORM.INV(RAND(), $O$31, $O$32) -> 1.805974 | C21: =_xlfn.LOGNORM.INV(RAND(), $O$28, $O$29) -> 158.69628 | D21: =_xlfn.LOGNORM.INV(RAND(), $O$25, $O$26) -> 131.61041 | E21: =((B21-$B$5)/0.1)*$D$5 + ((C21-$B$6)/10)*$D$6 + ((D21-$B$7)/10)*$D$7 -> 1307.4864 | F21: =IF(OR(B21<0.4, D21>50), 150, 0) -> 150 | G21: =(D21/10)*D19 -> 210.91158 | H21: =E21+F21+G21 -> 1668.398 | M21: Q4 2024 | N21: 0.84 | O21: 68.71 | P21: 78
A22: 14 | B22: =_xlfn.LOGNORM.INV(RAND(), $O$31, $O$32) -> 0.6104641 | C22: =_xlfn.LOGNORM.INV(RAND(), $O$28, $O$29) -> 173.06267 | D22: =_xlfn.LOGNORM.INV(RAND(), $O$25, $O$26) -> 57.996454 | E22: =((B22-$B$5)/0.1)*$D$5 + ((C22-$B$6)/10)*$D$6 + ((D22-$B$7)/10)*$D$7 -> 9.5078144 | F22: =IF(OR(B22<0.4, D22>50), 150, 0) -> 150 | G22: =(D22/10)*D20 -> 166.21749 | H22: =E22+F22+G22 -> 325.7253 | M22: Q1 2025 | N22: 0.79 | O22: 66.17 | P22: 82
A23: 15 | B23: =_xlfn.LOGNORM.INV(RAND(), $O$31, $O$32) -> 0.65497386 | C23: =_xlfn.LOGNORM.INV(RAND(), $O$28, $O$29) -> 147.12549 | D23: =_xlfn.LOGNORM.INV(RAND(), $O$25, $O$26) -> 28.729568 | E23: =((B23-$B$5)/0.1)*$D$5 + ((C23-$B$6)/10)*$D$6 + ((D23-$B$7)/10)*$D$7 -> -325.74912 | F23: =IF(OR(B23<0.4, D23>50), 150, 0) -> 0 | G23: =(D23/10)*D21 -> 378.11104 | H23: =E23+F23+G23 -> 52.36192 | M23: Q2 2025 | N23: 0.94 | O23: 52.36 | P23: 90
A24: 16 | B24: =_xlfn.LOGNORM.INV(RAND(), $O$31, $O$32) -> 0.55981938 | C24: =_xlfn.LOGNORM.INV(RAND(), $O$28, $O$29) -> 29.894758 | D24: =_xlfn.LOGNORM.INV(RAND(), $O$25, $O$26) -> 50.828455 | E24: =((B24-$B$5)/0.1)*$D$5 + ((C24-$B$6)/10)*$D$6 + ((D24-$B$7)/10)*$D$7 -> -445.41432 | F24: =IF(OR(B24<0.4, D24>50), 150, 0) -> 150 | G24: =(D24/10)*D22 -> 294.78702 | H24: =E24+F24+G24 -> -0.62730109
A25: 17 | B25: =_xlfn.LOGNORM.INV(RAND(), $O$31, $O$32) -> 1.0455131 | C25: =_xlfn.LOGNORM.INV(RAND(), $O$28, $O$29) -> 260.40649 | D25: =_xlfn.LOGNORM.INV(RAND(), $O$25, $O$26) -> 150.68416 | E25: =((B25-$B$5)/0.1)*$D$5 + ((C25-$B$6)/10)*$D$6 + ((D25-$B$7)/10)*$D$7 -> 1372.269 | F25: =IF(OR(B25<0.4, D25>50), 150, 0) -> 150 | G25: =(D25/10)*D23 -> 432.90909 | H25: =E25+F25+G25 -> 1955.1781 | L25: CARBON PRICE | M25: Mean of natural logs : | O25: {=AVERAGE(LN(P2:P23))} -> 3.6330366
A26: 18 | B26: =_xlfn.LOGNORM.INV(RAND(), $O$31, $O$32) -> 0.98382297 | C26: =_xlfn.LOGNORM.INV(RAND(), $O$28, $O$29) -> 126.1742 | D26: =_xlfn.LOGNORM.INV(RAND(), $O$25, $O$26) -> 31.319349 | E26: =((B26-$B$5)/0.1)*$D$5 + ((C26-$B$6)/10)*$D$6 + ((D26-$B$7)/10)*$D$7 -> -187.80498 | F26: =IF(OR(B26<0.4, D26>50), 150, 0) -> 0 | G26: =(D26/10)*D24 -> 159.19141 | H26: =E26+F26+G26 -> -28.613563 | M26: Standard deviation of natural logs : | O26: {=_xlfn.STDEV.S(LN(P2:P23))} -> 0.67533349
A27: 19 | B27: =_xlfn.LOGNORM.INV(RAND(), $O$31, $O$32) -> 0.84691627 | C27: =_xlfn.LOGNORM.INV(RAND(), $O$28, $O$29) -> 144.67512 | D27: =_xlfn.LOGNORM.INV(RAND(), $O$25, $O$26) -> 74.659596 | E27: =((B27-$B$5)/0.1)*$D$5 + ((C27-$B$6)/10)*$D$6 + ((D27-$B$7)/10)*$D$7 -> 223.39645 | F27: =IF(OR(B27<0.4, D27>50), 150, 0) -> 150 | G27: =(D27/10)*D25 -> 1125.0019 | H27: =E27+F27+G27 -> 1498.3983
A28: 20 | B28: =_xlfn.LOGNORM.INV(RAND(), $O$31, $O$32) -> 1.0275686 | C28: =_xlfn.LOGNORM.INV(RAND(), $O$28, $O$29) -> 66.249515 | D28: =_xlfn.LOGNORM.INV(RAND(), $O$25, $O$26) -> 41.832461 | E28: =((B28-$B$5)/0.1)*$D$5 + ((C28-$B$6)/10)*$D$6 + ((D28-$B$7)/10)*$D$7 -> -210.61276 | F28: =IF(OR(B28<0.4, D28>50), 150, 0) -> 0 | G28: =(D28/10)*D26 -> 131.01654 | H28: =E28+F28+G28 -> -79.596213 | L28: LCFS Price | M28: Mean of natural logs : | O28: {=AVERAGE(LN(O2:O23))} -> 4.627254
A29: 21 | B29: =_xlfn.LOGNORM.INV(RAND(), $O$31, $O$32) -> 1.5637059 | C29: =_xlfn.LOGNORM.INV(RAND(), $O$28, $O$29) -> 88.79598 | D29: =_xlfn.LOGNORM.INV(RAND(), $O$25, $O$26) -> 36.199965 | E29: =((B29-$B$5)/0.1)*$D$5 + ((C29-$B$6)/10)*$D$6 + ((D29-$B$7)/10)*$D$7 -> 57.497086 | F29: =IF(OR(B29<0.4, D29>50), 150, 0) -> 0 | G29: =(D29/10)*D27 -> 270.26748 | H29: =E29+F29+G29 -> 327.76456 | M29: Standard deviation of natural logs : | O29: {=_xlfn.STDEV.S(LN(O2:O23))} -> 0.53034028
A30: 22 | B30: =_xlfn.LOGNORM.INV(RAND(), $O$31, $O$32) -> 0.93345634 | C30: =_xlfn.LOGNORM.INV(RAND(), $O$28, $O$29) -> 104.80325 | D30: =_xlfn.LOGNORM.INV(RAND(), $O$25, $O$26) -> 24.521803 | E30: =((B30-$B$5)/0.1)*$D$5 + ((C30-$B$6)/10)*$D$6 + ((D30-$B$7)/10)*$D$7 -> -334.39114 | F30: =IF(OR(B30<0.4, D30>50), 150, 0) -> 0 | G30: =(D30/10)*D28 -> 102.58073 | H30: =E30+F30+G30 -> -231.8104
A31: 23 | B31: =_xlfn.LOGNORM.INV(RAND(), $O$31, $O$32) -> 0.72990423 | C31: =_xlfn.LOGNORM.INV(RAND(), $O$28, $O$29) -> 89.482523 | D31: =_xlfn.LOGNORM.INV(RAND(), $O$25, $O$26) -> 69.992076 | E31: =((B31-$B$5)/0.1)*$D$5 + ((C31-$B$6)/10)*$D$6 + ((D31-$B$7)/10)*$D$7 -> -19.766269 | F31: =IF(OR(B31<0.4, D31>50), 150, 0) -> 150 | G31: =(D31/10)*D29 -> 253.37107 | H31: =E31+F31+G31 -> 383.6048 | L31: RIN Price | M31: Mean of natural logs : | O31: {=AVERAGE(LN(N2:N23))} -> 0.010493868
A32: 24 | B32: =_xlfn.LOGNORM.INV(RAND(), $O$31, $O$32) -> 1.4271293 | C32: =_xlfn.LOGNORM.INV(RAND(), $O$28, $O$29) -> 116.41225 | D32: =_xlfn.LOGNORM.INV(RAND(), $O$25, $O$26) -> 33.007079 | E32: =((B32-$B$5)/0.1)*$D$5 + ((C32-$B$6)/10)*$D$6 + ((D32-$B$7)/10)*$D$7 -> 26.320624 | F32: =IF(OR(B32<0.4, D32>50), 150, 0) -> 0 | G32: =(D32/10)*D30 -> 80.939307 | H32: =E32+F32+G32 -> 107.25993 | M32: Standard deviation of natural logs : | O32: {=_xlfn.STDEV.S(LN(N2:N23))} -> 0.45604731
A33: 25 | B33: =_xlfn.LOGNORM.INV(RAND(), $O$31, $O$32) -> 1.2327417 | C33: =_xlfn.LOGNORM.INV(RAND(), $O$28, $O$29) -> 127.6799 | D33: =_xlfn.LOGNORM.INV(RAND(), $O$25, $O$26) -> 84.676063 | E33: =((B33-$B$5)/0.1)*$D$5 + ((C33-$B$6)/10)*$D$6 + ((D33-$B$7)/10)*$D$7 -> 473.98576 | F33: =IF(OR(B33<0.4, D33>50), 150, 0) -> 150 | G33: =(D33/10)*D31 -> 592.66535 | H33: =E33+F33+G33 -> 1216.6511
A34: 26 | B34: =_xlfn.LOGNORM.INV(RAND(), $O$31, $O$32) -> 1.2025477 | C34: =_xlfn.LOGNORM.INV(RAND(), $O$28, $O$29) -> 191.92547 | D34: =_xlfn.LOGNORM.INV(RAND(), $O$25, $O$26) -> 8.4562308 | E34: =((B34-$B$5)/0.1)*$D$5 + ((C34-$B$6)/10)*$D$6 + ((D34-$B$7)/10)*$D$7 -> -142.69562 | F34: =IF(OR(B34<0.4, D34>50), 150, 0) -> 0 | G34: =(D34/10)*D32 -> 27.911547 | H34: =E34+F34+G34 -> -114.78407
A35: 27 | B35: =_xlfn.LOGNORM.INV(RAND(), $O$31, $O$32) -> 1.4661783 | C35: =_xlfn.LOGNORM.INV(RAND(), $O$28, $O$29) -> 113.8645 | D35: =_xlfn.LOGNORM.INV(RAND(), $O$25, $O$26) -> 46.433699 | E35: =((B35-$B$5)/0.1)*$D$5 + ((C35-$B$6)/10)*$D$6 + ((D35-$B$7)/10)*$D$7 -> 173.74195 | F35: =IF(OR(B35<0.4, D35>50), 150, 0) -> 0 | G35: =(D35/10)*D33 -> 393.18229 | H35: =E35+F35+G35 -> 566.92424
A36: 28 | B36: =_xlfn.LOGNORM.INV(RAND(), $O$31, $O$32) -> 1.594518 | C36: =_xlfn.LOGNORM.INV(RAND(), $O$28, $O$29) -> 145.16911 | D36: =_xlfn.LOGNORM.INV(RAND(), $O$25, $O$26) -> 22.518109 | E36: =((B36-$B$5)/0.1)*$D$5 + ((C36-$B$6)/10)*$D$6 + ((D36-$B$7)/10)*$D$7 -> 77.0174 | F36: =IF(OR(B36<0.4, D36>50), 150, 0) -> 0 | G36: =(D36/10)*D34 -> 19.041833 | H36: =E36+F36+G36 -> 96.059232
A37: 29 | B37: =_xlfn.LOGNORM.INV(RAND(), $O$31, $O$32) -> 0.89158757 | C37: =_xlfn.LOGNORM.INV(RAND(), $O$28, $O$29) -> 108.88451 | D37: =_xlfn.LOGNORM.INV(RAND(), $O$25, $O$26) -> 70.425934 | E37: =((B37-$B$5)/0.1)*$D$5 + ((C37-$B$6)/10)*$D$6 + ((D37-$B$7)/10)*$D$7 -> 113.91895 | F37: =IF(OR(B37<0.4, D37>50), 150, 0) -> 150 | G37: =(D37/10)*D35 -> 327.01366 | H37: =E37+F37+G37 -> 590.93262
A38: 30 | B38: =_xlfn.LOGNORM.INV(RAND(), $O$31, $O$32) -> 1.5050401 | C38: =_xlfn.LOGNORM.INV(RAND(), $O$28, $O$29) -> 58.294505 | D38: =_xlfn.LOGNORM.INV(RAND(), $O$25, $O$26) -> 36.615339 | E38: =((B38-$B$5)/0.1)*$D$5 + ((C38-$B$6)/10)*$D$6 + ((D38-$B$7)/10)*$D$7 -> -43.935762 | F38: =IF(OR(B38<0.4, D38>50), 150, 0) -> 0 | G38: =(D38/10)*D36 -> 82.450819 | H38: =E38+F38+G38 -> 38.515058
A39: 31 | B39: =_xlfn.LOGNORM.INV(RAND(), $O$31, $O$32) -> 1.2492307 | C39: =_xlfn.LOGNORM.INV(RAND(), $O$28, $O$29) -> 123.39102 | D39: =_xlfn.LOGNORM.INV(RAND(), $O$25, $O$26) -> 14.547584 | E39: =((B39-$B$5)/0.1)*$D$5 + ((C39-$B$6)/10)*$D$6 + ((D39-$B$7)/10)*$D$7 -> -229.77672 | F39: =IF(OR(B39<0.4, D39>50), 150, 0) -> 0 | G39: =(D39/10)*D37 -> 102.45272 | H39: =E39+F39+G39 -> -127.32401
A40: 32 | B40: =_xlfn.LOGNORM.INV(RAND(), $O$31, $O$32) -> 1.2384542 | C40: =_xlfn.LOGNORM.INV(RAND(), $O$28, $O$29) -> 26.366217 | D40: =_xlfn.LOGNORM.INV(RAND(), $O$25, $O$26) -> 83.671246 | E40: =((B40-$B$5)/0.1)*$D$5 + ((C40-$B$6)/10)*$D$6 + ((D40-$B$7)/10)*$D$7 -> 213.50968 | F40: =IF(OR(B40<0.4, D40>50), 150, 0) -> 150 | G40: =(D40/10)*D38 -> 306.3651 | H40: =E40+F40+G40 -> 669.87478
A41: 33 | B41: =_xlfn.LOGNORM.INV(RAND(), $O$31, $O$32) -> 1.7190274 | C41: =_xlfn.LOGNORM.INV(RAND(), $O$28, $O$29) -> 56.22879 | D41: =_xlfn.LOGNORM.INV(RAND(), $O$25, $O$26) -> 25.919758 | E41: =((B41-$B$5)/0.1)*$D$5 + ((C41-$B$6)/10)*$D$6 + ((D41-$B$7)/10)*$D$7 -> -49.0622 | F41: =IF(OR(B41<0.4, D41>50), 150, 0) -> 0 | G41: =(D41/10)*D39 -> 37.706984 | H41: =E41+F41+G41 -> -11.355215
A42: 34 | B42: =_xlfn.LOGNORM.INV(RAND(), $O$31, $O$32) -> 2.2581068 | C42: =_xlfn.LOGNORM.INV(RAND(), $O$28, $O$29) -> 116.89106 | D42: =_xlfn.LOGNORM.INV(RAND(), $O$25, $O$26) -> 73.869686 | E42: =((B42-$B$5)/0.1)*$D$5 + ((C42-$B$6)/10)*$D$6 + ((D42-$B$7)/10)*$D$7 -> 851.63243 | F42: =IF(OR(B42<0.4, D42>50), 150, 0) -> 150 | G42: =(D42/10)*D40 -> 618.07687 | H42: =E42+F42+G42 -> 1619.7093
A43: 35 | B43: =_xlfn.LOGNORM.INV(RAND(), $O$31, $O$32) -> 1.161372 | C43: =_xlfn.LOGNORM.INV(RAND(), $O$28, $O$29) -> 96.729627 | D43: =_xlfn.LOGNORM.INV(RAND(), $O$25, $O$26) -> 65.005428 | E43: =((B43-$B$5)/0.1)*$D$5 + ((C43-$B$6)/10)*$D$6 + ((D43-$B$7)/10)*$D$7 -> 164.2189 | F43: =IF(OR(B43<0.4, D43>50), 150, 0) -> 150 | G43: =(D43/10)*D41 -> 168.49249 | H43: =E43+F43+G43 -> 482.7114
A44: 36 | B44: =_xlfn.LOGNORM.INV(RAND(), $O$31, $O$32) -> 0.82443011 | C44: =_xlfn.LOGNORM.INV(RAND(), $O$28, $O$29) -> 178.5642 | D44: =_xlfn.LOGNORM.INV(RAND(), $O$25, $O$26) -> 16.134624 | E44: =((B44-$B$5)/0.1)*$D$5 + ((C44-$B$6)/10)*$D$6 + ((D44-$B$7)/10)*$D$7 -> -288.37365 | F44: =IF(OR(B44<0.4, D44>50), 150, 0) -> 0 | G44: =(D44/10)*D42 -> 119.18596 | H44: =E44+F44+G44 -> -169.18768
... A1008: 1000 | B1008: =_xlfn.LOGNORM.INV(RAND(), $O$31, $O$32) -> 1.658505 | C1008: =_xlfn.LOGNORM.INV(RAND(), $O$28, $O$29) -> 108.26194 | D1008: =_xlfn.LOGNORM.INV(RAND(), $O$25, $O$26) -> 26.669191 | E1008: =((B1008-$B$5)/0.1)*$D$5 + ((C1008-$B$6)/10)*$D$6 + ((D1008-$B$7)/10)*$D$7 -> 58.253782 | F1008: =IF(OR(B1008<0.4, D1008>50), 150, 0) -> 0 | G1008: =(D1008/10)*D1006 -> 54.287671 | H1008: =E1008+F1008+G1008 -> 112.54145

Sheet Sneha
A1: Credit price mean ($/credit) | B1: 38
A2: Credit price stdev ($) | B2: 7
A3: Compliance exposure (credits/yr) | B3: 9500000
A4: Internal offset % | B4: 0.45
A5: Pass-through % | B5: 0.3 | N5: compliance cost formula
A6: Accrued fraction % | B6: 0.3 | N6: =(C12*B12*(1-B5)*(1-B4))/B8 -> 135.26226
A7: Sim paths (rows) | B7: 1000
A8: $ scale (1 for $, 1,000,000 for $M) | B8: 1000000
A11: Path | B11: Carbon Credit Price ($) | C11: Exposure | D11: Offset % | E11: Gross Cost | F11: Offset $ | G11: Net After Offset | H11: Pass-Through $ | I11: Compliance Cost | J11: ΔNWC ($M) | K11: Curr Liab Δ ($M) | L11: Equity Δ ($M)
A12: =ROW()-11 -> 1 | B12: =_xlfn.NORM.INV(RAND(),$B$1,$B$2) -> 36.982162 | C12: =$B$3 -> 9500000 | D12: =$B$4 -> 0.45 | E12: =(B12*C12)/$B$8 -> 351.33054 | F12: =E12*D12 -> 158.09874 | G12: =E12-F12 -> 193.23179 | H12: =G12*$B$5 -> 57.969538 | I12: =G12-H12 -> 135.26226 | J12: =I12*(1-$B$6) -> 94.683579 | K12: =-I12*$B$6 -> -40.578677 | L12: =-I12 -> -135.26226
A13: =ROW()-11 -> 2 | B13: =_xlfn.NORM.INV(RAND(),$B$1,$B$2) -> 23.07436 | C13: =$B$3 -> 9500000 | D13: =$B$4 -> 0.45 | E13: =(B13*C13)/$B$8 -> 219.20642 | F13: =E13*D13 -> 98.642891 | G13: =E13-F13 -> 120.56353 | H13: =G13*$B$5 -> 36.16906 | I13: =G13-H13 -> 84.394473 | J13: =I13*(1-$B$6) -> 59.076131 | K13: =-I13*$B$6 -> -25.318342 | L13: =-I13 -> -84.394473
A14: =ROW()-11 -> 3 | B14: =_xlfn.NORM.INV(RAND(),$B$1,$B$2) -> 41.802983 | C14: =$B$3 -> 9500000 | D14: =$B$4 -> 0.45 | E14: =(B14*C14)/$B$8 -> 397.12834 | F14: =E14*D14 -> 178.70775 | G14: =E14-F14 -> 218.42059 | H14: =G14*$B$5 -> 65.526176 | I14: =G14-H14 -> 152.89441 | J14: =I14*(1-$B$6) -> 107.02609 | K14: =-I14*$B$6 -> -45.868323 | L14: =-I14 -> -152.89441 | N14: Average Compliance Cost | O14: =AVERAGE(I20:INDEX(I:I,19+$B$7)) -> 139.88173
A15: =ROW()-11 -> 4 | B15: =_xlfn.NORM.INV(RAND(),$B$1,$B$2) -> 41.229883 | C15: =$B$3 -> 9500000 | D15: =$B$4 -> 0.45 | E15: =(B15*C15)/$B$8 -> 391.68389 | F15: =E15*D15 -> 176.25775 | G15: =E15-F15 -> 215.42614 | H15: =G15*$B$5 -> 64.627842 | I15: =G15-H15 -> 150.7983 | J15: =I15*(1-$B$6) -> 105.55881 | K15: =-I15*$B$6 -> -45.239489 | L15: =-I15 -> -150.7983 | N15: P5 (worst case) | O15: =_xlfn.PERCENTILE.INC(I20:INDEX(I:I,19+$B$7),0.05) -> 98.93809
A16: =ROW()-11 -> 5 | B16: =_xlfn.NORM.INV(RAND(),$B$1,$B$2) -> 34.515772 | C16: =$B$3 -> 9500000 | D16: =$B$4 -> 0.45 | E16: =(B16*C16)/$B$8 -> 327.89984 | F16: =E16*D16 -> 147.55493 | G16: =E16-F16 -> 180.34491 | H16: =G16*$B$5 -> 54.103473 | I16: =G16-H16 -> 126.24144 | J16: =I16*(1-$B$6) -> 88.369006 | K16: =-I16*$B$6 -> -37.872431 | L16: =-I16 -> -126.24144 | N16: P95 (best case) | O16: =_xlfn.PERCENTILE.INC(I20:INDEX(I:I,19+$B$7),0.95) -> 181.84693
A17: =ROW()-11 -> 6 | B17: =_xlfn.NORM.INV(RAND(),$B$1,$B$2) -> 46.138169 | C17: =$B$3 -> 9500000 | D17: =$B$4 -> 0.45 | E17: =(B17*C17)/$B$8 -> 438.3126 | F17: =E17*D17 -> 197.24067 | G17: =E17-F17 -> 241.07193 | H17: =G17*$B$5 -> 72.321579 | I17: =G17-H17 -> 168.75035 | J17: =I17*(1-$B$6) -> 118.12525 | K17: =-I17*$B$6 -> -50.625106 | L17: =-I17 -> -168.75035 | N17: Std Dev | O17: =_xlfn.STDEV.P(I20:INDEX(I:I,19+$B$7)) -> 25.40655
A18: =ROW()-11 -> 7 | B18: =_xlfn.NORM.INV(RAND(),$B$1,$B$2) -> 40.077711 | C18: =$B$3 -> 9500000 | D18: =$B$4 -> 0.45 | E18: =(B18*C18)/$B$8 -> 380.73826 | F18: =E18*D18 -> 171.33222 | G18: =E18-F18 -> 209.40604 | H18: =G18*$B$5 -> 62.821813 | I18: =G18-H18 -> 146.58423 | J18: =I18*(1-$B$6) -> 102.60896 | K18: =-I18*$B$6 -> -43.975269 | L18: =-I18 -> -146.58423
A19: =ROW()-11 -> 8 | B19: =_xlfn.NORM.INV(RAND(),$B$1,$B$2) -> 36.41847 | C19: =$B$3 -> 9500000 | D19: =$B$4 -> 0.45 | E19: =(B19*C19)/$B$8 -> 345.97547 | F19: =E19*D19 -> 155.68896 | G19: =E19-F19 -> 190.28651 | H19: =G19*$B$5 -> 57.085952 | I19: =G19-H19 -> 133.20055 | J19: =I19*(1-$B$6) -> 93.240388 | K19: =-I19*$B$6 -> -39.960166 | L19: =-I19 -> -133.20055 | N19: Balancesheet Summary
A20: =ROW()-11 -> 9 | B20: =_xlfn.NORM.INV(RAND(),$B$1,$B$2) -> 44.001329 | C20: =$B$3 -> 9500000 | D20: =$B$4 -> 0.45 | E20: =(B20*C20)/$B$8 -> 418.01262 | F20: =E20*D20 -> 188.10568 | G20: =E20-F20 -> 229.90694 | H20: =G20*$B$5 -> 68.972082 | I20: =G20-H20 -> 160.93486 | J20: =I20*(1-$B$6) -> 112.6544 | K20: =-I20*$B$6 -> -48.280458 | L20: =-I20 -> -160.93486 | N20: Average Compliance Cost ($M) | O20: =AVERAGE(I20:INDEX(I:I,19+$B$7)) -> 139.88173
A21: =ROW()-11 -> 10 | B21: =_xlfn.NORM.INV(RAND(),$B$1,$B$2) -> 50.443846 | C21: =$B$3 -> 9500000 | D21: =$B$4 -> 0.45 | E21: =(B21*C21)/$B$8 -> 479.21654 | F21: =E21*D21 -> 215.64744 | G21: =E21-F21 -> 263.56909 | H21: =G21*$B$5 -> 79.070728 | I21: =G21-H21 -> 184.49837 | J21: =I21*(1-$B$6) -> 129.14886 | K21: =-I21*$B$6 -> -55.34951 | L21: =-I21 -> -184.49837 | N21: Paid Portion (Cash Outflow) | O21: =ROUND(C54*(1-$B$5),2) -> 6650000
A22: =ROW()-11 -> 11 | B22: =_xlfn.NORM.INV(RAND(),$B$1,$B$2) -> 42.464736 | C22: =$B$3 -> 9500000 | D22: =$B$4 -> 0.45 | E22: =(B22*C22)/$B$8 -> 403.41499 | F22: =E22*D22 -> 181.53675 | G22: =E22-F22 -> 221.87824 | H22: =G22*$B$5 -> 66.563473 | I22: =G22-H22 -> 155.31477 | J22: =I22*(1-$B$6) -> 108.72034 | K22: =-I22*$B$6 -> -46.594431 | L22: =-I22 -> -155.31477 | N22: Accrued Portion (Current Liabilities) | O22: =ROUND(C54*$B$5,2) -> 2850000
A23: =ROW()-11 -> 12 | B23: =_xlfn.NORM.INV(RAND(),$B$1,$B$2) -> 39.95932 | C23: =$B$3 -> 9500000 | D23: =$B$4 -> 0.45 | E23: =(B23*C23)/$B$8 -> 379.61354 | F23: =E23*D23 -> 170.82609 | G23: =E23-F23 -> 208.78745 | H23: =G23*$B$5 -> 62.636234 | I23: =G23-H23 -> 146.15121 | J23: =I23*(1-$B$6) -> 102.30585 | K23: =-I23*$B$6 -> -43.845364 | L23: =-I23 -> -146.15121 | N23: Total Equity Impact (Retained Earnings) | O23: =ROUND(-C54,2) -> -9500000
A24: =ROW()-11 -> 13 | B24: =_xlfn.NORM.INV(RAND(),$B$1,$B$2) -> 44.06842 | C24: =$B$3 -> 9500000 | D24: =$B$4 -> 0.45 | E24: =(B24*C24)/$B$8 -> 418.64999 | F24: =E24*D24 -> 188.3925 | G24: =E24-F24 -> 230.2575 | H24: =G24*$B$5 -> 69.077249 | I24: =G24-H24 -> 161.18025 | J24: =I24*(1-$B$6) -> 112.82617 | K24: =-I24*$B$6 -> -48.354074 | L24: =-I24 -> -161.18025 | N24: Change in Net Working Capital (ΔNWC) | O24: =ROUND(-(C55+C56),2) -> -19000000
A25: =ROW()-11 -> 14 | B25: =_xlfn.NORM.INV(RAND(),$B$1,$B$2) -> 46.972331 | C25: =$B$3 -> 9500000 | D25: =$B$4 -> 0.45 | E25: =(B25*C25)/$B$8 -> 446.23715 | F25: =E25*D25 -> 200.80672 | G25: =E25-F25 -> 245.43043 | H25: =G25*$B$5 -> 73.629129 | I25: =G25-H25 -> 171.8013 | J25: =I25*(1-$B$6) -> 120.26091 | K25: =-I25*$B$6 -> -51.540391 | L25: =-I25 -> -171.8013
A26: =ROW()-11 -> 15 | B26: =_xlfn.NORM.INV(RAND(),$B$1,$B$2) -> 45.578689 | C26: =$B$3 -> 9500000 | D26: =$B$4 -> 0.45 | E26: =(B26*C26)/$B$8 -> 432.99754 | F26: =E26*D26 -> 194.84889 | G26: =E26-F26 -> 238.14865 | H26: =G26*$B$5 -> 71.444594 | I26: =G26-H26 -> 166.70405 | J26: =I26*(1-$B$6) -> 116.69284 | K26: =-I26*$B$6 -> -50.011216 | L26: =-I26 -> -166.70405
A27: =ROW()-11 -> 16 | B27: =_xlfn.NORM.INV(RAND(),$B$1,$B$2) -> 52.840622 | C27: =$B$3 -> 9500000 | D27: =$B$4 -> 0.45 | E27: =(B27*C27)/$B$8 -> 501.98591 | F27: =E27*D27 -> 225.89366 | G27: =E27-F27 -> 276.09225 | H27: =G27*$B$5 -> 82.827675 | I27: =G27-H27 -> 193.26457 | J27: =I27*(1-$B$6) -> 135.2852 | K27: =-I27*$B$6 -> -57.979372 | L27: =-I27 -> -193.26457
A28: =ROW()-11 -> 17 | B28: =_xlfn.NORM.INV(RAND(),$B$1,$B$2) -> 45.649168 | C28: =$B$3 -> 9500000 | D28: =$B$4 -> 0.45 | E28: =(B28*C28)/$B$8 -> 433.6671 | F28: =E28*D28 -> 195.15019 | G28: =E28-F28 -> 238.5169 | H28: =G28*$B$5 -> 71.555071 | I28: =G28-H28 -> 166.96183 | J28: =I28*(1-$B$6) -> 116.87328 | K28: =-I28*$B$6 -> -50.08855 | L28: =-I28 -> -166.96183
A29: =ROW()-11 -> 18 | B29: =_xlfn.NORM.INV(RAND(),$B$1,$B$2) -> 27.228705 | C29: =$B$3 -> 9500000 | D29: =$B$4 -> 0.45 | E29: =(B29*C29)/$B$8 -> 258.6727 | F29: =E29*D29 -> 116.40271 | G29: =E29-F29 -> 142.26998 | H29: =G29*$B$5 -> 42.680995 | I29: =G29-H29 -> 99.588988 | J29: =I29*(1-$B$6) -> 69.712292 | K29: =-I29*$B$6 -> -29.876696 | L29: =-I29 -> -99.588988
A30: =ROW()-11 -> 19 | B30: =_xlfn.NORM.INV(RAND(),$B$1,$B$2) -> 39.050684 | C30: =$B$3 -> 9500000 | D30: =$B$4 -> 0.45 | E30: =(B30*C30)/$B$8 -> 370.9815 | F30: =E30*D30 -> 166.94167 | G30: =E30-F30 -> 204.03982 | H30: =G30*$B$5 -> 61.211947 | I30: =G30-H30 -> 142.82788 | J30: =I30*(1-$B$6) -> 99.979513 | K30: =-I30*$B$6 -> -42.848363 | L30: =-I30 -> -142.82788
A31: =ROW()-11 -> 20 | B31: =_xlfn.NORM.INV(RAND(),$B$1,$B$2) -> 27.796642 | C31: =$B$3 -> 9500000 | D31: =$B$4 -> 0.45 | E31: =(B31*C31)/$B$8 -> 264.0681 | F31: =E31*D31 -> 118.83065 | G31: =E31-F31 -> 145.23746 | H31: =G31*$B$5 -> 43.571237 | I31: =G31-H31 -> 101.66622 | J31: =I31*(1-$B$6) -> 71.166354 | K31: =-I31*$B$6 -> -30.499866 | L31: =-I31 -> -101.66622
A32: =ROW()-11 -> 21 | B32: =_xlfn.NORM.INV(RAND(),$B$1,$B$2) -> 44.922853 | C32: =$B$3 -> 9500000 | D32: =$B$4 -> 0.45 | E32: =(B32*C32)/$B$8 -> 426.7671 | F32: =E32*D32 -> 192.0452 | G32: =E32-F32 -> 234.72191 | H32: =G32*$B$5 -> 70.416572 | I32: =G32-H32 -> 164.30533 | J32: =I32*(1-$B$6) -> 115.01373 | K32: =-I32*$B$6 -> -49.2916 | L32: =-I32 -> -164.30533
A33: =ROW()-11 -> 22 | B33: =_xlfn.NORM.INV(RAND(),$B$1,$B$2) -> 44.001536 | C33: =$B$3 -> 9500000 | D33: =$B$4 -> 0.45 | E33: =(B33*C33)/$B$8 -> 418.01459 | F33: =E33*D33 -> 188.10657 | G33: =E33-F33 -> 229.90803 | H33: =G33*$B$5 -> 68.972408 | I33: =G33-H33 -> 160.93562 | J33: =I33*(1-$B$6) -> 112.65493 | K33: =-I33*$B$6 -> -48.280686 | L33: =-I33 -> -160.93562
A34: =ROW()-11 -> 23 | B34: =_xlfn.NORM.INV(RAND(),$B$1,$B$2) -> 31.352222 | C34: =$B$3 -> 9500000 | D34: =$B$4 -> 0.45 | E34: =(B34*C34)/$B$8 -> 297.84611 | F34: =E34*D34 -> 134.03075 | G34: =E34-F34 -> 163.81536 | H34: =G34*$B$5 -> 49.144608 | I34: =G34-H34 -> 114.67075 | J34: =I34*(1-$B$6) -> 80.269527 | K34: =-I34*$B$6 -> -34.401226 | L34: =-I34 -> -114.67075
A35: =ROW()-11 -> 24 | B35: =_xlfn.NORM.INV(RAND(),$B$1,$B$2) -> 42.581666 | C35: =$B$3 -> 9500000 | D35: =$B$4 -> 0.45 | E35: =(B35*C35)/$B$8 -> 404.52583 | F35: =E35*D35 -> 182.03662 | G35: =E35-F35 -> 222.48921 | H35: =G35*$B$5 -> 66.746762 | I35: =G35-H35 -> 155.74244 | J35: =I35*(1-$B$6) -> 109.01971 | K35: =-I35*$B$6 -> -46.722733 | L35: =-I35 -> -155.74244
A36: =ROW()-11 -> 25 | B36: =_xlfn.NORM.INV(RAND(),$B$1,$B$2) -> 32.055206 | C36: =$B$3 -> 9500000 | D36: =$B$4 -> 0.45 | E36: =(B36*C36)/$B$8 -> 304.52446 | F36: =E36*D36 -> 137.036 | G36: =E36-F36 -> 167.48845 | H36: =G36*$B$5 -> 50.246535 | I36: =G36-H36 -> 117.24192 | J36: =I36*(1-$B$6) -> 82.069341 | K36: =-I36*$B$6 -> -35.172575 | L36: =-I36 -> -117.24192
... A1011: =ROW()-11 -> 1000 | B1011: =_xlfn.NORM.INV(RAND(),$B$1,$B$2) -> 36.962238 | C1011: =$B$3 -> 9500000 | D1011: =$B$4 -> 0.45 | E1011: =(B1011*C1011)/$B$8 -> 351.14126 | F1011: =E1011*D1011 -> 158.01357 | G1011: =E1011-F1011 -> 193.12769 | H1011: =G1011*$B$5 -> 57.938308 | I1011: =G1011-H1011 -> 135.18939 | J1011: =I1011*(1-$B$6) -> 94.63257 | K1011: =-I1011*$B$6 -> -40.556816 | L1011: =-I1011 -> -135.18939

Sheet Balance Sheet
A1: Balance Sheet | B1: 2024 As Reported | C1: 2024 Simulation Results | E1: Simulated | J1: Simulated
A2: ASSETS
A3: Cash And Equivalents | B3: 4657 | J3: 4657
A4: operating cash flow from simulation(CFO) | C4: =Arvind!D21/1000000 -> 66.845427 | J4: ='Income Statement Yearly'!C18 -> 2980.7058
A5: = Cash and Cash Equivalents | C5: =Sneha!O20 -> 139.88173
A6: + Cash and Cash Equivalents | C6: =B5 -> 0
A7: Total Cash & ST Investments | B7: =B4 -> 0 | C7: =C4+C6 -> 66.845427 | J7: =J4 -> 2980.7058
A9: Accounts Receivable | B9: 9731 | J9: 9731
A10: = Allowance for Doubtful Accounts Receivable | B10: -20 | J10: -20
A11: + Allowance for Doubtful Accounts Receivable | B11: - | J11: -
A12: + Receivables | B12: 10708 | J12: 10708
A13: - Derivative Assets, Current | B13: 5812 | J13: 5812
A14: - Accounts Receivables | B14: 3939 | J14: 3939
A15: - Derivative Assets, Current | B15: -20 | J15: -20
A16: - Other Receivables | B16: 272 | J16: 272
A17: - Other Receivables | B17: 705 | J17: 705
A18: + Receivables | B18: 10708 | J18: 10708
A19: - Allowance for Doubtful Accounts Receivable | B19: -20 | J19: -20
A20: - Other Receivables | B20: 272 | J20: 272
A21: - Other Receivables | B21: 705 | J21: 705
A22: Other Receivables | B22: 977 | J22: 977
A23: = Other Receivables | B23: - | J23: -
A24: + Other Receivables | B24: 272 | J24: 272
A25: + Other Receivables | B25: 705 | J25: 705
A26: Total Receivables | B26: 10708 | J26: 10708
A28: Inventory | B28: 7761 | C28: =SUM(C29:C33)+364 -> 45875.108 | D28: =C28/B28 -> 5.910979 | J28: 7761
A29: = Inventories - Raw Materials | B29: 364 | C29: =Krishna_V2!P6 -> -34.292093 | J29: 364
A30: + Inventories - Finished Goods | B30: 2167 | C30: =Krishna_V2!L6 -> 6855.5269 | J30: 2167
A31: + Inventories - Finished Goods | B31: 4016 | C31: =Krishna_V2!M6 -> 10985.117 | J31: 4016
A32: + Inventories - Finished Goods | B32: 872 | C32: =Krishna_V2!N6 -> 27558.865 | J32: 872
A33: + Inventories - Finished Goods | B33: 342 | C33: =Krishna_V2!O6 -> 145.89054 | J33: 342
A34: Prepaid Exp. | B34: 611 | C34: =SUM(C35:C36) -> 611 | J34: 611
A35: = Prepaid Expenses and Other Current Assets | B35: 611 | C35: =B35 -> 611 | J35: 611
A36: + Prepaid Expenses and Others | B36: - | C36: 0 | J36: -
A37: Other Current Assets | B37: - | C37: =SUM(C38:C40) -> 0 | J37: -
A38: = Derivative Assets, Current | B38: - | C38: 0 | J38: -
A39: + Derivative Assets, Current | B39: - | C39: 0 | J39: -
A40: + Derivative Assets, Current | B40: - | C40: 0 | J40: -
A41: Total Current Assets | B41: 23737 | J41: 23737
A43: Gross Property, Plant & Equipment | B43: 53466 | C43: =B43 -> 53466 | D43: Gross PP&E used for calculation in C54 | J43: 53466
A44: = Right-of-use asset-Capital lease -Gross | B44: 3348 | J44: 3348
A45: + Right-of-Use asset-Operating lease-Gross | B45: 1098 | J45: 1098
A46: + Buildings | B46: 1147 | J46: 1147
A47: + Land | B47: 500 | J47: 500
A48: + Construction in Progress | B48: 604 | J48: 604
A49: + Other Property, Plant and Equipment | B49: 34089 | J49: 34089
A50: + Other Property, Plant and Equipment | B50: 6013 | J50: 6013
A51: + Other Property, Plant and Equipment | B51: 3616 | J51: 3616
A52: + Other Property, Plant and Equipment | B52: 1058 | J52: 1058
A53: + Other Property, Plant and Equipment | B53: 1993 | J53: 1993
A54: + Gross Property Plant and Equipment | B54: - | J54: -
A55: Accumulated Depreciation | B55: -23054 | C55: =Ramita!F9 -> 0 | D55: Less: Accumulated Depreciation (in this case, PP&E Impairment) | J55: -23054
A56: = Right-of-use asset-Capital lease -Accumulated Depreciation | B56: - | J56: -
A57: + Accumulated Depreciation | B57: -23054 | J57: -23054
A58: - Right-of-use asset-Capital lease -Accumulated Depreciation | B58: - | J58: -
A59: Less: Accumulated Impairment | C59: =C43-C55 -> 53466 | D59: NET PP&E For only treatment of Impairment
A60: Net Property, Plant & Equipment | B60: 30412 | J60: 30412
B61: 695 | J61: 695
A62: Long-term Investments | B62: - | J62: -
A63: = Equity Method Investments | B63: 695 | J63: 695
A64: + Equity Method Investments | B64: 260 | J64: 260
A65: Goodwill | B65: 260 | J65: 260
A66: = Goodwill | B66: - | J66: -
A67: + Goodwill | B67: 151 | J67: 151
A68: Other Intangibles | B68: - | J68: -
A69: = Intangible Assets | B69: 151 | J69: 151
A70: + Intangible Assets | B70: 2689 | J70: 2689
A71: Deferred Charges, LT | B71: - | J71: -
A72: = Deferred Charges | B72: 2689 | J72: 2689
A73: - Equity Method Investments | B73: 2199 | J73: 2199
A74: Other Long-Term Assets | B74: 7092 | J74: 7092
A75: = Deferred Charges and Other Assets | B75: 2689 | J75: 2689
A76: - Deferred Charges | B76: 1098 | J76: 1098
A77: - Right-of-Use asset-Operating lease-Gross | B77: 695 | J77: 695
A78: - Equity Method Investments | B78: 488 | J78: 488
A79: - Other Receivables Long Term | B79: 260 | J79: 260
A80: - Goodwill | B80: 151 | J80: 151
A81: - Goodwill | B81: 317 | J81: 317
A82: - Other Receivables Long Term | B82: 488 | J82: 488
A83: + Other Receivables Long Term | B83: 317 | J83: 317
A84: + Other Receivables Long Term | B84: 60143 | J84: 60143
A85: Total Assets
A87: LIABILITIES | B87: 12092 | J87: 12092
A88: Accounts Payable | B88: 12092 | J88: 12092
A89: = Accounts Payable | B89: - | J89: -
A90: + Accounts Payable | B90: 2030 | J90: 2030
A91: Accrued Exp. | B91: 1130 | J91: 1130
A92: = Accrued Expenses | B92: 378 | J92: 378
A93: - Current Portion Of Lease Liabilities | B93: 73 | J93: 73
A94: - Accrued Expenses | B94: 45 | J94: 45
A95: - Accrued Expenses | B95: 307 | J95: 307
A96: - Accrued Expenses | B96: 68 | J96: 68
A97: - Accrued Expenses | B97: 82 | J97: 82
A98: - Unearned Revenue, Current | B98: 78 | J98: 78
A99: - Accrued Expenses | B99: 99 | J99: 99
A100: - Accrued Expenses | B100: 1130 | J100: 1130
A101: + Accrued Expenses | B101: 378 | J101: 378
... A126: - Accrued Expenses | B126: 99 | J126: 99
A127: - Accrued Expenses | B127: - | J127: -
A128: + Accrued Expenses | B128: 1130 | J128: 1130
...

Sheet Income Statement Yearly
A1: For the Fiscal Period Ending | B1: 12 months Dec-31-2024 | C1: Simulated
A2: Currency | B2: USD | C2: USD
A4: Revenue | B4: 123974 | C4: 123974
A5: Other Revenue | B5: 0 | C5: 0
A6: Total Revenue | B6: =B4+B5 -> 123974 | C6: =C4+C5 -> 123974
A8: Cost Of Goods Sold | B8: 116440 | C8: 116440
A9: Gross Profit | B9: =B6-B8 -> 7534 | C9: =C6-C8 -> 7534
A11: Selling General & Admin Exp. | B11: 871 | C11: 871
A12: R & D Exp. | B12: - | C12: -
A13: Depreciation & Amort. | B13: 2774 | C13: 2774
A14: Other Operating Expense/(Income) | B14: 44 | C14: 44
A16: Other Operating Exp., Total | B16: 3689 | C16: 3689
A18: Operating Income | B18: 3845 | C18: =Arvind!D21/1000000-Sneha!O14+'Income Statement Yearly'!B13+Ramita!K5 -> 2980.7058 | D18: =C18/B18 -> 0.77521607 | E18: 1
A20: Interest Expense | B20: -556
A21: Interest and Invest. Income | B21: -
A22: Net Interest Exp. | B22: -556 | C22: -556
A24: Other Non-Operating Inc. (Exp.) | B24: 409 | C24: 409
A25: EBT Excl. Unusual Items | B25: =B18+B22+B24 -> 3698 | C25: =C18+C22+C24 -> 2833.7058
A27: Restructuring Charges | B27: -
A28: Impairment of Goodwill | B28: -
A29: Other Unusual Items | B29: -
A30: EBT Incl. Unusual Items | B30: 3698 | C30: =C25 -> 2833.7058
A32: Income Tax Expense | B32: 692 | C32: 692
A33: Earnings from Cont. Ops. | B33: 3006 | C33: =C30-C32 -> 2141.7058
A35: Earnings of Discontinued Ops. | B35: -
A36: Extraord. Item & Account. Change | B36: -
A37: Net Income to Company | B37: 3006 | C37: =C33 -> 2141.7058
A39: Minority Int. in Earnings | B39: -236 | C39: -236
A40: Net Income | B40: 2770 | C40: =C37+C39 -> 1905.7058
A42: Pref. Dividends and Other Adj. | B42: 8 | C42: 8
A44: NI to Common Incl Extra Items | B44: 2762 | C44: =C40-C42 -> 1897.7058
A45: NI to Common Excl. Extra Items | B45: 2762 | C45: =C40-C42 -> 1897.7058

Sheet Balance Sheet Yearly
A1: Balance Sheet as of: Dec-31-2024 | B1: As Reported | F1: As Simulated
A2: Currency | B2: USD | F2: USD
A3: ASSETS
A4: Cash Flow from Operations (CFO) | F4: =Arvind!D21/1000000+Ramita!K5-Sneha!O14+'Income Statement Yearly'!B13 -> 2980.7058
A5: Cash And Equivalents | B5: 4657
A6: Total Cash & ST Investments | B6: 4657 | F6: =F4 -> 2980.7058 | G6: =F6/B6 -> 0.64004848
A8: Accounts Receivable | B8: 9731 | F8: 9731
A9: Other Receivables | B9: 977 | F9: 977
A10: Total Receivables | B10: 10708 | F10: 10708
A12: Inventory | B12: 7761 | F12: =Krishna_V2!L6 -> 6855.5269 | G12: =F12/B12 -> 0.88333036
A13: Prepaid Exp. | B13: 611 | F13: 611
A14: Other Current Assets | B14: -
A15: Total Current Assets | B15: 23737 | F15: =F6+F10+F12+F13+F14 -> 21155.233
A17: Gross Property, Plant & Equipment | B17: 53466 | F17: 53466
A18: Accumulated Depreciation | B18: -23054 | F18: -23054
A19: Net Property, Plant & Equipment | B19: 30412 | F19: 30412
A21: Long-term Investments | B21: 695 | F21: 695
A22: Goodwill | B22: 260 | F22: 260
A23: Other Intangibles | B23: 151 | F23: 151
A24: Deferred Charges, LT | B24: 2689 | F24: 2689
A25: Other Long-Term Assets | B25: 2199 | F25: 2199
A26: Total Assets | B26: 60143 | F26: =F15+F19+SUM(F21:F25) -> 57561.233 | G26: =F26/B26 -> 0.95707285
A28: LIABILITIES
A29: Accounts Payable | B29: 12092 | F29: =Krishna_V2!M6 -> 10985.117 | G29: =F29/B29 -> 0.90846154
A30: Accrued Exp. | B30: 2030 | F30: 2030
A31: Curr. Port. of LT Debt | B31: 499 | F31: 499
A32: Curr. Port. of Leases | B32: 622 | F32: 622
A33: Curr. Income Taxes Payable | B33: 170 | F33: 170
A34: Unearned Revenue, Current | B34: 82 | F34: 82
A35: Other Current Liabilities | B35: - | F35: -
A36: Total Current Liabilities | B36: 15495 | F36: =SUM(F29:F35) -> 14388.117
A38: Long-Term Debt | B38: 7586 | F38: 7586
A39: Long-Term Leases | B39: 2833 | F39: 2833
A40: Pension & Other Post-Retire. Benefits | B40: 423 | F40: 423
A41: Def. Tax Liability, Non-Curr. | B41: 5267 | F41: 5267
A42: Other Non-Current Liabilities | B42: 1018 | F42: 1018
A43: Total Liabilities | B43: 32622 | F43: =SUM(F36:F42) -> 31515.117 | G43: =F43/B43 -> 0.96606943
A45: Common Stock | B45: 7 | F45: 7
A46: Additional Paid In Capital | B46: 6939 | F46: 6939
A47: Retained Earnings | B47: 47016 | F47: 47016
A48: Treasury Stock | B48: -28178 | F48: -28178
A49: Comprehensive Inc. and Other | B49: -1272 | F49: -1272
A50: Total Common Equity | B50: 24512 | F50: 24512
A52: Minority Interest | B52: 3009 | F52: 3009
A54: Total Equity | B54: 27521 | F54: 27521
A56: Total Liabilities And Equity | B56: 60143 | F56: =SUM(F54,F43) -> 59036.117 | G56: =F56/B56 -> 0.98159581

Sheet Income Statement
A1: For the Fiscal Period Ending | B1: 3 months Q1 Mar-31-2025 | C1: Restated 3 months Q2 Jun-30-2025 | D1: 3 months Q3 Sep-30-2025
A2: Currency | B2: USD | C2: USD | D2: USD
A4: Revenue | B4: 28754 | C4: 28227 | D4: 30341
A5: Other Revenue | B5: - | C5: - | D5: -
A6: Total Revenue | B6: 28754 | C6: 28227 | D6: 30341
A8: Cost Of Goods Sold | B8: 27567 | C8: 26192 | D8: 27695
A9: Gross Profit | B9: 1187 | C9: 2035 | D9: 2646
A11: Selling General & Admin Exp. | B11: 242 | C11: 200 | D11: 228
A12: R & D Exp. | B12: - | C12: - | D12: -
A13: Depreciation & Amort. | B13: 691 | C13: 714 | D13: 736
A14: Other Operating Expense/(Income) | B14: 4 | C14: 4 | D14: 5
A16: Other Operating Exp., Total | B16: 937 | C16: 918 | D16: 969
A18: Operating Income | B18: 250 | C18: 1117 | D18: 1677
A20: Interest Expense | B20: -137 | C20: -141 | D20: -139
A21: Interest and Invest. Income | B21: - | C21: - | D21: -
A22: Net Interest Exp. | B22: -137 | C22: -141 | D22: -139
A24: Other Non-Operating Inc. (Exp.) | B24: 101 | C24: 66 | D24: 68
A25: EBT Excl. Unusual Items | B25: 214 | C25: 1042 | D25: 1606
A27: Restructuring Charges | B27: -1131 | C27: -100 | D27: -150
A28: Impairment of Goodwill | B28: - | C28: - | D28: -
A29: Other Unusual Items | B29: - | C29: - | D29: -
A30: EBT Incl. Unusual Items | B30: -917 | C30: 942 | D30: 1456
A32: Income Tax Expense | B32: -265 | C32: 279 | D32: 390
A33: Earnings from Cont. Ops. | B33: -652 | C33: 663 | D33: 1066
A35: Earnings of Discontinued Ops. | B35: - | C35: - | D35: -
A36: Extraord. Item & Account. Change | B36: - | C36: - | D36: -
A37: Net Income to Company | B37: -652 | C37: 663 | D37: 1066
A39: Minority Int. in Earnings | B39: 57 | C39: 51 | D39: 29
A40: Net Income | B40: -595 | C40: 714 | D40: 1095
A42: Pref. Dividends and Other Adj. | B42: 1 | C42: -1 | D42: 3
A44: NI to Common Incl Extra Items | B44: -596 | C44: 715 | D44: 1092
A45: NI to Common Excl. Extra Items | B45: -596 | C45: 715 | D45: 1092
A47: Per Share Items
A48: Basic EPS | B48: -1.9 | C48: 2.29 | D48: 3.53
A49: Basic EPS Excl. Extra Items | B49: -1.9 | C49: 2.291666 | D49: 3.53398
A50: Weighted Avg. Basic Shares Out. | B50: 314 | C50: 312 | D50: 309
A52: Diluted EPS | B52: -1.9 | C52: 2.29 | D52: 3.53
A53: Diluted EPS Excl. Extra Items | B53: -1.9 | C53: 2.291666 | D53: 3.53
A54: Weighted Avg. Diluted Shares Out. | B54: 314 | C54: 312 | D54: 309
A56: Normalized Basic EPS | B56: 0.61 | C56: 2.25 | D56: 3.34
A57: Normalized Diluted EPS | B57: 0.607484 | C57: 2.250801 | D57: 3.342233
A59: Dividends per Share | B59: 1.13 | C59: 1.13 | D59: 1.13
A60: Payout Ratio % | B60: NM | C60: 0.495798 | D60: 0.320547
A62: Supplemental Items
A63: EBITDA | B63: 941 | C63: 1931 | D63: 2313
A64: EBITA | B64: 250 | C64: 1117 | D64: 1677
A65: EBIT | B65: 250 | C65: 1117 | D65: 1677
A66: Effective Tax Rate % | B66: NM | C66: 0.296178 | D66: 0.267857
A68: Normalized Net Income | B68: 190.75 | C68: 702.25 | D68: 1032.75
A69: Interest Capitalized | B69: 5 | C69: NA | D69: 5
A70: Interest on Long Term Debt | B70: 142 | C70: NA | D70: 144
A71: Non-Cash Pension Expense | B71: -20 | C71: - | D71: -20
A72: Filing Date | B72: 45771 | C72: 45953 | D72: 45953
A73: Restatement Type | B73: O | C73: RS | D73: O
A74: Calculation Type | B74: REP | C74: YTDQS | D74: REP
A76: Supplemental Operating Expense Items
A77: General and Administrative Exp. | B77: 261 | C77: 220 | D77: 246

Sheet Cash Flow Yearly
A1: For the Fiscal Period Ending | B1: 12 months Dec-31-2024
A2: Currency | B2: USD
A4: Net Income | B4: 2770
A5: Depreciation & Amort. | B5: 1922
A6: Amort. of Goodwill and Intangibles | B6: 852
A7: Depreciation & Amort., Total | B7: 2774
A9: Asset Writedown & Restructuring Costs | B9: -
A10: Other Operating Activities | B10: 149
A11: Change in Acc. Receivable | B11: 1562
A12: Change In Inventories | B12: -286
A13: Change in Acc. Payable | B13: -430
A14: Change in Inc. Taxes | B14: -146
A15: Change in Other Net Operating Assets | B15: 290
A16: Cash from Ops. | B16: 6683
A18: Capital Expenditure | B18: -907
A19: Cash Acquisitions | B19: -
A20: Divestitures | B20: -
A21: Invest. in Marketable & Equity Securt. | B21: 52
A22: Net (Inc.) Dec. in Loans Originated/Sold | B22: -
A23: Other Investing Activities | B23: -1126
A24: Cash from Investing | B24: -1981
A26: Short Term Debt Issued | B26: -
A27: Long-Term Debt Issued | B27: 7137
A28: Total Debt Issued | B28: 7137
A29: Short Term Debt Repaid | B29: -
A30: Long-Term Debt Repaid | B30: -7785
A31: Total Debt Repaid | B31: -7785
A33: Repurchase of Common Stock | B33: -2875
A35: Common Dividends Paid | B35: -1384
A36: Total Dividends Paid | B36: -1384
A38: Special Dividend Paid | B38: -
A39: Other Financing Activities | B39: -142
A40: Cash from Financing | B40: -5049
A42: Foreign Exchange Rate Adj. | B42: -248
A43: Net Change in Cash | B43: -595

Sheet Scenerio Analysis
G12: Regulatory | H12: change in Operating Income | I12: PP&E Impairment | J12: ARO Increase | K12: Total Impact
A14: Driver | B14: Best | C14: Worst | D14: Normal | G14: Best | H14: =(($B$15-Ramita!$O$31)/0.1)*Ramita!$D$5 + (($B$16-Ramita!$B$28)/10)*Ramita!$D$6 + (($B$17-Ramita!$B$25)/10)*Ramita!$D$7 -> 286.33567 | I14: =IF(OR($B$15<0.4, $B$17>50), 150, 0) -> 0 | J14: =($B$17/10)*Ramita!$D$7 -> 26.461748 | K14: =H14+I14+J14 -> 312.79741
A15: RIN Cost | B15: =LN(1.71) -> 0.53649337 | C15: =LN(0.512) -> -0.66943065 | D15: =LN(1.06) -> 0.058268908 | G15: Normal | H15: =(($D$15-Ramita!$O$31)/0.1)*Ramita!$D$5 + (($D$16-Ramita!$O$28)/10)*Ramita!$D$6 + (($D$17-Ramita!$O$25)/10)*Ramita!$D$7 -> 22.461029 | I15: =IF(OR($D$15<0.4, $D$17>50), 150, 0) -> 150 | J15: =($D$17/10)*Ramita!$D$7 -> 35.409593 | K15: =H15+I15+J15 -> 207.87062
A16: LCFS Price | B16: =LN(52.42) -> 3.9592882 | C16: =LN(200.85) -> 5.3025584 | D16: =LN(83.51) -> 4.4249664 | G16: Worst | H16: =(($C$15-Ramita!$O$31)/0.1)*Ramita!$D$5 + (($C$16-Ramita!$O$28)/10)*Ramita!$D$6 + (($C$17-Ramita!$O$25)/10)*Ramita!$D$7 -> -330.56159 | I16: =IF(OR($C$15<0.4, $C$17>50), 150, 0) -> 150 | J16: =($C$17/10)*Ramita!$D$7 -> 44.042772 | K16: =H16+I16+J16 -> -136.51882
A17: Carbon Price | B17: =LN(14.1) -> 2.6461748 | C17: =LN(81.8) -> 4.4042772 | D17: =LN(34.5) -> 3.5409593
A18: Utilization | B18: =Krishna_V2!S9 -> 0.96 | C18: =Krishna_V2!S8 -> 0.77 | D18: =Krishna_V2!S7 -> 0.92 | G18: Operational | H18: Inventory | I18: Accounts Payable | J18: COGS
G19: Best | H19: =Krishna_V2!$W$2+Krishna_V2!$V$2*'Scenerio Analysis'!B18+Krishna_V2!$Y$2+_xlfn.NORM.INV(RAND(),0,1) -> 7966.3516 | I19: =MAX(0,Krishna_V2!$W$3+Krishna_V2!$V$3*'Scenerio Analysis'!B18*Krishna_V2!$Y$3*_xlfn.NORM.INV(RAND(),0,1)) -> 1.1655861e+08 | J19: =Krishna_V2!$W$4+Krishna_V2!$V$4*'Scenerio Analysis'!B18+Krishna_V2!$Y$4*_xlfn.NORM.INV(RAND(),0,1) -> 41763.487
A20: Weightages | G20: Normal | H20: =Krishna_V2!$W$2+Krishna_V2!$V$2*'Scenerio Analysis'!D18+Krishna_V2!$Y$2+_xlfn.NORM.INV(RAND(),0,1) -> 7647.592 | I20: =MAX(0,Krishna_V2!$W$3+Krishna_V2!$V$3*'Scenerio Analysis'!D18*Krishna_V2!$Y$3*_xlfn.NORM.INV(RAND(),0,1)) -> 0 | J20: =Krishna_V2!$W$4+Krishna_V2!$V$4*'Scenerio Analysis'!D18+Krishna_V2!$Y$4*_xlfn.NORM.INV(RAND(),0,1) -> 37636.976
A21: Normal | B21: 0.7 | C21: Assuming | G21: Worst | H21: =Krishna_V2!$W$2+Krishna_V2!$V$2*'Scenerio Analysis'!C18+Krishna_V2!$Y$2+_xlfn.NORM.INV(RAND(),0,1) -> 6457.8501 | I21: =MAX(0, Krishna_V2!$W$3+Krishna_V2!$V$3*'Scenerio Analysis'!C18*Krishna_V2!$Y$3*_xlfn.NORM.INV(RAND(),0,1)) -> 0 | J21: =Krishna_V2!$W$4+Krishna_V2!$V$4*'Scenerio Analysis'!C18+Krishna_V2!$Y$4*_xlfn.NORM.INV(RAND(),0,1) -> 9411.0335
A22: Best | B22: 0.15 | C22: Assuming
A23: Worst | B23: 0.15 | C23: Assuming | H23: Inventory | I23: =B21*H20+B22*H19+B23*H21 -> 7516.9447 | J23: Accounts Payable | K23: =B21*I20+B22*I19+B23*I21 -> 17483792
H24: Regulatory | I24: =B21*K15+B22*K14+B23*K16 -> 171.95122
A25: Driver | B25: Best | C25: Worst | D25: Normal | H25: Market | I25: =B21*K28+B22*K27+B23*K29 -> 66618414
A26: ULS Diesel less WTI | B26: 29.680965 | C26: 11.424165 | D26: 20.542971 | G26: Market | H26: Refining Operating Income | I26: RD Operating Income | J26: Ethanol Operating Income | K26: Total Adjusted Operating Income
A27: Spread CBOB Gas less WTI | B27: 21.499923 | C27: 8.2665412 | D27: 14.834834 | G27: Best | H27: =(B26+B27)/2*Arvind!$C$4*365-Arvind!$C$5-Arvind!$C$6 -> 27290962 | I27: =(B29/1.7*42+B26)*Arvind!$C$7*365-Arvind!$C$8-Arvind!$C$9 -> 67213634 | J27: =(B31-B30/2.8)*Arvind!$C$10*365-Arvind!$C$11-Arvind!$C$12 -> 558771.17 | K27: =H27+I27+J27 -> 95063367
A28: RD Feedstock Cost (USGC UCO) | B28: 0.77321463 | C28: 0.33922333 | D28: 0.56113679 | G28: Normal | H28: =(D26+D27)/2*Arvind!$C$4*365-Arvind!$C$5-Arvind!$C$6 -> 18863731 | I28: =(D29/1.7*42+D26)*Arvind!$C$7*365-Arvind!$C$8-Arvind!$C$9 -> 47409919 | J28: =(D31-D30/2.8)*Arvind!$C$10*365-Arvind!$C$11-Arvind!$C$12 -> 376307.27 | K28: =H28+I28+J28 -> 66649958
A29: RD Reg. Price (Biodiesel RIN) | B29: 1.5268785 | C29: 0.6467057 | D29: 1.0929039 | G29: Worst | H29: =(C26+C27)/2*Arvind!$C$4*365-Arvind!$C$5-Arvind!$C$6 -> 10498351 | I29: =(C29/1.7*42+C26)*Arvind!$C$7*365-Arvind!$C$8-Arvind!$C$9 -> 27324195 | J29: =(C31-C30/2.8)*Arvind!$C$10*365-Arvind!$C$11-Arvind!$C$12 -> 203713.72 | K29: =H29+I29+J29 -> 38026259
A30: Eth. Feedstock Cost (CBOT Corn) | B30: 6.5667923 | C30: 2.4381317 | D30: 4.5257474
A31: Eth. Product Price (NY Harbor Ethanol) | B31: 2.6794149 | C31: 0.9926392 | D31: 1.841393

Sheet SA Income Statement
A1: For the Fiscal Period Ending | B1: 12 months Dec-31-2024 | C1: Weighted Simulation | D1: Normal | E1: Best | F1: Worst
A2: Currency | B2: USD | C2: USD | D2: USD | E2: USD | F2: USD
A4: Revenue | B4: 123974 | C4: 123974 | D4: 123974 | E4: 123974 | F4: 123974
A5: Other Revenue | B5: 0 | C5: 0 | D5: 0 | E5: 0 | F5: 0
A6: Total Revenue | B6: =B4+B5 -> 123974 | C6: =C4+C5 -> 123974 | D6: =D4+D5 -> 123974 | E6: =E4+E5 -> 123974 | F6: =F4+F5 -> 123974
A8: Cost Of Goods Sold | B8: 116440 | C8: 116440 | D8: 116440 | E8: 116440 | F8: 116440
A9: Gross Profit | B9: =B6-B8 -> 7534 | C9: =C6-C8 -> 7534 | D9: =D6-D8 -> 7534 | E9: =E6-E8 -> 7534 | F9: =F6-F8 -> 7534
A11: Selling General & Admin Exp. | B11: 871 | C11: 871 | D11: 871 | E11: 871 | F11: 871
A12: R & D Exp. | B12: - | C12: - | D12: - | E12: - | F12: -
A13: Depreciation & Amort. | B13: 2774 | C13: 2774 | D13: 2774 | E13: 2774 | F13: 2774
A14: Other Operating Expense/(Income) | B14: 44 | C14: 44 | D14: 44 | E14: 44 | F14: 44
A16: Other Operating Exp., Total | B16: 3689 | C16: 3689 | D16: 3689 | E16: 3689 | F16: 3689
A18: Operating Income | B18: 3845 | C18: ='Scenerio Analysis'!I25/1000000+Sneha!$O$14+$B$13+'Scenerio Analysis'!I24 -> 3152.4514 | D18: ='Scenerio Analysis'!K28/1000000+Sneha!$O$14+$B$13+'Scenerio Analysis'!K15 -> 3188.4023 | E18: ='Scenerio Analysis'!K27/1000000+Sneha!$O$14+$B$13+'Scenerio Analysis'!K14 -> 3321.7425 | F18: ='Scenerio Analysis'!K29/1000000+Sneha!$O$14+$B$13+'Scenerio Analysis'!K16 -> 2815.3892
A20: Interest Expense | B20: -556
A21: Interest and Invest. Income | B21: -
A22: Net Interest Exp. | B22: -556 | C22: -556 | D22: -556 | E22: -556 | F22: -556
A24: Other Non-Operating Inc. (Exp.) | B24: 409 | C24: 409 | D24: 409 | E24: 409 | F24: 409
A25: EBT Excl. Unusual Items | B25: =B18+B22+B24 -> 3698 | C25: =C18+C22+C24 -> 3005.4514 | D25: =D18+D22+D24 -> 3041.4023 | E25: =E18+E22+E24 -> 3174.7425 | F25: =F18+F22+F24 -> 2668.3892
A27: Restructuring Charges | B27: -
A28: Impairment of Goodwill | B28: -
A29: Other Unusual Items | B29: -
A30: EBT Incl. Unusual Items | B30: 3698 | C30: =C25 -> 3005.4514 | D30: =D25 -> 3041.4023 | E30: =E25 -> 3174.7425 | F30: =F25 -> 2668.3892
A32: Income Tax Expense | B32: 692 | C32: 692 | D32: 692 | E32: 692 | F32: 692
A33: Earnings from Cont. Ops. | B33: 3006 | C33: =C30-C32 -> 2313.4514 | D33: =D30-D32 -> 2349.4023 | E33: =E30-E32 -> 2482.7425 | F33: =F30-F32 -> 1976.3892
A35: Earnings of Discontinued Ops. | B35: -
A36: Extraord. Item & Account. Change | B36: -
A37: Net Income to Company | B37: 3006 | C37: =C33 -> 2313.4514 | D37: =D33 -> 2349.4023 | E37: =E33 -> 2482.7425 | F37: =F33 -> 1976.3892
A39: Minority Int. in Earnings | B39: -236 | C39: -236 | D39: -236 | E39: -236 | F39: -236
A40: Net Income | B40: 2770 | C40: =C37+C39 -> 2077.4514 | D40: =D37+D39 -> 2113.4023 | E40: =E37+E39 -> 2246.7425 | F40: =F37+F39 -> 1740.3892
A42: Pref. Dividends and Other Adj. | B42: 8 | C42: 8 | D42: 8 | E42: 8 | F42: 8
A44: NI to Common Incl Extra Items | B44: 2762 | C44: =C40-C42 -> 2069.4514 | D44: =D40-D42 -> 2105.4023 | E44: =E40-E42 -> 2238.7425 | F44: =F40-F42 -> 1732.3892
A45: NI to Common Excl. Extra Items | B45: 2762 | C45: =C40-C42 -> 2069.4514 | D45: =D40-D42 -> 2105.4023 | E45: =E40-E42 -> 2238.7425 | F45: =F40-F42 -> 1732.3892

Sheet SA Balance sheet
A1: Balance Sheet as of: Dec-31-2024 | B1: As Reported | D1: As Weighted Simulation | E1: Normal | F1: Best | G1: Worst
A2: Currency | B2: USD | D2: USD | E2: USD | F2: USD | G2: USD
A3: ASSETS
A4: Cash Flow from Operations (CFO) | D4: ='Scenerio Analysis'!I25/1000000+'Scenerio Analysis'!I24-Sneha!$O$14+'SA Income Statement'!C18 -> 3251.1393 | E4: ='Scenerio Analysis'!K28/1000000-Sneha!$O$14+'SA Income Statement'!D18+'Scenerio Analysis'!K15 -> 3323.0412 | F4: ='Scenerio Analysis'!K27/1000000-Sneha!$O$14+'SA Income Statement'!E18+'Scenerio Analysis'!K14 -> 3589.7216 | G4: ='Scenerio Analysis'!K29/1000000-Sneha!$O$14+'SA Income Statement'!F18+'Scenerio Analysis'!K16 -> 2577.0149
A5: Cash And Equivalents | B5: 4657
A6: Total Cash & ST Investments | B6: 4657 | D6: =D4 -> 3251.1393 | E6: =E4 -> 3323.0412 | F6: =F4 -> 3589.7216 | G6: =G4 -> 2577.0149
A8: Accounts Receivable | B8: 9731 | D8: 9731 | E8: 9731 | F8: 9731 | G8: 9731
A9: Other Receivables | B9: 977 | D9: 977 | E9: 977 | F9: 977 | G9: 977
A10: Total Receivables | B10: 10708 | D10: 10708 | E10: 10708 | F10: 10708 | G10: 10708
A12: Inventory | B12: 7761 | D12: ='Scenerio Analysis'!I23 -> 7516.9447 | E12: ='Scenerio Analysis'!H20 -> 7647.592 | F12: ='Scenerio Analysis'!H19 -> 7966.3516 | G12: ='Scenerio Analysis'!H21 -> 6457.8501
A13: Prepaid Exp. | B13: 611 | D13: 611 | E13: 611 | F13: 611 | G13: 611
A14: Other Current Assets | B14: -
A15: Total Current Assets | B15: 23737 | D15: =D6+D10+D12+D13+D14 -> 22087.084 | E15: =E6+E10+E12+E13+E14 -> 22289.633 | F15: =F6+F10+F12+F13+F14 -> 22875.073 | G15: =G6+G10+G12+G13+G14 -> 20353.865
A17: Gross Property, Plant & Equipment | B17: 53466 | D17: 53466 | E17: 53466 | F17: 53466 | G17: 53466
A18: Accumulated Depreciation | B18: -23054 | D18: -23054 | E18: -23054 | F18: -23054 | G18: -23054
A19: Net Property, Plant & Equipment | B19: 30412 | D19: 30412 | E19: 30412 | F19: 30412 | G19: 30412
A21: Long-term Investments | B21: 695 | D21: 695 | E21: 695 | F21: 695 | G21: 695
A22: Goodwill | B22: 260 | D22: 260 | E22: 260 | F22: 260 | G22: 260
A23: Other Intangibles | B23: 151 | D23: 151 | E23: 151 | F23: 151 | G23: 151
A24: Deferred Charges, LT | B24: 2689 | D24: 2689 | E24: 2689 | F24: 2689 | G24: 2689
A25: Other Long-Term Assets | B25: 2199 | D25: 2199 | E25: 2199 | F25: 2199 | G25: 2199
A26: Total Assets | B26: 60143 | D26: =D15+D19+SUM(D21:D25) -> 58493.084 | E26: =E15+E19+SUM(E21:E25) -> 58695.633 | F26: =F15+F19+SUM(F21:F25) -> 59281.073 | G26: =G15+G19+SUM(G21:G25) -> 56759.865
A28: LIABILITIES
A29: Accounts Payable | B29: 12092 | D29: 12092 | E29: 12092 | F29: 12092 | G29: 12092
A30: Accrued Exp. | B30: 2030 | D30: 2030 | E30: 2030 | F30: 2030 | G30: 2030
A31: Curr. Port. of LT Debt | B31: 499 | D31: 499 | E31: 499 | F31: 499 | G31: 499
A32: Curr. Port. of Leases | B32: 622 | D32: 622 | E32: 622 | F32: 622 | G32: 622
A33: Curr. Income Taxes Payable | B33: 170 | D33: 170 | E33: 170 | F33: 170 | G33: 170
A34: Unearned Revenue, Current | B34: 82 | D34: 82 | E34: 82 | F34: 82 | G34: 82
A35: Other Current Liabilities | B35: - | D35: - | E35: - | F35: - | G35: -
A36: Total Current Liabilities | B36: 15495 | D36: 15495 | E36: 15495 | F36: 15495 | G36: 15495
A38: Long-Term Debt | B38: 7586 | D38: 7586 | E38: 7586 | F38: 7586 | G38: 7586
A39: Long-Term Leases | B39: 2833 | D39: 2833 | E39: 2833 | F39: 2833 | G39: 2833
A40: Pension & Other Post-Retire. Benefits | B40: 423 | D40: 423 | E40: 423 | F40: 423 | G40: 423
A41: Def. Tax Liability, Non-Curr. | B41: 5267 | D41: 5267 | E41: 5267 | F41: 5267 | G41: 5267
A42: Other Non-Current Liabilities | B42: 1018 | D42: 1018 | E42: 1018 | F42: 1018 | G42: 1018
A43: Total Liabilities | B43: 32622 | D43: 32622 | E43: 32622 | F43: 32622 | G43: 32622
A45: Common Stock | B45: 7 | D45: 7 | E45: 7 | F45: 7 | G45: 7
A46: Additional Paid In Capital | B46: 6939 | D46: 6939 | E46: 6939 | F46: 6939 | G46: 6939
A47: Retained Earnings | B47: 47016 | D47: 47016 | E47: 47016 | F47: 47016 | G47: 47016
A48: Treasury Stock | B48: -28178 | D48: -28178 | E48: -28178 | F48: -28178 | G48: -28178
A49: Comprehensive Inc. and Other | B49: -1272 | D49: -1272 | E49: -1272 | F49: -1272 | G49: -1272
... A56: Total Liabilities And Equity | B56: 60143 | D56: 60143 | E56: 60143 | F56: 60143 | G56: 60143

Sheet Final Projections and Charts
B1: Arvind
B17: Krishna
B33: Ramita
B49: Sneha | C49: Compliance Cost

Sheet Cash Flow
A1: For the Fiscal Period Ending | B1: 3 months Q1 Mar-31-2025 | C1: 3 months Q2 Jun-30-2025 | D1: 3 months Q3 Sep-30-2025
A2: Currency | B2: USD | C2: USD | D2: USD
A4: Net Income | B4: -595 | C4: 714 | D4: 1095
A5: Depreciation & Amort. | B5: 691 | C5: 814 | D5: 636
A6: Depreciation & Amort., Total | B6: 691 | C6: 814 | D6: 636
A8: Asset Writedown & Restructuring Costs | B8: 1131 | C8: 0 | D8: 200
A9: Other Operating Activities | B9: -381 | C9: 14 | D9: -58
A10: Change in Acc. Receivable | B10: -457 | C10: 345 | D10: 731
A11: Change In Inventories | B11: 693 | C11: -275 | D11: 111
A12: Change in Acc. Payable | B12: -42 | C12: -571 | D12: -825
A13: Change in Inc. Taxes | B13: -3 | C13: -113 | D13: 235
A14: Change in Other Net Operating Assets | B14: -85 | C14: 8 | D14: -244
A15: Cash from Ops. | B15: 952 | C15: 936 | D15: 1881
A17: Capital Expenditure | B17: -249 | C17: -150 | D17: -177
A18: Cash Acquisitions | B18: - | C18: - | D18: -
A19: Divestitures | B19: - | C19: - | D19: -
A20: Invest. in Marketable & Equity Securt. | B20: 3 | C20: 0 | D20: 2
A21: Net (Inc.) Dec. in Loans Originated/Sold | B21: - | C21: - | D21: -
A22: Other Investing Activities | B22: -389 | C22: -262 | D22: -204
A23: Cash from Investing | B23: -635 | C23: -412 | D23: -379
A25: Short Term Debt Issued | B25: - | C25: - | D25: -
A26: Long-Term Debt Issued | B26: 2499 | C26: - | D26: -
A27: Total Debt Issued | B27: 2499 | C27: 2550 | D27: 950
A28: Short Term Debt Repaid | B28: - | C28: - | D28: -
A29: Long-Term Debt Repaid | B29: -2116 | C29: - | D29: -
A30: Total Debt Repaid | B30: -2116 | C30: -2774 | D30: -1023
A32: Repurchase of Common Stock | B32: -274 | C32: -366 | D32: -922
A34: Common Dividends Paid | B34: -356 | C34: -354 | D34: -351
A35: Total Dividends Paid | B35: -356 | C35: -354 | D35: -351
A37: Special Dividend Paid | B37: - | C37: - | D37: -
A38: Other Financing Activities | B38: -135 | C38: 95 | D38: 147
A39: Cash from Financing | B39: -382 | C39: -849 | D39: -1199
A41: Foreign Exchange Rate Adj. | B41: 43 | C41: 230 | D41: -74
A42: Net Change in Cash | B42: -22 | C42: -95 | D42: 229
A44: Supplemental Items
A45: Cash Interest Paid | B45: 84 | C45: 179 | D45: 99
A46: Cash Taxes Paid | B46: 35 | C46: 248 | D46: 115
A47: Levered Free Cash Flow | B47: 863.625 | C47: 657 | D47: 1487.25
A48: Unlevered Free Cash Flow | B48: 949.25 | C48: 745.125 | D48: 1574.125
A49: Change in Net Working Capital | B49: -351 | C49: 617 | D49: -67
A50: Net Debt Issued | B50: 383 | C50: -224 | D50: -73
A51: Filing Date | B51: 45771 | C51: 45953 | D51: 45953
A52: Restatement Type | B52: O | C52: NC | D52: O
A53: Calculation Type | B53: REP | C53: CFQ | D53: CFQ

Sheet Balance Sheet_1
A1: Currency | B1: USD | C1: USD | D1: USD | E1: Only Operations | F1: Only Regulatory
A2: ASSETS
A3: Cash And Equivalents | B3: 4634 | C3: 4537 | D3: 4764 | E3: 4537
A4: Total Cash & ST Investments | B4: 4634 | C4: 4537 | D4: 4764 | E4: =SUM(E3) -> 4537
A6: Accounts Receivable | B6: 11238 | C6: 10206 | D6: 9996 | E6: 10206
A7: Total Receivables | B7: 11238 | C7: 10206 | D7: 9996 | E7: =SUM(E6) -> 10206
A9: Inventory | B9: 7119 | C9: 7538 | D9: 7394 | E9: =Krishna_V2!Q6 -> -30.770984
A10: Prepaid Exp. | B10: 599 | C10: 656 | D10: 1013 | E10: 656
A11: Other Current Assets | B11: - | C11: 867 | D11: 337 | E11: 867
A12: Total Current Assets | B12: 23590 | C12: 23804 | D12: 23504 | E12: =SUM(E9:E11,E7,E4) -> 16235.229
A14: Gross Property, Plant & Equipment | B14: 49293 | C14: 49701 | D14: 49663 | E14: 49701
A15: Accumulated Depreciation | B15: -20744 | C15: -21465 | D15: -21922 | E15: -21465
A16: Net Property, Plant & Equipment | B16: 28549 | C16: 28236 | D16: 27741 | E16: =SUM(E14:E15) -> 28236
A18: Long-term Investments | B18: 691 | C18: 690 | D18: 687 | E18: 687
A19: Deferred Charges, LT | B19: 6347 | C19: 6703 | D19: 6683 | E19: 6683
A20: Other Long-Term Assets | B20: - | C20: - | D20: -
A21: Total Assets | B21: 59177 | C21: 59433 | D21: 58615 | E21: =SUM(E18:E19,E16,E12) -> 51841.229
A23: LIABILITIES
A24: Accounts Payable | B24: 11982 | C24: 11499 | D24: 10694 | E24: 11499
A25: Accrued Exp. | B25: 2395 | C25: 2676 | D25: 2789 | E25: 2676
A26: Curr. Port. of LT Debt | B26: 542 | C26: 382 | D26: 894 | E26: 382
A27: Curr. Income Taxes Payable | B27: 167 | C27: 57 | D27: 290 | E27: 57
A28: Unearned Revenue, Current | B28: 57 | C28: 59 | D28: 62 | E28: 59
A29: Other Current Liabilities | B29: - | C29: 4 | D29: - | E29: 4
A30: Total Current Liabilities | B30: 15143 | C30: 14677 | D30: 14729 | E30: =SUM(E24:E29) -> 14677
A32: Long-Term Debt | B32: 7986 | C32: 7988 | D32: 7472 | E32: 7988
A33: Long-Term Leases | B33: 2326 | C33: 2277 | D33: 2215 | E33: 2277
A34: Def. Tax Liability, Non-Curr. | B34: 4951 | C34: 5048 | D34: 5023 | E34: 5048
A35: Other Non-Current Liabilities | B35: 2456 | C35: 2496 | D35: 2430 | E35: 2496
A36: Total Liabilities | B36: 32862 | C36: 32486 | D36: 31869 | E36: =SUM(E32:E35,E30) -> 32486
A38: Common Stock | B38: 7 | C38: 7 | D38: 7 | E38: 7
A39: Additional Paid In Capital | B39: 6944 | C39: 6956 | D39: 6972 | E39: 6956
A40: Retained Earnings | B40: 46065 | C40: 46425 | D40: 47169 | E40: 46425
A41: Treasury Stock | B41: -28417 | C41: -28757 | D41: -29686 | E41: -28757
A42: Comprehensive Inc. and Other | B42: -1109 | C42: -553 | D42: -708 | E42: -553
A43: Total Common Equity | B43: 23490 | C43: 24078 | D43: 23754 | E43: =SUM(E38:E42) -> 24078
A45: Minority Interest | B45: 2825 | C45: 2869 | D45: 2992 | E45: 2869
A47: Total Equity | B47: 26315 | C47: 26947 | D47: 26746 | E47: =SUM(E45,E43) -> 26947
A49: Total Liabilities And Equity | B49: 59177 | C49: 59433 | D49: 58615 | E49: =SUM(E47,E36) -> 59433
A51: Supplemental Items
A52: Total Shares Out. on Filing Date | B52: 313.2 | C52: 310.7 | D52: 305 | E52: 310.7
A53: Total Shares Out. on Balance Sheet Date | B53: 313.2 | C53: 310.7 | D53: 305 | E53: 310.7
A54: Book Value/Share | B54: 75 | C54: 77.51 | D54: 77.88 | E54: 77.51
A55: Tangible Book Value | B55: 23490 | C55: 24078 | D55: 23754 | E55: 24078
A56: Tangible Book Value/Share | B56: 75 | C56: 77.51 | D56: 77.88 | E56: 77.51
A57: Total Debt | B57: 10854 | C57: 10647 | D57: 10581 | E57: 10647
A58: Net Debt | B58: 6220 | C58: 6110 | D58: 5817 | E58: 6110
A59: Total Minority Interest | B59: 2825 | C59: 2869 | D59: 2992 | E59: 2869
A60: Equity Method Investments | B60: 691 | C60: 690 | D60: 687 | E60: 690
A61: LIFO Reserve | B61: -3700 | C61: -3700 | D61: -3400 | E61: -3700
A62: Raw Materials Inventory | B62: 370 | C62: 391 | D62: 401 | E62: 391
A63: Finished Goods Inventory | B63: 6749 | C63: 7147 | D63: 6993 | E63: 7147
A64: Filing Date | B64: Apr-24-2025 | C64: Oct-23-2025 | D64: Oct-23-2025 | E64: Oct-23-2025
A65: Restatement Type | B65: O | C65: NC | D65: O | E65: NC
A66: Calculation Type | B66: REP | C66: RUP | D66: REP | E66: RUP
